Workbook

Sheet README
A1: Blockchain in Indian Government Administration: A Project-Level Dataset (2017–2026)
A2: Version 1.1.0 · created 2026-10-15 · licence CC BY 4.0 · authors: Santanu Mondal (ORCID 0009-0001-6243-1709) and T. Chithralekha, Pondicherry University
A3: DOI (all versions, always the latest): https://doi.org/10.5281/zenodo.23136332 · this version 1.1.0: https://doi.org/10.5281/zenodo.23415599
A5: Coded, source-linked inventory of blockchain / distributed-ledger initiatives by Indian public bodies (Union, all 28 States and 8 Union Territories, regulators, courts, statutory bodies), with dated lifecycle events, source-reported challenges (TOE-coded), evidence scores and a time series of the NIC blockchain platform. Structured as normalised tables with controlled vocabularies so new projects, events and snapshots can be added and validated.
A7: Sheets
A8: All projects – THE COMBINED TABLE: every project (Union, State, UT, district, municipal, PSU, regulator, court ...) in one row with level of government, body type, region, who built it, stage dates, NIC usage, challenges and evidence
A9: Summary – live counts by stage, tier, use-case and evidence score (formulas on the Projects sheet)
A10: Stage events – dated lifecycle events with sources (announced, pilot, live, scaled, latest update)
A11: Challenges – source-reported challenges, TOE-coded (see Vocabularies for TOE/DOI mapping)
A12: Sources / Project sources – all sources with type and evidence score, and which project each supports
A13: NIC snapshots – time series of the NIC blockchain platform by platform, application and department
A14: Jurisdictions – all 36 States/UTs with ISO 3166-2 and LGD codes, search results and live project counts
... A20: "Unclear" means no public update was found, not that a project failed.

Sheet Summary
A1: Summary (live formulas on the 'All projects' sheet; active records only)
A3: Stage | B3: Union | C3: State | D3: Union Territory | E3: District | F3: Municipal | G3: Total | H3: % of all
A4: Implemented | B4: =COUNTIFS('All projects'!$AB$2:$AB$119,$A4,'All projects'!$E$2:$E$119,B$3,'All projects'!$D$2:$D$119,"active") -> 19 | C4: =COUNTIFS('All projects'!$AB$2:$AB$119,$A4,'All projects'!$E$2:$E$119,C$3,'All projects'!$D$2:$D$119,"active") -> 23 | D4: =COUNTIFS('All projects'!$AB$2:$AB$119,$A4,'All projects'!$E$2:$E$119,D$3,'All projects'!$D$2:$D$119,"active") -> 5 | E4: =COUNTIFS('All projects'!$AB$2:$AB$119,$A4,'All projects'!$E$2:$E$119,E$3,'All projects'!$D$2:$D$119,"active") -> 2 | F4: =COUNTIFS('All projects'!$AB$2:$AB$119,$A4,'All projects'!$E$2:$E$119,F$3,'All projects'!$D$2:$D$119,"active") -> 1 | G4: =SUM(B4:F4) -> 50 | H4: =IF($G$10=0,0,G4/$G$10) -> 0.42735043
A5: In progress | B5: =COUNTIFS('All projects'!$AB$2:$AB$119,$A5,'All projects'!$E$2:$E$119,B$3,'All projects'!$D$2:$D$119,"active") -> 7 | C5: =COUNTIFS('All projects'!$AB$2:$AB$119,$A5,'All projects'!$E$2:$E$119,C$3,'All projects'!$D$2:$D$119,"active") -> 9 | D5: =COUNTIFS('All projects'!$AB$2:$AB$119,$A5,'All projects'!$E$2:$E$119,D$3,'All projects'!$D$2:$D$119,"active") -> 0 | E5: =COUNTIFS('All projects'!$AB$2:$AB$119,$A5,'All projects'!$E$2:$E$119,E$3,'All projects'!$D$2:$D$119,"active") -> 0 | F5: =COUNTIFS('All projects'!$AB$2:$AB$119,$A5,'All projects'!$E$2:$E$119,F$3,'All projects'!$D$2:$D$119,"active") -> 0 | G5: =SUM(B5:F5) -> 16 | H5: =IF($G$10=0,0,G5/$G$10) -> 0.13675214
A6: Proposed / Planned | B6: =COUNTIFS('All projects'!$AB$2:$AB$119,$A6,'All projects'!$E$2:$E$119,B$3,'All projects'!$D$2:$D$119,"active") -> 4 | C6: =COUNTIFS('All projects'!$AB$2:$AB$119,$A6,'All projects'!$E$2:$E$119,C$3,'All projects'!$D$2:$D$119,"active") -> 8 | D6: =COUNTIFS('All projects'!$AB$2:$AB$119,$A6,'All projects'!$E$2:$E$119,D$3,'All projects'!$D$2:$D$119,"active") -> 0 | E6: =COUNTIFS('All projects'!$AB$2:$AB$119,$A6,'All projects'!$E$2:$E$119,E$3,'All projects'!$D$2:$D$119,"active") -> 0 | F6: =COUNTIFS('All projects'!$AB$2:$AB$119,$A6,'All projects'!$E$2:$E$119,F$3,'All projects'!$D$2:$D$119,"active") -> 1 | G6: =SUM(B6:F6) -> 13 | H6: =IF($G$10=0,0,G6/$G$10) -> 0.11111111
A7: Pilot completed | B7: =COUNTIFS('All projects'!$AB$2:$AB$119,$A7,'All projects'!$E$2:$E$119,B$3,'All projects'!$D$2:$D$119,"active") -> 6 | C7: =COUNTIFS('All projects'!$AB$2:$AB$119,$A7,'All projects'!$E$2:$E$119,C$3,'All projects'!$D$2:$D$119,"active") -> 4 | D7: =COUNTIFS('All projects'!$AB$2:$AB$119,$A7,'All projects'!$E$2:$E$119,D$3,'All projects'!$D$2:$D$119,"active") -> 0 | E7: =COUNTIFS('All projects'!$AB$2:$AB$119,$A7,'All projects'!$E$2:$E$119,E$3,'All projects'!$D$2:$D$119,"active") -> 1 | F7: =COUNTIFS('All projects'!$AB$2:$AB$119,$A7,'All projects'!$E$2:$E$119,F$3,'All projects'!$D$2:$D$119,"active") -> 0 | G7: =SUM(B7:F7) -> 11 | H7: =IF($G$10=0,0,G7/$G$10) -> 0.094017094
A8: Unclear (no recent update) | B8: =COUNTIFS('All projects'!$AB$2:$AB$119,$A8,'All projects'!$E$2:$E$119,B$3,'All projects'!$D$2:$D$119,"active") -> 3 | C8: =COUNTIFS('All projects'!$AB$2:$AB$119,$A8,'All projects'!$E$2:$E$119,C$3,'All projects'!$D$2:$D$119,"active") -> 21 | D8: =COUNTIFS('All projects'!$AB$2:$AB$119,$A8,'All projects'!$E$2:$E$119,D$3,'All projects'!$D$2:$D$119,"active") -> 1 | E8: =COUNTIFS('All projects'!$AB$2:$AB$119,$A8,'All projects'!$E$2:$E$119,E$3,'All projects'!$D$2:$D$119,"active") -> 1 | F8: =COUNTIFS('All projects'!$AB$2:$AB$119,$A8,'All projects'!$E$2:$E$119,F$3,'All projects'!$D$2:$D$119,"active") -> 1 | G8: =SUM(B8:F8) -> 27 | H8: =IF($G$10=0,0,G8/$G$10) -> 0.23076923
A9: Discontinued | B9: =COUNTIFS('All projects'!$AB$2:$AB$119,$A9,'All projects'!$E$2:$E$119,B$3,'All projects'!$D$2:$D$119,"active") -> 0 | C9: =COUNTIFS('All projects'!$AB$2:$AB$119,$A9,'All projects'!$E$2:$E$119,C$3,'All projects'!$D$2:$D$119,"active") -> 0 | D9: =COUNTIFS('All projects'!$AB$2:$AB$119,$A9,'All projects'!$E$2:$E$119,D$3,'All projects'!$D$2:$D$119,"active") -> 0 | E9: =COUNTIFS('All projects'!$AB$2:$AB$119,$A9,'All projects'!$E$2:$E$119,E$3,'All projects'!$D$2:$D$119,"active") -> 0 | F9: =COUNTIFS('All projects'!$AB$2:$AB$119,$A9,'All projects'!$E$2:$E$119,F$3,'All projects'!$D$2:$D$119,"active") -> 0 | G9: =SUM(B9:F9) -> 0 | H9: =IF($G$10=0,0,G9/$G$10) -> 0
A10: Total | B10: =SUM(B4:B9) -> 39 | C10: =SUM(C4:C9) -> 65 | D10: =SUM(D4:D9) -> 6 | E10: =SUM(E4:E9) -> 4 | F10: =SUM(F4:F9) -> 3 | G10: =SUM(G4:G9) -> 117
A12: Pilot-to-production rate = Implemented ÷ (Implemented + Pilot completed + Unclear) | B12: =IFERROR(G4/(G4+G7+G8),0) -> 0.56818182
A13: Share backed by an official source (evidence score 4–5) | B13: =COUNTIFS('All projects'!$AX$2:$AX$119,">=4",'All projects'!$D$2:$D$119,"active")/$G$10 -> 0.61538462
A14: Mean evidence score | B14: =AVERAGEIFS('All projects'!$AX$2:$AX$119,'All projects'!$D$2:$D$119,"active") -> 3.8547009
A16: Type of public body | B16: Implemented | C16: All | D16: Implemented %
A17: Ministry / department | B17: =COUNTIFS('All projects'!$F$2:$F$119,$A17,'All projects'!$AB$2:$AB$119,"Implemented",'All projects'!$D$2:$D$119,"active") -> 24 | C17: =COUNTIFS('All projects'!$F$2:$F$119,$A17,'All projects'!$D$2:$D$119,"active") -> 50 | D17: =IF(C17=0,"",B17/C17) -> 0.48
A18: Government (whole of government) | B18: =COUNTIFS('All projects'!$F$2:$F$119,$A18,'All projects'!$AB$2:$AB$119,"Implemented",'All projects'!$D$2:$D$119,"active") -> 0 | C18: =COUNTIFS('All projects'!$F$2:$F$119,$A18,'All projects'!$D$2:$D$119,"active") -> 4 | D18: =IF(C18=0,"",B18/C18) -> 0
A19: IT / e-governance agency | B19: =COUNTIFS('All projects'!$F$2:$F$119,$A19,'All projects'!$AB$2:$AB$119,"Implemented",'All projects'!$D$2:$D$119,"active") -> 7 | C19: =COUNTIFS('All projects'!$F$2:$F$119,$A19,'All projects'!$D$2:$D$119,"active") -> 13 | D19: =IF(C19=0,"",B19/C19) -> 0.53846154
A20: Policy / planning body | B20: =COUNTIFS('All projects'!$F$2:$F$119,$A20,'All projects'!$AB$2:$AB$119,"Implemented",'All projects'!$D$2:$D$119,"active") -> 0 | C20: =COUNTIFS('All projects'!$F$2:$F$119,$A20,'All projects'!$D$2:$D$119,"active") -> 5 | D20: =IF(C20=0,"",B20/C20) -> 0
A21: PSU / state-owned company | B21: =COUNTIFS('All projects'!$F$2:$F$119,$A21,'All projects'!$AB$2:$AB$119,"Implemented",'All projects'!$D$2:$D$119,"active") -> 2 | C21: =COUNTIFS('All projects'!$F$2:$F$119,$A21,'All projects'!$D$2:$D$119,"active") -> 6 | D21: =IF(C21=0,"",B21/C21) -> 0.33333333
A22: Regulator / central bank | B22: =COUNTIFS('All projects'!$F$2:$F$119,$A22,'All projects'!$AB$2:$AB$119,"Implemented",'All projects'!$D$2:$D$119,"active") -> 2 | C22: =COUNTIFS('All projects'!$F$2:$F$119,$A22,'All projects'!$D$2:$D$119,"active") -> 7 | D22: =IF(C22=0,"",B22/C22) -> 0.28571429
A23: Court / judiciary | B23: =COUNTIFS('All projects'!$F$2:$F$119,$A23,'All projects'!$AB$2:$AB$119,"Implemented",'All projects'!$D$2:$D$119,"active") -> 2 | C23: =COUNTIFS('All projects'!$F$2:$F$119,$A23,'All projects'!$D$2:$D$119,"active") -> 4 | D23: =IF(C23=0,"",B23/C23) -> 0.5
A24: Election commission | B24: =COUNTIFS('All projects'!$F$2:$F$119,$A24,'All projects'!$AB$2:$AB$119,"Implemented",'All projects'!$D$2:$D$119,"active") -> 0 | C24: =COUNTIFS('All projects'!$F$2:$F$119,$A24,'All projects'!$D$2:$D$119,"active") -> 3 | D24: =IF(C24=0,"",B24/C24) -> 0
A25: Statutory board / authority | B25: =COUNTIFS('All projects'!$F$2:$F$119,$A25,'All projects'!$AB$2:$AB$119,"Implemented",'All projects'!$D$2:$D$119,"active") -> 5 | C25: =COUNTIFS('All projects'!$F$2:$F$119,$A25,'All projects'!$D$2:$D$119,"active") -> 11 | D25: =IF(C25=0,"",B25/C25) -> 0.45454545
A26: University / research institute | B26: =COUNTIFS('All projects'!$F$2:$F$119,$A26,'All projects'!$AB$2:$AB$119,"Implemented",'All projects'!$D$2:$D$119,"active") -> 4 | C26: =COUNTIFS('All projects'!$F$2:$F$119,$A26,'All projects'!$D$2:$D$119,"active") -> 6 | D26: =IF(C26=0,"",B26/C26) -> 0.66666667
A27: Society / foundation | B27: =COUNTIFS('All projects'!$F$2:$F$119,$A27,'All projects'!$AB$2:$AB$119,"Implemented",'All projects'!$D$2:$D$119,"active") -> 1 | C27: =COUNTIFS('All projects'!$F$2:$F$119,$A27,'All projects'!$D$2:$D$119,"active") -> 1 | D27: =IF(C27=0,"",B27/C27) -> 1
A28: District administration | B28: =COUNTIFS('All projects'!$F$2:$F$119,$A28,'All projects'!$AB$2:$AB$119,"Implemented",'All projects'!$D$2:$D$119,"active") -> 2 | C28: =COUNTIFS('All projects'!$F$2:$F$119,$A28,'All projects'!$D$2:$D$119,"active") -> 4 | D28: =IF(C28=0,"",B28/C28) -> 0.5
A29: Municipal body | B29: =COUNTIFS('All projects'!$F$2:$F$119,$A29,'All projects'!$AB$2:$AB$119,"Implemented",'All projects'!$D$2:$D$119,"active") -> 1 | C29: =COUNTIFS('All projects'!$F$2:$F$119,$A29,'All projects'!$D$2:$D$119,"active") -> 3 | D29: =IF(C29=0,"",B29/C29) -> 0.33333333
A31: Built by | B31: Implemented | C31: All | D31: Implemented %
A32: Government IT (NIC / C-DAC / NeGD) | B32: =COUNTIFS('All projects'!$Z$2:$Z$119,$A32,'All projects'!$AB$2:$AB$119,"Implemented",'All projects'!$D$2:$D$119,"active") -> 31 | C32: =COUNTIFS('All projects'!$Z$2:$Z$119,$A32,'All projects'!$D$2:$D$119,"active") -> 43 | D32: =IF(C32=0,"",B32/C32) -> 0.72093023
A33: State IT agency (in-house) | B33: =COUNTIFS('All projects'!$Z$2:$Z$119,$A33,'All projects'!$AB$2:$AB$119,"Implemented",'All projects'!$D$2:$D$119,"active") -> 1 | C33: =COUNTIFS('All projects'!$Z$2:$Z$119,$A33,'All projects'!$D$2:$D$119,"active") -> 5 | D33: =IF(C33=0,"",B33/C33) -> 0.2
A34: Private technology vendor | B34: =COUNTIFS('All projects'!$Z$2:$Z$119,$A34,'All projects'!$AB$2:$AB$119,"Implemented",'All projects'!$D$2:$D$119,"active") -> 9 | C34: =COUNTIFS('All projects'!$Z$2:$Z$119,$A34,'All projects'!$D$2:$D$119,"active") -> 30 | D34: =IF(C34=0,"",B34/C34) -> 0.3
A35: Academic / research partner | B35: =COUNTIFS('All projects'!$Z$2:$Z$119,$A35,'All projects'!$AB$2:$AB$119,"Implemented",'All projects'!$D$2:$D$119,"active") -> 3 | C35: =COUNTIFS('All projects'!$Z$2:$Z$119,$A35,'All projects'!$D$2:$D$119,"active") -> 8 | D35: =IF(C35=0,"",B35/C35) -> 0.375
A36: Banks, depositories or telecom operators | B36: =COUNTIFS('All projects'!$Z$2:$Z$119,$A36,'All projects'!$AB$2:$AB$119,"Implemented",'All projects'!$D$2:$D$119,"active") -> 2 | C36: =COUNTIFS('All projects'!$Z$2:$Z$119,$A36,'All projects'!$D$2:$D$119,"active") -> 6 | D36: =IF(C36=0,"",B36/C36) -> 0.33333333
A37: Government–industry consortium | B37: =COUNTIFS('All projects'!$Z$2:$Z$119,$A37,'All projects'!$AB$2:$AB$119,"Implemented",'All projects'!$D$2:$D$119,"active") -> 3 | C37: =COUNTIFS('All projects'!$Z$2:$Z$119,$A37,'All projects'!$D$2:$D$119,"active") -> 4 | D37: =IF(C37=0,"",B37/C37) -> 0.75
A38: International organisation | B38: =COUNTIFS('All projects'!$Z$2:$Z$119,$A38,'All projects'!$AB$2:$AB$119,"Implemented",'All projects'!$D$2:$D$119,"active") -> 0 | C38: =COUNTIFS('All projects'!$Z$2:$Z$119,$A38,'All projects'!$D$2:$D$119,"active") -> 2 | D38: =IF(C38=0,"",B38/C38) -> 0
A39: Not applicable (policy or judgment) | B39: =COUNTIFS('All projects'!$Z$2:$Z$119,$A39,'All projects'!$AB$2:$AB$119,"Implemented",'All projects'!$D$2:$D$119,"active") -> 0 | C39: =COUNTIFS('All projects'!$Z$2:$Z$119,$A39,'All projects'!$D$2:$D$119,"active") -> 2 | D39: =IF(C39=0,"",B39/C39) -> 0
A40: Not disclosed | B40: =COUNTIFS('All projects'!$Z$2:$Z$119,$A40,'All projects'!$AB$2:$AB$119,"Implemented",'All projects'!$D$2:$D$119,"active") -> 1 | C40: =COUNTIFS('All projects'!$Z$2:$Z$119,$A40,'All projects'!$D$2:$D$119,"active") -> 17 | D40: =IF(C40=0,"",B40/C40) -> 0.058823529
A42: Region | B42: Implemented | C42: All | D42: Implemented %
A43: Northern | B43: =COUNTIFS('All projects'!$M$2:$M$119,$A43,'All projects'!$AB$2:$AB$119,"Implemented",'All projects'!$D$2:$D$119,"active") -> 4 | C43: =COUNTIFS('All projects'!$M$2:$M$119,$A43,'All projects'!$D$2:$D$119,"active") -> 10 | D43: =IF(C43=0,"",B43/C43) -> 0.4
A44: Central | B44: =COUNTIFS('All projects'!$M$2:$M$119,$A44,'All projects'!$AB$2:$AB$119,"Implemented",'All projects'!$D$2:$D$119,"active") -> 4 | C44: =COUNTIFS('All projects'!$M$2:$M$119,$A44,'All projects'!$D$2:$D$119,"active") -> 11 | D44: =IF(C44=0,"",B44/C44) -> 0.36363636
A45: Eastern | B45: =COUNTIFS('All projects'!$M$2:$M$119,$A45,'All projects'!$AB$2:$AB$119,"Implemented",'All projects'!$D$2:$D$119,"active") -> 2 | C45: =COUNTIFS('All projects'!$M$2:$M$119,$A45,'All projects'!$D$2:$D$119,"active") -> 9 | D45: =IF(C45=0,"",B45/C45) -> 0.22222222
A46: Western | B46: =COUNTIFS('All projects'!$M$2:$M$119,$A46,'All projects'!$AB$2:$AB$119,"Implemented",'All projects'!$D$2:$D$119,"active") -> 5 | C46: =COUNTIFS('All projects'!$M$2:$M$119,$A46,'All projects'!$D$2:$D$119,"active") -> 14 | D46: =IF(C46=0,"",B46/C46) -> 0.35714286
A47: Southern | B47: =COUNTIFS('All projects'!$M$2:$M$119,$A47,'All projects'!$AB$2:$AB$119,"Implemented",'All projects'!$D$2:$D$119,"active") -> 14 | C47: =COUNTIFS('All projects'!$M$2:$M$119,$A47,'All projects'!$D$2:$D$119,"active") -> 29 | D47: =IF(C47=0,"",B47/C47) -> 0.48275862
A48: North-Eastern | B48: =COUNTIFS('All projects'!$M$2:$M$119,$A48,'All projects'!$AB$2:$AB$119,"Implemented",'All projects'!$D$2:$D$119,"active") -> 2 | C48: =COUNTIFS('All projects'!$M$2:$M$119,$A48,'All projects'!$D$2:$D$119,"active") -> 5 | D48: =IF(C48=0,"",B48/C48) -> 0.4
A49: Island UTs | B49: =COUNTIFS('All projects'!$M$2:$M$119,$A49,'All projects'!$AB$2:$AB$119,"Implemented",'All projects'!$D$2:$D$119,"active") -> 0 | C49: =COUNTIFS('All projects'!$M$2:$M$119,$A49,'All projects'!$D$2:$D$119,"active") -> 0 | D49: =IF(C49=0,"",B49/C49)
A50: National | B50: =COUNTIFS('All projects'!$M$2:$M$119,$A50,'All projects'!$AB$2:$AB$119,"Implemented",'All projects'!$D$2:$D$119,"active") -> 19 | C50: =COUNTIFS('All projects'!$M$2:$M$119,$A50,'All projects'!$D$2:$D$119,"active") -> 39 | D50: =IF(C50=0,"",B50/C50) -> 0.48717949
A52: Use-case | B52: Implemented | C52: All | D52: Implemented %
A53: Authentication & anti-fraud | B53: =COUNTIFS('All projects'!$R$2:$R$119,$A53,'All projects'!$AB$2:$AB$119,"Implemented",'All projects'!$D$2:$D$119,"active") -> 3 | C53: =COUNTIFS('All projects'!$R$2:$R$119,$A53,'All projects'!$D$2:$D$119,"active") -> 3 | D53: =IF(C53=0,"",B53/C53) -> 1
A54: CBDC / digital payments | B54: =COUNTIFS('All projects'!$R$2:$R$119,$A54,'All projects'!$AB$2:$AB$119,"Implemented",'All projects'!$D$2:$D$119,"active") -> 0 | C54: =COUNTIFS('All projects'!$R$2:$R$119,$A54,'All projects'!$D$2:$D$119,"active") -> 1 | D54: =IF(C54=0,"",B54/C54) -> 0
A55: Certificates & identity | B55: =COUNTIFS('All projects'!$R$2:$R$119,$A55,'All projects'!$AB$2:$AB$119,"Implemented",'All projects'!$D$2:$D$119,"active") -> 20 | C55: =COUNTIFS('All projects'!$R$2:$R$119,$A55,'All projects'!$D$2:$D$119,"active") -> 28 | D55: =IF(C55=0,"",B55/C55) -> 0.71428571
A56: E-voting | B56: =COUNTIFS('All projects'!$R$2:$R$119,$A56,'All projects'!$AB$2:$AB$119,"Implemented",'All projects'!$D$2:$D$119,"active") -> 0 | C56: =COUNTIFS('All projects'!$R$2:$R$119,$A56,'All projects'!$D$2:$D$119,"active") -> 3 | D56: =IF(C56=0,"",B56/C56) -> 0
A57: Energy trading | B57: =COUNTIFS('All projects'!$R$2:$R$119,$A57,'All projects'!$AB$2:$AB$119,"Implemented",'All projects'!$D$2:$D$119,"active") -> 0 | C57: =COUNTIFS('All projects'!$R$2:$R$119,$A57,'All projects'!$D$2:$D$119,"active") -> 2 | D57: =IF(C57=0,"",B57/C57) -> 0
A58: Financial infrastructure | B58: =COUNTIFS('All projects'!$R$2:$R$119,$A58,'All projects'!$AB$2:$AB$119,"Implemented",'All projects'!$D$2:$D$119,"active") -> 1 | C58: =COUNTIFS('All projects'!$R$2:$R$119,$A58,'All projects'!$D$2:$D$119,"active") -> 5 | D58: =IF(C58=0,"",B58/C58) -> 0.2
A59: Land / property registry | B59: =COUNTIFS('All projects'!$R$2:$R$119,$A59,'All projects'!$AB$2:$AB$119,"Implemented",'All projects'!$D$2:$D$119,"active") -> 5 | C59: =COUNTIFS('All projects'!$R$2:$R$119,$A59,'All projects'!$D$2:$D$119,"active") -> 22 | D59: =IF(C59=0,"",B59/C59) -> 0.22727273
A60: Platform / ecosystem | B60: =COUNTIFS('All projects'!$R$2:$R$119,$A60,'All projects'!$AB$2:$AB$119,"Implemented",'All projects'!$D$2:$D$119,"active") -> 8 | C60: =COUNTIFS('All projects'!$R$2:$R$119,$A60,'All projects'!$D$2:$D$119,"active") -> 19 | D60: =IF(C60=0,"",B60/C60) -> 0.42105263
A61: Public procurement | B61: =COUNTIFS('All projects'!$R$2:$R$119,$A61,'All projects'!$AB$2:$AB$119,"Implemented",'All projects'!$D$2:$D$119,"active") -> 0 | C61: =COUNTIFS('All projects'!$R$2:$R$119,$A61,'All projects'!$D$2:$D$119,"active") -> 1 | D61: =IF(C61=0,"",B61/C61) -> 0
A62: Records & audit trail | B62: =COUNTIFS('All projects'!$R$2:$R$119,$A62,'All projects'!$AB$2:$AB$119,"Implemented",'All projects'!$D$2:$D$119,"active") -> 5 | C62: =COUNTIFS('All projects'!$R$2:$R$119,$A62,'All projects'!$D$2:$D$119,"active") -> 11 | D62: =IF(C62=0,"",B62/C62) -> 0.45454545
A63: Supply-chain traceability | B63: =COUNTIFS('All projects'!$R$2:$R$119,$A63,'All projects'!$AB$2:$AB$119,"Implemented",'All projects'!$D$2:$D$119,"active") -> 4 | C63: =COUNTIFS('All projects'!$R$2:$R$119,$A63,'All projects'!$D$2:$D$119,"active") -> 12 | D63: =IF(C63=0,"",B63/C63) -> 0.33333333
A64: Tokenisation / NFTs | B64: =COUNTIFS('All projects'!$R$2:$R$119,$A64,'All projects'!$AB$2:$AB$119,"Implemented",'All projects'!$D$2:$D$119,"active") -> 2 | C64: =COUNTIFS('All projects'!$R$2:$R$119,$A64,'All projects'!$D$2:$D$119,"active") -> 4 | D64: =IF(C64=0,"",B64/C64) -> 0.5
A65: Welfare delivery | B65: =COUNTIFS('All projects'!$R$2:$R$119,$A65,'All projects'!$AB$2:$AB$119,"Implemented",'All projects'!$D$2:$D$119,"active") -> 2 | C65: =COUNTIFS('All projects'!$R$2:$R$119,$A65,'All projects'!$D$2:$D$119,"active") -> 6 | D65: =IF(C65=0,"",B65/C65) -> 0.33333333
A67: Evidence score | B67: Projects
A68: 5 | B68: =COUNTIFS('All projects'!$AX$2:$AX$119,$A68,'All projects'!$D$2:$D$119,"active") -> 42
A69: 4 | B69: =COUNTIFS('All projects'!$AX$2:$AX$119,$A69,'All projects'!$D$2:$D$119,"active") -> 30
A70: 3 | B70: =COUNTIFS('All projects'!$AX$2:$AX$119,$A70,'All projects'!$D$2:$D$119,"active") -> 35
A71: 2 | B71: =COUNTIFS('All projects'!$AX$2:$AX$119,$A71,'All projects'!$D$2:$D$119,"active") -> 6
A72: 1 | B72: =COUNTIFS('All projects'!$AX$2:$AX$119,$A72,'All projects'!$D$2:$D$119,"active") -> 4

Sheet All projects
A1: project_id | B1: project_name | C1: description | D1: record_status | E1: government_level | F1: body_category | G1: implementing_body | H1: parent_ministry_or_state | I1: dataset_group | J1: jurisdiction_id | K1: state_ut | L1: jurisdiction_type | M1: region | N1: lgd_code | O1: domain | P1: cofog_division | Q1: cofog_label | R1: use_case | S1: problem | T1: service_type | U1: platform_reported | V1: platform | W1: platform_family | X1: chain_type | Y1: tech_partner | Z1: implementation_model | AA1: is_nic_chain | AB1: stage | AC1: stage_generic | AD1: status_text | AE1: status_as_of | AF1: start_year | AG1: date_announced | AH1: date_pilot_started | AI1: date_pilot_completed | AJ1: date_live | AK1: date_scaled | AL1: date_discontinued | AM1: date_latest_update | AN1: months_to_live | AO1: years_since_update | AP1: scale_text | AQ1: scale_tier | AR1: nic_documents_latest | AS1: nic_verifications_latest | AT1: nic_snapshot_date | AU1: challenge_codes | AV1: toe_dimensions | AW1: n_challenges | AX1: evidence_score | AY1: evidence_label | AZ1: n_sources | BA1: n_official_sources | BB1: primary_source_url | BC1: verify_note | BD1: related_projects | BE1: last_reviewed
A2: C01 | B2: National Blockchain Framework – Vishvasya Blockchain Stack (BaaS) | C2: Shared permissioned blockchain service for all departments; nodes at NIC data centres Bhubaneswar, Pune, Hyderabad | D2: active | E2: Union | F2: IT / e-governance agency | G2: MeitY / NIC | H2: Ministry of Electronics & IT | I2: Union government | J2: IN | K2: Union / national | L2: National | M2: National | O2: Platform & Infrastructure | P2: 1 | Q2: General public services | R2: Platform / ecosystem | S2: Capacity & shared infrastructure | T2: G2G | U2: Permissioned (NIC) | V2: NIC chains (Hyperledger-based) | W2: Hyperledger family | X2: Permissioned | Y2: NIC, C-DAC | Z2: Government IT (NIC / C-DAC / NeGD) | AA2: Yes | AB2: Implemented | AC2: Live | AD2: Live. NIC dashboard: 6 products, 12 central orgs/states, 22 departments, 4 PoCs | AE2: 2026-10-03 | AF2: 2021 | AG2: 2021-03 | AJ2: 2024-09-04 | AM2: 2026-10-03 | AN2: 42 | AO2: 0.0 | AP2: 11,25,46,175 documents; 47,13,59,890 verifications; outlay ₹64.76 crore | AQ2: Large (≥10 lakh) | AU2: O2;O3 | AV2: Organisation | AW2: 2 | AX2: 5 | AY2: 5 – Official source with live/current data | AZ2: 7 | BA2: 4 | BB2: https://blockchain.gov.in/Home/Home | BE2: 2026-10-15
A3: C02 | B3: NBFLite – blockchain sandbox | C3: Sandbox with smart-contract templates for startups, academia, students | D3: active | E3: Union | F3: Ministry / department | G3: MeitY | H3: Ministry of Electronics & IT | I3: Union government | J3: IN | K3: Union / national | L3: National | M3: National | O3: Platform & Infrastructure | P3: 1 | Q3: General public services | R3: Platform / ecosystem | S3: Capacity & shared infrastructure | T3: G2B | U3: Permissioned | V3: NIC chains (Hyperledger-based) | W3: Hyperledger family | X3: Permissioned | Y3: NIC | Z3: Government IT (NIC / C-DAC / NeGD) | AA3: Yes | AB3: Implemented | AC3: Live | AD3: Live | AE3: 2025-10-24 | AF3: 2024 | AJ3: 2024-09-04 | AM3: 2025-10-24 | AO3: 1.0 | AQ3: Not reported | AW3: 0 | AX3: 5 | AY3: 5 – Official source with live/current data | AZ3: 4 | BA3: 3 | BB3: https://www.pib.gov.in/PressReleasePage.aspx?PRID=2182023 | BE3: 2026-10-15
A4: C03 | B4: Praamaanik – mobile app verification | C4: Checks a mobile app's origin against blockchain records; verified via M-Kavach-2 app | D4: active | E4: Union | F4: Ministry / department | G4: MeitY | H4: Ministry of Electronics & IT | I4: Union government | J4: IN | K4: Union / national | L4: National | M4: National | O4: Telecom & Cyber | P4: 4 | Q4: Economic affairs | R4: Authentication & anti-fraud | S4: Fraud / spam / fake apps | T4: G2C | U4: Permissioned | V4: NIC chains (Hyperledger-based) | W4: Hyperledger family | X4: Permissioned | Y4: NIC; MPSEDC apps onboarded | Z4: Government IT (NIC / C-DAC / NeGD) | AA4: Yes | AB4: Implemented | AC4: Live | AD4: Live; 14 citizen apps of MPSEDC onboarded | AE4: 2026-03-27 | AF4: 2024 | AJ4: 2024-09-04 | AM4: 2026-03-27 | AO4: 0.6 | AP4: 14 apps | AQ4: Small (<10,000) | AW4: 0 | AX4: 5 | AY4: 5 – Official source with live/current data | AZ4: 5 | BA4: 4 | BB4: https://www.pib.gov.in/PressReleasePage.aspx?PRID=2246221&reg=3&lang=1 | BE4: 2026-10-15
A5: C04 | B5: Blockchain India Challenge / Startup Challenge (Blockchain & Web3) | C5: Stage-wise funding for startups building permissioned govt blockchain apps in 10 domains (e-procurement, supply chain, PDS, education, health, agriculture, power, IoT, land records, environment) | D5: active | E5: Union | F5: Ministry / department | G5: MeitY with C-DAC | H5: Ministry of Electronics & IT | I5: Union government | J5: IN | K5: Union / national | L5: National | M5: National | O5: Platform & Infrastructure | P5: 1 | Q5: General public services | R5: Platform / ecosystem | S5: Capacity & shared infrastructure | T5: G2B | U5: Permissioned (NBF) | V5: NIC chains (Hyperledger-based) | W5: Hyperledger family | X5: Permissioned | Y5: C-DAC, DPIIT | Z5: Government IT (NIC / C-DAC / NeGD) | AA5: Yes | AB5: In progress | AC5: In development | AD5: Call open; staged grants up to ₹50 lakh per team | AE5: 2026-03-27 | AF5: 2026 | AG5: 2026-02-23 | AM5: 2026-03-27 | AO5: 0.6 | AP5: Up to 40/30/20/10 teams by stage | AQ5: Not reported | AW5: 0 | AX5: 5 | AY5: 5 – Official source with live/current data | AZ5: 7 | BA5: 3 | BB5: https://www.pib.gov.in/PressReleasePage.aspx?PRID=2246221&reg=3&lang=1 | BE5: 2026-10-15
A6: C05 | B6: CoE in Blockchain Technology + Blockchain-as-a-Service | C6: Consultancy, training, PoCs; runs NIC chains and BaaS (hosting, smart contracts, security) for departments | D6: active | E6: Union | F6: IT / e-governance agency | G6: NIC – Centre of Excellence in Blockchain (Bengaluru) | H6: Ministry of Electronics & IT | I6: Union government | J6: IN | K6: Union / national | L6: National | M6: National | O6: Platform & Infrastructure | P6: 1 | Q6: General public services | R6: Platform / ecosystem | S6: Capacity & shared infrastructure | T6: G2G | U6: Hyperledger Fabric, Hyperledger Sawtooth, Ethereum | V6: Hyperledger Fabric | W6: Hyperledger family | X6: Permissioned | Y6: — | Z6: Government IT (NIC / C-DAC / NeGD) | AA6: No | AB6: Implemented | AC6: Live | AD6: Operational | AE6: 2026-10-03 | AF6: 2019 | AG6: 2020-01-17 | AJ6: 2020-01-18 | AK6: 2024-09-04 | AM6: 2026-10-03 | AN6: 0 | AO6: 0.0 | AP6: Growth: Jun 2024 8.08 crore docs (9 orgs, 19 depts) → Dec 2025 10.38 crore (10, 21) → Oct 2026 11.25 crore (12, 22) | AQ6: Large (≥10 lakh) | AU6: O1;O2;T2 | AV6: Organisation;Technology | AW6: 3 | AX6: 5 | AY6: 5 – Official source with live/current data | AZ6: 10 | BA6: 5 | BB6: https://blockchain.gov.in/Home/Home | BE6: 2026-10-15
A7: C06 | B7: Document Chain | C7: Store/verify caste, income, ration card, driving licence, birth & death certificates | D7: active | E7: Union | F7: IT / e-governance agency | G7: NIC | H7: Ministry of Electronics & IT | I7: Union government | J7: IN | K7: Union / national | L7: National | M7: National | O7: Certificates & Identity | P7: 1 | Q7: General public services | R7: Certificates & identity | S7: Forgery / fake documents | T7: G2C | U7: Permissioned (NIC) | V7: NIC chains (Hyperledger-based) | W7: Hyperledger family | X7: Permissioned | Y7: — | Z7: Government IT (NIC / C-DAC / NeGD) | AA7: Yes | AB7: Implemented | AC7: Live | AD7: Live | AE7: 2026-10-03 | AF7: 2020 | AJ7: 2024-04 | AM7: 2026-10-03 | AO7: 0.0 | AP7: 48,000+ documents | AQ7: Medium (10,000–10 lakh) | AW7: 0 | AX7: 5 | AY7: 5 – Official source with live/current data | AZ7: 7 | BA7: 5 | BB7: https://www.pib.gov.in/PressReleasePage.aspx?PRID=2182023 | BE7: 2026-10-15
A8: C07 | B8: Property Chain | C8: Records every property transaction; full history visible before purchase | D8: active | E8: Union | F8: IT / e-governance agency | G8: NIC | H8: Ministry of Electronics & IT | I8: Union government | J8: IN | K8: Union / national | L8: National | M8: National | O8: Land & Property | P8: 1 | Q8: General public services | R8: Land / property registry | S8: Land fraud & disputes | T8: G2C | U8: Permissioned (NIC) | V8: NIC chains (Hyperledger-based) | W8: Hyperledger family | X8: Permissioned | Y8: — | Z8: Government IT (NIC / C-DAC / NeGD) | AA8: Yes | AB8: Implemented | AC8: Live | AD8: Live | AE8: 2026-10-03 | AF8: 2020 | AJ8: 2025-10-21 | AM8: 2026-10-03 | AO8: 0.0 | AP8: 34 crore+ property documents (per PIB) | AQ8: Large (≥10 lakh) | AW8: 0 | AX8: 5 | AY8: 5 – Official source with live/current data | AZ8: 6 | BA8: 5 | BB8: https://www.pib.gov.in/PressReleasePage.aspx?PRID=2182023 | BC8: PIB gives 34 crore for both total and property – confirm | BE8: 2026-10-15
A9: C08 | B9: Judiciary Chain | C9: Supreme Court bail and judgment orders recorded; proposed uses: judicial deposits, FIR/charge-sheet transfer, e-summons | D9: active | E9: Union | F9: Court / judiciary | G9: NIC with Supreme Court of India | H9: Ministry of Law & Justice / Judiciary | I9: Union government | J9: IN | K9: Union / national | L9: National | M9: National | O9: Justice & Police | P9: 3 | Q9: Public order and safety | R9: Records & audit trail | S9: Tampering of records | T9: G2G | U9: Permissioned (NIC) | V9: NIC chains (Hyperledger-based) | W9: Hyperledger family | X9: Permissioned | Y9: — | Z9: Government IT (NIC / C-DAC / NeGD) | AA9: Yes | AB9: Implemented | AC9: Live | AD9: Live (Supreme Court) | AE9: 2026-10-14 | AF9: 2023 | AJ9: 2023-11-13 | AM9: 2026-10-14 | AO9: 0.0 | AP9: 447 documents; 987 verifications (NIC statistics, 2026-10-14) | AQ9: Small (<10,000) | AR9: 447 | AS9: 987 | AT9: 2026-10-14 | AW9: 0 | AX9: 5 | AY9: 5 – Official source with live/current data | AZ9: 6 | BA9: 4 | BB9: https://blockchain.gov.in/Home/Home | BE9: 2026-10-15
A10: C09 | B10: Inter-operable Criminal Justice System chain | C10: Links police, forensic and court records; live for High Court of Karnataka | D10: active | E10: Union | F10: Court / judiciary | G10: NIC – ICJS with High Court of Karnataka | H10: Ministry of Home Affairs / Judiciary | I10: Union government | J10: IN | K10: Union / national | L10: National | M10: National | O10: Justice & Police | P10: 3 | Q10: Public order and safety | R10: Records & audit trail | S10: Tampering of records | T10: G2G | U10: Permissioned (NIC) | V10: NIC chains (Hyperledger-based) | W10: Hyperledger family | X10: Permissioned | Y10: — | Z10: Government IT (NIC / C-DAC / NeGD) | AA10: Yes | AB10: Implemented | AC10: Live | AD10: Live; grew from 39,000 docs (Oct 2025) to 17.4 lakh | AE10: 2026-10-14 | AF10: 2022 | AJ10: 2025-10 | AM10: 2026-10-14 | AO10: 0.0 | AP10: 17,41,654 documents; 21,62,694 verifications (NIC statistics, 2026-10-14) | AQ10: Large (≥10 lakh) | AR10: 1741654 | AS10: 2162694 | AT10: 2026-10-14 | AW10: 0 | AX10: 5 | AY10: 5 – Official source with live/current data | AZ10: 4 | BA10: 4 | BB10: https://blockchain.gov.in/Home/Home | BE10: 2026-10-15
A11: C10 | B11: NIC PoCs: Assam land records, Blood Bank chain, GST Chain, PDS chain | C11: Blood bank: safe-blood and donor traceability; GST: running tax liability ledger; PDS: grain from MSP procurement to ration card | D11: active | E11: Union | F11: IT / e-governance agency | G11: MeitY / NIC | H11: Ministry of Electronics & IT | I11: Union government | J11: IN | K11: Union / national | L11: National | M11: National | O11: Platform & Infrastructure | P11: 1 | Q11: General public services | R11: Platform / ecosystem | S11: Capacity & shared infrastructure | T11: G2G | U11: Permissioned (NIC) | V11: NIC chains (Hyperledger-based) | W11: Hyperledger family | X11: Permissioned | Y11: NIC | Z11: Government IT (NIC / C-DAC / NeGD) | AA11: Yes | AB11: Proposed / Planned | AC11: Planned | AD11: Listed as PoCs on NIC dashboard | AE11: 2026-10-03 | AF11: 2023 | AG11: 2023 | AM11: 2026-10-03 | AO11: 0.0 | AP11: 4 PoCs | AQ11: Not reported | AW11: 0 | AX11: 5 | AY11: 5 – Official source with live/current data | AZ11: 7 | BA11: 6 | BB11: https://blockchain.gov.in/Home/Home | BE11: 2026-10-15
A12: C11 | B12: Legal Metrology approvals on NIC Document Chain | C12: Packaged commodity registration, weights & measures approvals, importer certificates | D12: active | E12: Union | F12: Ministry / department | G12: Dept of Consumer Affairs – Legal Metrology | H12: Ministry of Consumer Affairs, Food & PD | I12: Union government | J12: IN | K12: Union / national | L12: National | M12: National | O12: Certificates & Identity | P12: 1 | Q12: General public services | R12: Certificates & identity | S12: Forgery / fake documents | T12: G2B | U12: Permissioned (NIC) | V12: NIC chains (Hyperledger-based) | W12: Hyperledger family | X12: Permissioned | Y12: NIC | Z12: Government IT (NIC / C-DAC / NeGD) | AA12: Yes | AB12: Implemented | AC12: Live | AD12: Live | AE12: 2026-10-14 | AF12: 2023 | AJ12: 2023 | AM12: 2026-10-14 | AO12: 0.0 | AP12: 23,047 documents; 16 verifications (NIC statistics, 2026-10-14) | AQ12: Medium (10,000–10 lakh) | AR12: 23047 | AS12: 16 | AT12: 2026-10-14 | AW12: 0 | AX12: 5 | AY12: 5 – Official source with live/current data | AZ12: 4 | BA12: 2 | BB12: https://blockchain.gov.in/Home/Home | BE12: 2026-10-15
A13: C12 | B13: Skill documents on NIC Document Chain | C13: Rural skills (training) documents recorded for verification | D13: active | E13: Union | F13: Ministry / department | G13: Ministry of Rural Development – Rural Skills Division | H13: Ministry of Rural Development | I13: Union government | J13: IN | K13: Union / national | L13: National | M13: National | O13: Education & Skills | P13: 9 | Q13: Education | R13: Certificates & identity | S13: Forgery / fake documents | T13: G2C | U13: Permissioned (NIC) | V13: NIC chains (Hyperledger-based) | W13: Hyperledger family | X13: Permissioned | Y13: NIC | Z13: Government IT (NIC / C-DAC / NeGD) | AA13: Yes | AB13: Implemented | AC13: Live | AD13: Live (small scale) | AE13: 2026-10-14 | AJ13: 2026-10-03 | AM13: 2026-10-14 | AO13: 0.0 | AP13: 4,553 documents; 1,702 verifications (NIC statistics, 2026-10-14) | AQ13: Small (<10,000) | AR13: 4553 | AS13: 1702 | AT13: 2026-10-14 | AW13: 0 | AX13: 5 | AY13: 5 – Official source with live/current data | AZ13: 4 | BA13: 2 | BB13: https://blockchain.gov.in/Home/Home | BC13: Confirm which scheme (e.g. DDU-GKY) | BE13: 2026-10-15
A14: C13 | B14: CBDC-based DBT for food subsidy (PMGKAY) | C14: Programmable e₹ in beneficiary wallets, redeemable for wheat/rice at authorised shops | D14: active | E14: Union | F14: Ministry / department | G14: Dept of Food & Public Distribution with RBI, PFMS, Canara Bank | H14: Ministry of Consumer Affairs, Food & PD | I14: Union government | J14: IN | K14: Union / national | L14: National | M14: National | O14: Welfare & Subsidy | P14: 10 | Q14: Social protection | R14: Welfare delivery | S14: Leakage / beneficiary fraud | T14: G2C | U14: CBDC (e₹) – DLT use not confirmed by RBI | V14: RBI CBDC infrastructure | W14: CBDC infrastructure | X14: CBDC (DLT not confirmed) | Y14: RBI, Canara Bank | Z14: Banks, depositories or telecom operators | AA14: No | AB14: In progress | AC14: In development | AD14: Rolling out; full coverage of eligible beneficiaries in Chandigarh & DNH | AE14: 2026-08-14 | AF14: 2026 | AH14: 2026-02 | AJ14: 2026-08-14 | AM14: 2026-08-14 | AN14: 6 | AO14: 0.2 | AP14: Target: 80 crore PDS beneficiaries nationally | AQ14: Not reported | AW14: 0 | AX14: 5 | AY14: 5 – Official source with live/current data | AZ14: 4 | BA14: 1 | BB14: https://www.pib.gov.in/PressReleseDetailm.aspx?PRID=2233186&reg=3&lang=1 | BC14: Treat as digital currency, not proven blockchain | BE14: 2026-10-15
A15: C14 | B15: Blockchain solutions with NIC (details not public) | C15: Named by MeitY as developing blockchain solutions | D15: active | E15: Union | F15: Ministry / department | G15: Ministry of Corporate Affairs | H15: Ministry of Corporate Affairs | I15: Union government | J15: IN | K15: Union / national | L15: National | M15: National | O15: Grievance & Records | P15: 1 | Q15: General public services | R15: Platform / ecosystem | S15: Capacity & shared infrastructure | T15: G2G | U15: Not disclosed | V15: Not disclosed | W15: Not disclosed | X15: Not disclosed | Y15: NIC | Z15: Government IT (NIC / C-DAC / NeGD) | AA15: No | AB15: In progress | AC15: In development | AD15: Development stage | AE15: 2024-12-16 | AF15: 2024 | AG15: 2024 | AM15: 2024-12-16 | AO15: 1.8 | AQ15: Not reported | AW15: 0 | AX15: 3 | AY15: 3 – Mainstream news | AZ15: 1 | BA15: 0 | BB15: https://www.medianama.com/2024/12/223-blockchain-land-use-pilot-karnataka-jharkhandd/ | BC15: Scope not public | BE15: 2026-10-15
A16: C15 | B16: Kasturi Cotton Bharat – blockchain traceability | C16: QR certification at each stage plus blockchain platform for end-to-end traceability and transaction certificates | D16: active | E16: Union | F16: Ministry / department | G16: Ministry of Textiles – Cotton Corporation of India & TEXPROCIL | H16: Ministry of Textiles | I16: Union government | J16: IN | K16: Union / national | L16: National | M16: National | O16: Agriculture & Trade | P16: 4 | Q16: Economic affairs | R16: Supply-chain traceability | S16: Lack of traceability / counterfeits | T16: G2B | U16: Not disclosed | V16: Not disclosed | W16: Not disclosed | X16: Not disclosed | Y16: CCI, TEXPROCIL | Z16: Not disclosed | AA16: No | AB16: Implemented | AC16: Live | AD16: Operational nationwide | AE16: 2026-08-06 | AF16: 2022 | AG16: 2022-12-15 | AJ16: 2024-08-06 | AM16: 2026-08-06 | AN16: 20 | AO16: 0.2 | AP16: ₹30 crore budget; 343 ginning units registered | AQ16: Not reported | AW16: 0 | AX16: 5 | AY16: 5 – Official source with live/current data | AZ16: 8 | BA16: 2 | BB16: https://www.pib.gov.in/PressReleasePage.aspx?PRID=2042089 | BE16: 2026-10-15
A17: C16 | B17: PM Rashtriya Bal Puraskar certificates on blockchain | C17: Award certificates issued as blockchain digital certificates (IIT Kanpur National Blockchain Project) | D17: active | E17: Union | F17: Ministry / department | G17: Ministry of Women & Child Development | H17: Ministry of Women & Child Development | I17: Union government | J17: IN | K17: Union / national | L17: National | M17: National | O17: Certificates & Identity | P17: 1 | Q17: General public services | R17: Certificates & identity | S17: Forgery / fake documents | T17: G2C | U17: IIT Kanpur NBP platform | V17: IIT Kanpur NBP | W17: Other enterprise DLT | X17: Not disclosed | Y17: IIT Kanpur, CRUBN | Z17: Academic / research partner | AA17: No | AB17: Implemented | AC17: Live | AD17: Issued digitally for 2021 & 2022 awards | AE17: 2022-01-24 | AF17: 2022 | AG17: 2022-01-21 | AJ17: 2022-01-24 | AM17: 2022-01-24 | AN17: 0 | AO17: 4.7 | AP17: 61 awardees | AQ17: Small (<10,000) | AW17: 0 | AX17: 4 | AY17: 4 – Official document (govt site, PIB, tender, court) | AZ17: 5 | BA17: 4 | BB17: https://www.pib.gov.in/PressReleaseIframePage.aspx?PRID=1792136 | BE17: 2026-10-15
A18: C17 | B18: Blockchain-based tamper-proof railway signalling | C18: Distributed ledger for signal records and smart-contract automation | D18: active | E18: Union | F18: Ministry / department | G18: Ministry of Railways with IIT Kharagpur & IIT Bhubaneswar | H18: Ministry of Railways | I18: Union government | J18: IN | K18: Union / national | L18: National | M18: National | O18: Transport | P18: 4 | Q18: Economic affairs | R18: Records & audit trail | S18: Tampering of records | T18: G2G | U18: Not stated | V18: Not disclosed | W18: Not disclosed | X18: Not disclosed | Y18: IIT KGP, IIT BBS | Z18: Academic / research partner | AA18: No | AB18: Proposed / Planned | AC18: Planned | AD18: Under development / testing; approved by Railway Minister | AE18: 2023-07-11 | AF18: 2023 | AG18: 2023-06 | AM18: 2023-07-11 | AO18: 3.3 | AQ18: Not reported | AW18: 0 | AX18: 3 | AY18: 3 – Mainstream news | AZ18: 3 | BA18: 0 | BB18: https://www.freepressjournal.in/education/iit-kharagpur-developing-tamper-proof-signalling-system-for-safety-of-trains | BE18: 2026-10-15
A19: C18 | B19: Fertilizer subsidy supply-chain pilot (GNFC) | C19: Automated quantity certification and claims to cut subsidy reimbursement time | D19: active | E19: Union | F19: Policy / planning body | G19: NITI Aayog | H19: NITI Aayog | I19: Union government | J19: IN | K19: Union / national | L19: National | M19: National | O19: Welfare & Subsidy | P19: 10 | Q19: Social protection | R19: Welfare delivery | S19: Leakage / beneficiary fraud | T19: G2B | U19: Not stated | V19: Not disclosed | W19: Not disclosed | X19: Not disclosed | Y19: PwC, Intel, GNFC | Z19: Private technology vendor | AA19: No | AB19: Pilot completed | AC19: Pilot completed | AD19: PoC done; lessons published | AE19: 2020-01 | AF19: 2019 | AG19: 2018-06-29 | AI19: 2020-01 | AM19: 2020-01 | AO19: 6.7 | AQ19: Not reported | AU19: T1 | AV19: Technology | AW19: 1 | AX19: 4 | AY19: 4 – Official document (govt site, PIB, tender, court) | AZ19: 2 | BA19: 2 | BB19: https://www.niti.gov.in/sites/default/files/2020-01/Blockchain_The_India_Strategy_Part_I.pdf | BE19: 2026-10-15
A20: C19 | B20: Drug supply chain pilot (blockchain + IoT) | C20: Track drugs from manufacturer to patient to stop fake medicines | D20: active | E20: Union | F20: Policy / planning body | G20: NITI Aayog | H20: NITI Aayog | I20: Union government | J20: IN | K20: Union / national | L20: National | M20: National | O20: Health & Supply Chain | P20: 7 | Q20: Health | R20: Supply-chain traceability | S20: Lack of traceability / counterfeits | T20: G2B | U20: Oracle Blockchain | V20: Oracle Blockchain | W20: Other enterprise DLT | X20: Permissioned | Y20: Oracle, Apollo Hospitals, Strides Pharma | Z20: Private technology vendor | AA20: No | AB20: Pilot completed | AC20: Pilot completed | AD20: Pilot executed (reported in NITI Aayog draft strategy, Jan 2020); no follow-up found | AE20: 2020-01 | AF20: 2018 | AG20: 2018-09-28 | AI20: 2020-01 | AM20: 2020-01 | AO20: 6.7 | AQ20: Not reported | AU20: E2;T1;T2 | AV20: Environment;Technology | AW20: 3 | AX20: 4 | AY20: 4 – Official document (govt site, PIB, tender, court) | AZ20: 3 | BA20: 2 | BB20: https://www.niti.gov.in/sites/default/files/2020-01/Blockchain_The_India_Strategy_Part_I.pdf | BC20: v1.1: official PIB release (Sep 2018) and NITI Aayog draft strategy (Jan 2020) found; the strategy reports the pilot as executed. | BE20: 2026-10-15
A21: C20 | B21: IndiaChain – national blockchain network | C21: Proposed common national blockchain infrastructure | D21: active | E21: Union | F21: Policy / planning body | G21: NITI Aayog | H21: NITI Aayog | I21: Union government | J21: IN | K21: Union / national | L21: National | M21: National | O21: Platform & Infrastructure | P21: 1 | Q21: General public services | R21: Platform / ecosystem | S21: Capacity & shared infrastructure | T21: G2G | U21: Not stated | V21: Not disclosed | W21: Not disclosed | X21: Not disclosed | Y21: — | Z21: Not disclosed | AA21: No | AB21: Unclear (no recent update) | AC21: Unclear | AD21: No separate launch; idea later taken up by MeitY's NBF | AE21: 2022-10-18 | AF21: 2018 | AG21: 2017-11-13 | AM21: 2022-10-18 | AO21: 4.0 | AQ21: Not reported | AU21: E1;T3 | AV21: Environment;Technology | AW21: 2 | AX21: 4 | AY21: 4 – Official document (govt site, PIB, tender, court) | AZ21: 3 | BA21: 1 | BB21: https://www.investindia.gov.in/team-india-blogs/implementing-blockchain-india | BE21: 2026-10-15
A22: O01 | B22: Digital Rupee – wholesale (e₹-W) and retail (e₹-R) CBDC | C22: CBDC pilots: wholesale for govt securities; retail token wallets via banks; offline and programmable features | D22: active | E22: Union | F22: Regulator / central bank | G22: Reserve Bank of India | H22: Central bank | I22: Other public body | J22: IN | K22: Union / national | L22: National | M22: National | O22: Finance & Payments | P22: 4 | Q22: Economic affairs | R22: CBDC / digital payments | S22: Payment efficiency & programmability | T22: G2C | U22: Not publicly confirmed as DLT | V22: RBI CBDC infrastructure | W22: CBDC infrastructure | X22: CBDC (DLT not confirmed) | Y22: Pilot banks & non-banks | Z22: Banks, depositories or telecom operators | AA22: No | AB22: In progress | AC22: In development | AD22: Still in pilot; ~10 million retail users; extended to subsidies (PDS) | AE22: 2026-10-01 | AF22: 2022 | AG22: 2022-02-01 | AH22: 2022-11-01 | AM22: 2026-10-01 | AO22: 0.0 | AP22: 19 pilot banks; ₹1,016 crore in circulation (Mar 2025) | AQ22: Large (≥10 lakh) | AU22: E2 | AV22: Environment | AW22: 2 | AX22: 5 | AY22: 5 – Official source with live/current data | AZ22: 9 | BA22: 4 | BB22: https://www.rbi.org.in/commonman/English/scripts/FAQs.aspx?Id=3686 | BC22: Do not call e₹ blockchain-based without RBI source | BE22: 2026-10-15
A23: O02 | B23: Blockchain letter-of-credit trade finance pilot | C23: Digital LCs to stop document tampering | D23: active | E23: Union | F23: Regulator / central bank | G23: RBI with SBI, HDFC Bank, ICICI Bank | H23: Central bank | I23: Other public body | J23: IN | K23: Union / national | L23: National | M23: National | O23: Finance & Payments | P23: 4 | Q23: Economic affairs | R23: Financial infrastructure | S23: Market transparency & settlement risk | T23: G2B | U23: Corda / IBM / SettleMint | V23: Corda / IBM | W23: Other enterprise DLT | X23: Permissioned | Y23: IBM, Corda, SettleMint | Z23: Private technology vendor | AA23: No | AB23: Pilot completed | AC23: Pilot completed | AD23: PoC stage reported | AE23: 2024-12-30 | AF23: 2022 | AG23: 2022-06-23 | AH23: 2022-06 | AI23: 2022-07 | AM23: 2024-12-30 | AO23: 1.8 | AQ23: Not reported | AU23: O3;T1 | AV23: Organisation;Technology | AW23: 2 | AX23: 4 | AY23: 4 – Official document (govt site, PIB, tender, court) | AZ23: 5 | BA23: 1 | BB23: https://rbihub.in/wp-content/uploads/2023/04/RBIH-Interoperable-DLT-PoC-Closure-Report.pdf | BE23: 2026-10-15
A24: O03 | B24: Invoice tokenisation for MSME supply-chain finance | C24: Tokenises accepted supplier invoices; lenders finance against tokens | D24: active | E24: Union | F24: Regulator / central bank | G24: RBI Regulatory Sandbox – IBDIC (bank-owned) | H24: Central bank | I24: Other public body | J24: IN | K24: Union / national | L24: National | M24: National | O24: Finance & Payments | P24: 4 | Q24: Economic affairs | R24: Financial infrastructure | S24: Market transparency & settlement risk | T24: G2B | U24: Not disclosed | V24: Not disclosed | W24: Not disclosed | X24: Not disclosed | Y24: ICICI, HDFC, Yes Bank, Aditya Birla Capital | Z24: Banks, depositories or telecom operators | AA24: No | AB24: Pilot completed | AC24: Pilot completed | AD24: Exited sandbox; may be adopted by regulated entities | AE24: 2025-08-27 | AF24: 2024 | AG24: 2024-07-26 | AH24: 2024-08 | AI24: 2025-08-14 | AM24: 2025-08-27 | AO24: 1.1 | AQ24: Not reported | AW24: 0 | AX24: 4 | AY24: 4 – Official document (govt site, PIB, tender, court) | AZ24: 4 | BA24: 2 | BB24: https://www.rbi.org.in/scripts/BS_PressReleaseDisplay.aspx?prid=58377 | BE24: 2026-10-15
A25: O04 | B25: Trade finance & payments PoCs | C25: Letter of credit and payment PoCs with banks | D25: active | E25: Union | F25: Regulator / central bank | G25: RBI – IDRBT | H25: Central bank (research arm) | I25: Other public body | J25: IN | K25: Union / national | L25: National | M25: National | O25: Finance & Payments | P25: 4 | Q25: Economic affairs | R25: Financial infrastructure | S25: Market transparency & settlement risk | T25: G2B | U25: Not stated | V25: Not disclosed | W25: Not disclosed | X25: Not disclosed | Y25: MonetaGo (with NPCI and banks) | Z25: Private technology vendor | AA25: No | AB25: Pilot completed | AC25: Pilot completed | AD25: PoCs completed | AE25: 2018 | AF25: 2017 | AG25: 2017-01 | AI25: 2017-01 | AM25: 2018 | AO25: 8.3 | AQ25: Not reported | AW25: 0 | AX25: 4 | AY25: 4 – Official document (govt site, PIB, tender, court) | AZ25: 5 | BA25: 1 | BB25: https://www.investindia.gov.in/team-india-blogs/implementing-blockchain-india | BE25: 2026-10-15
A26: O05 | B26: DLT security & covenant monitoring for NCDs | C26: Records asset charges, asset cover, covenants and ratings of debentures | D26: active | E26: Union | F26: Regulator / central bank | G26: SEBI with NSDL & CDSL | H26: Capital markets regulator | I26: Other public body | J26: IN | K26: Union / national | L26: National | M26: National | O26: Finance & Payments | P26: 4 | Q26: Economic affairs | R26: Financial infrastructure | S26: Market transparency & settlement risk | T26: G2B | U26: Permissioned DLT (2 depository nodes) | V26: Depository / regulator DLT | W26: Other enterprise DLT | X26: Permissioned | Y26: NSDL, CDSL | Z26: Banks, depositories or telecom operators | AA26: No | AB26: Implemented | AC26: Live | AD26: Mandatory and operational (NSDL 'DeLiTe' platform) | AE26: 2025-10-24 | AF26: 2021 | AG26: 2021-08-13 | AJ26: 2022-04-01 | AM26: 2025-10-24 | AN26: 8 | AO26: 1.0 | AP26: 550+ issuers; 3,800+ secured ISINs (~90% of outstanding) per deck | AQ26: Large (≥10 lakh) | AW26: 0 | AX26: 5 | AY26: 5 – Official source with live/current data | AZ26: 9 | BA26: 4 | BB26: https://www.pib.gov.in/PressReleasePage.aspx?PRID=2182023 | BC26: Deck cites Cognizant case study for numbers Cognizant case study (data as of 28 Nov 2024) reports 4,291 issuers and 6,368 secured ISINs, higher than the deck figures. | BE26: 2026-10-15
A27: O06 | B27: DLT for commercial SMS / telemarketing | C27: Senders and telemarketers register message chains; end-to-end SMS tracking | D27: active | E27: Union | F27: Regulator / central bank | G27: TRAI | H27: Telecom regulator | I27: Other public body | J27: IN | K27: Union / national | L27: National | M27: National | O27: Telecom & Cyber | P27: 4 | Q27: Economic affairs | R27: Authentication & anti-fraud | S27: Fraud / spam / fake apps | T27: G2B | U27: Permissioned DLT | V27: Depository / regulator DLT | W27: Other enterprise DLT | X27: Permissioned | Y27: Telcos, RBI, SEBI, NIC, C-DAC | Z27: Banks, depositories or telecom operators | AA27: No | AB27: Implemented | AC27: Live | AD27: Operational | AE27: 2025-10-24 | AF27: 2020 | AG27: 2018-07-19 | AJ27: 2021-03-08 | AK27: 2024-12-11 | AM27: 2025-10-24 | AN27: 32 | AO27: 1.0 | AP27: 1.13 lakh+ entities | AQ27: Large (≥10 lakh) | AU27: E2 | AV27: Environment | AW27: 2 | AX27: 5 | AY27: 5 – Official source with live/current data | AZ27: 6 | BA27: 4 | BB27: https://www.pib.gov.in/PressReleasePage.aspx?PRID=2182023 | BE27: 2026-10-15
A28: O07 | B28: Remote Voting Chain – PoC for migrant/in-service voters | C28: Encrypted remote votes stored on blockchain; only the parent-constituency returning officer can decrypt on counting day | D28: active | E28: Union | F28: Election commission | G28: Election Commission of India with NIC (and IIT Madras research) | H28: Constitutional body | I28: Other public body | J28: IN | K28: Union / national | L28: National | M28: National | O28: Elections | P28: 1 | Q28: General public services | R28: E-voting | S28: Voter access & vote integrity | T28: G2C | U28: Permissioned (NIC) | V28: NIC chains (Hyperledger-based) | W28: Hyperledger family | X28: Permissioned | Y28: NIC; IIT Madras | Z28: Government IT (NIC / C-DAC / NeGD) | AA28: Yes | AB28: Pilot completed | AC28: Pilot completed | AD28: PoC built per ECI directions and demonstrated; no rollout | AE28: 2022-01 | AF28: 2021 | AG28: 2020-02 | AM28: 2022-01 | AO28: 4.7 | AQ28: Not reported | AU28: E2;T3 | AV28: Environment;Technology | AW28: 2 | AX28: 4 | AY28: 4 – Official document (govt site, PIB, tender, court) | AZ28: 10 | BA28: 3 | BB28: https://blockchain.gov.in/Home/CaseStudy?CaseStudy=remotevotingchain | BE28: 2026-10-15
A29: O08 | B29: eCourts Phase III vision: digital signatures & blockchain for document authentication | C29: Vision document lists blockchain (with digital signatures) to secure and authenticate court documents | D29: active | E29: Union | F29: Court / judiciary | G29: Supreme Court of India – e-Committee | H29: Judiciary | I29: Other public body | J29: IN | K29: Union / national | L29: National | M29: National | O29: Justice & Police | P29: 3 | Q29: Public order and safety | R29: Records & audit trail | S29: Tampering of records | T29: G2C | U29: Not specified | V29: Not disclosed | W29: Not disclosed | X29: Not disclosed | Y29: — | Z29: Not applicable (policy or judgment) | AA29: No | AB29: Proposed / Planned | AC29: Planned | AD29: Proposed in vision; no blockchain-specific rollout published | AE29: 2025-12-19 | AF29: 2022 | AG29: 2022-09-23 | AM29: 2025-12-19 | AO29: 0.8 | AQ29: Not reported | AW29: 0 | AX29: 4 | AY29: 4 – Official document (govt site, PIB, tender, court) | AZ29: 6 | BA29: 4 | BB29: https://cdnbbsr.s3waas.gov.in/s35d6646aad9bcc0be55b2c82f69750387/uploads/2024/07/202407161620804267.pdf | BC29: Only one line in the vision document | BE29: 2026-10-15
A30: O09 | B30: Samiullah v. State of Bihar (2025 INSC 1292) – blockchain for land registration | C30: Bench suggested blockchain to make land registration tamper-proof; asked Law Commission to study reform and Union to set up a body with States | D30: active | E30: Union | F30: Court / judiciary | G30: Supreme Court of India (judgment) | H30: Judiciary | I30: Other public body | J30: IN | K30: Union / national | L30: National | M30: National | O30: Land & Property | P30: 1 | Q30: General public services | R30: Land / property registry | S30: Land fraud & disputes | T30: G2C | U30: — | V30: Not disclosed | W30: Not disclosed | X30: Not disclosed | Y30: — | Z30: Not applicable (policy or judgment) | AA30: No | AB30: Proposed / Planned | AC30: Planned | AD30: Judicial recommendation; Law Commission study requested | AE30: 2026-01-22 | AF30: 2025 | AG30: 2025-11-07 | AM30: 2026-01-22 | AO30: 0.7 | AP30: Property disputes ≈66% of civil cases (as cited) | AQ30: Not reported | AU30: E1;O4;T4 | AV30: Environment;Organisation;Technology | AW30: 3 | AX30: 4 | AY30: 4 – Official document (govt site, PIB, tender, court) | AZ30: 7 | BA30: 1 | BB30: https://www.lawcurb.in/judgements/samiullah-vs-the-state-of-bihar-&-ors-2025-insc-1292 | BE30: 2026-10-15
A31: O10 | B31: Asset tokenisation with wholesale CBDC settlement | C31: Tokenised certificates of deposit and bonds settled atomically in wholesale e₹ on a depository-run ledger | D31: active | E31: Union | F31: Regulator / central bank | G31: RBI with depositories – Unified Markets Interface (UMI) | H31: Central bank | I31: Other public body | J31: IN | K31: Union / national | L31: National | M31: National | O31: Finance & Payments | P31: 4 | Q31: Economic affairs | R31: Tokenisation / NFTs | S31: Asset liquidity / digital ownership | T31: G2B | U31: DLT run by depositories + wholesale CBDC | V31: Depository / regulator DLT | W31: Other enterprise DLT | X31: Permissioned | Y31: NSDL/CDSL; issuers incl. REC (state-owned) | Z31: Banks, depositories or telecom operators | AA31: No | AB31: In progress | AC31: In development | AD31: CD pilot (2025); bond pilot (Sep 2026) – REC ₹500 crore, L&T ₹500 crore, IIFL ₹25 crore | AE31: 2026-09-11 | AF31: 2025 | AG31: 2025-10-08 | AH31: 2025-10 | AM31: 2026-09-11 | AO31: 0.1 | AP31: ₹1,025 crore (~$107M) bond pilot | AQ31: Not reported | AW31: 0 | AX31: 4 | AY31: 4 – Official document (govt site, PIB, tender, court) | AZ31: 10 | BA31: 2 | BB31: https://www.bis.org/review/r251014b.pdf | BE31: 2026-10-15
A32: O11 | B32: Digi Yatra – paperless air travel with self-sovereign identity | C32: Face-based boarding; data encrypted, kept on passenger phone, blockchain used for storage (Minister) | D32: active | E32: Union | F32: Society / foundation | G32: DigiYatra Foundation (Ministry of Civil Aviation; AAI stakeholder) | H32: Ministry of Civil Aviation | I32: Other public body | J32: IN | K32: Union / national | L32: National | M32: National | O32: Certificates & Identity | P32: 1 | Q32: General public services | R32: Certificates & identity | S32: Identity verification & privacy | T32: G2C | U32: Hyperledger-based SSI (per deck) | V32: Hyperledger (other) | W32: Hyperledger family | X32: Permissioned | Y32: — | Z32: Private technology vendor | AA32: No | AB32: Implemented | AC32: Live | AD32: Live and expanding | AE32: 2026-09-21 | AF32: 2022 | AG32: 2018-10-04 | AI32: 2021-12-16 | AJ32: 2022-12-01 | AK32: 2024-09-06 | AM32: 2026-09-21 | AN32: 50 | AO32: 0.1 | AP32: 24 airports, 16 million users (deck, Dec 2025) | AQ32: Large (≥10 lakh) | AU32: E1;O3;O4;T3 | AV32: Environment;Organisation;Technology | AW32: 4 | AX32: 4 | AY32: 4 – Official document (govt site, PIB, tender, court) | AZ32: 9 | BA32: 4 | BB32: https://www.pib.gov.in/newsite/printrelease.aspx?relid=183958&reg=48&lang=2 | BE32: 2026-10-15
A33: O12 | B33: Blockchain traceability for Gir cow ghee (and Badri ghee) | C33: QR on pack shows farm-to-table journey; linked with Bharat Pashudhan traceability | D33: active | E33: Union | F33: Statutory board / authority | G33: NDDB / Mother Dairy with GS1 India | H33: Ministry of Cooperation / Dept of Animal Husbandry & Dairying | I33: Other public body | J33: IN | K33: Union / national | L33: National | M33: National | O33: Agriculture & Trade | P33: 4 | Q33: Economic affairs | R33: Supply-chain traceability | S33: Lack of traceability / counterfeits | T33: G2B | U33: Hyperledger Fabric (Spydra) | V33: Hyperledger Fabric | W33: Hyperledger family | X33: Permissioned | Y33: GS1 India, Spydra | Z33: Private technology vendor | AA33: No | AB33: Implemented | AC33: Live | AD33: Live; showcased in Republic Day 2025 tableau (per deck) | AE33: 2025-12 | AF33: 2024 | AG33: 2024-07-11 | AJ33: 2024-10-22 | AM33: 2025-12 | AN33: 3 | AO33: 0.8 | AP33: ~10,000 farmers; ~20,000 cattle (Junagadh) | AQ33: Medium (10,000–10 lakh) | AW33: 0 | AX33: 4 | AY33: 4 – Official document (govt site, PIB, tender, court) | AZ33: 6 | BA33: 3 | BB33: https://www.nddb.coop/node/2436 | BC33: NDDB page says 'Bharat Pashudhan'; blockchain per GS1/vendor | BE33: 2026-10-15
A34: O13 | B34: NFT souvenir train tickets (Holi 2024; MahaKumbh 2025) | C34: Travel to MahaKumbh recorded as verifiable NFT | D34: active | E34: Union | F34: PSU / state-owned company | G34: IRCTC (Ministry of Railways PSU) | H34: Ministry of Railways | I34: Other public body | J34: IN | K34: Union / national | L34: National | M34: National | O34: Transport | P34: 4 | Q34: Economic affairs | R34: Tokenisation / NFTs | S34: Digital souvenirs / ownership | T34: G2C | U34: Polygon (public) | V34: Polygon | W34: Ethereum / EVM chains | X34: Public | Y34: Chaincode Consulting, NFTtrace | Z34: Private technology vendor | AA34: No | AB34: Implemented | AC34: Live | AD34: Issued for events | AE34: 2025-01-13 | AF34: 2024 | AG34: 2024-03 | AJ34: 2024-03 | AM34: 2025-01-13 | AN34: 0 | AO34: 1.8 | AQ34: Not reported | AW34: 0 | AX34: 2 | AY34: 2 – Trade/crypto press or secondary (eBook, deck, blog) | AZ34: 3 | BA34: 0 | BB34: https://cointelegraph.com/news/indian-railways-nft-tickets-mahakumbh-mela | BE34: 2026-10-15
A35: O14 | B35: Academic documents on NIC Certificate Chain (cbse.certchain.nic.in) | C35: Tamper-proof academic records verifiable online | D35: active | E35: Union | F35: Statutory board / authority | G35: Central Board of Secondary Education (CBSE) | H35: Ministry of Education | I35: Other public body | J35: IN | K35: Union / national | L35: National | M35: National | O35: Education & Skills | P35: 9 | Q35: Education | R35: Certificates & identity | S35: Forgery / fake documents | T35: G2C | U35: Permissioned (NIC) | V35: NIC chains (Hyperledger-based) | W35: Hyperledger family | X35: Permissioned | Y35: NIC | Z35: Government IT (NIC / C-DAC / NeGD) | AA35: Yes | AB35: Implemented | AC35: Live | AD35: Live – 2nd largest NIC chain by documents | AE35: 2026-10-14 | AF35: 2019 | AG35: 2021-09-22 | AJ35: 2021-09-22 | AM35: 2026-10-14 | AN35: 0 | AO35: 0.0 | AP35: 2,10,71,556 documents; 85,261 verifications (NIC statistics, 2026-10-14) | AQ35: Large (≥10 lakh) | AR35: 21071556 | AS35: 85261 | AT35: 2026-10-14 | AW35: 0 | AX35: 5 | AY35: 5 – Official source with live/current data | AZ35: 7 | BA35: 6 | BB35: https://blockchain.gov.in/Home/Home | BE35: 2026-10-15
A36: O15 | B36: Blockchain digital degrees & certificates | C36: Forgery-proof, verifiable digital certificates (IIT Kanpur degrees, PM Bal Puraskar) and self-sovereign identity (SSI) ID cards for IITK employees | D36: active | E36: Union | F36: University / research institute | G36: IIT Kanpur – National Blockchain Project (NSCS-coordinated) | H36: Ministry of Education / NSCS | I36: Other public body | J36: IN | K36: Union / national | L36: National | M36: National | O36: Education & Skills | P36: 9 | Q36: Education | R36: Certificates & identity | S36: Forgery / fake documents | T36: G2C | U36: IIT Kanpur NBP platform | V36: IIT Kanpur NBP | W36: Other enterprise DLT | X36: Not disclosed | Y36: CRUBN | Z36: Academic / research partner | AA36: No | AB36: Implemented | AC36: Live | AD36: In use | AE36: 2025-12 | AF36: 2021 | AJ36: 2021-12-28 | AK36: 2022-01 | AM36: 2025-12 | AO36: 0.8 | AQ36: Not reported | AW36: 0 | AX36: 4 | AY36: 4 – Official document (govt site, PIB, tender, court) | AZ36: 8 | BA36: 4 | BB36: https://www.pib.gov.in/Pressreleaseshare.aspx?PRID=1785750&reg=3&lang=2 | BE36: 2026-10-15
A37: O16 | B37: Blockchain coffee e-marketplace | C37: Bean-to-cup traceability; fewer middlemen | D37: active | E37: Union | F37: Statutory board / authority | G37: Coffee Board of India | H37: Ministry of Commerce & Industry | I37: Other public body | J37: IN | K37: Union / national | L37: National | M37: National | O37: Agriculture & Trade | P37: 4 | Q37: Economic affairs | R37: Supply-chain traceability | S37: Lack of traceability / counterfeits | T37: G2B | U37: Ethereum | V37: Ethereum | W37: Ethereum / EVM chains | X37: Public | Y37: Eka Plus | Z37: Private technology vendor | AA37: No | AB37: Unclear (no recent update) | AC37: Unclear | AD37: Grew to ~30,000 farmers; no later status | AE37: 2021 | AF37: 2019 | AG37: 2019-03-28 | AH37: 2019-03-28 | AM37: 2021 | AO37: 5.3 | AP37: ~30,000 farmers | AQ37: Medium (10,000–10 lakh) | AU37: E2 | AV37: Environment | AW37: 1 | AX37: 2 | AY37: 2 – Trade/crypto press or secondary (eBook, deck, blog) | AZ37: 2 | BA37: 0 | BB37: https://www.ledgerinsights.com/blockchain-coffee-food-traceability-india/ | BE37: 2026-10-15
A38: O17 | B38: Spice traceability & trading (eSpiceBazaar) | C38: Traceability for chilli and turmeric with GS1 farm IDs, linked to e-Spice Bazaar | D38: active | E38: Union | F38: Statutory board / authority | G38: Spices Board with UNDP & GS1 India | H38: Ministry of Commerce & Industry | I38: Other public body | J38: IN | K38: Union / national | L38: National | M38: National | O38: Agriculture & Trade | P38: 4 | Q38: Economic affairs | R38: Supply-chain traceability | S38: Lack of traceability / counterfeits | T38: G2B | U38: Not stated | V38: Not disclosed | W38: Not disclosed | X38: Not disclosed | Y38: UNDP Accelerator Lab, GS1 India | Z38: International organisation | AA38: No | AB38: Unclear (no recent update) | AC38: Unclear | AD38: Pilot in select AP districts; no later status found | AE38: 2021-04-05 | AF38: 2021 | AG38: 2021-04-05 | AM38: 2021-04-05 | AO38: 5.5 | AP38: 3,000+ farmers (pilot) | AQ38: Small (<10,000) | AW38: 0 | AX38: 4 | AY38: 4 – Official document (govt site, PIB, tender, court) | AZ38: 2 | BA38: 1 | BB38: https://www.pib.gov.in/PressReleseDetailm.aspx?PRID=1709674&reg=3&lang=2 | BE38: 2026-10-15
A39: O18 | B39: Blockchain solutions with NIC (details not public) | C39: Named by MeitY as developing blockchain solutions | D39: active | E39: Union | F39: PSU / state-owned company | G39: UIDAI; SPMCIL; Cotton Corporation of India; Forensic Science Laboratory | H39: Various ministries | I39: Other public body | J39: IN | K39: Union / national | L39: National | M39: National | O39: Platform & Infrastructure | P39: 1 | Q39: General public services | R39: Platform / ecosystem | S39: Capacity & shared infrastructure | T39: G2G | U39: Not disclosed | V39: Not disclosed | W39: Not disclosed | X39: Not disclosed | Y39: NIC | Z39: Government IT (NIC / C-DAC / NeGD) | AA39: No | AB39: In progress | AC39: In development | AD39: Development stage | AE39: 2024-12-16 | AF39: 2024 | AG39: 2024-12 | AM39: 2024-12-16 | AO39: 1.8 | AQ39: Not reported | AW39: 0 | AX39: 3 | AY39: 3 – Mainstream news | AZ39: 1 | BA39: 0 | BB39: https://www.medianama.com/2024/12/223-blockchain-land-use-pilot-karnataka-jharkhandd/ | BC39: Scope not public | BE39: 2026-10-15
A40: O19 | B40: Tamper-proof eStamp transaction records | C40: eStamp records on blockchain | D40: active | E40: Union | F40: PSU / state-owned company | G40: Govt financial agencies (eStamp) | H40: Ministry of Finance | I40: Other public body | J40: IN | K40: Union / national | L40: National | M40: National | O40: Finance & Payments | P40: 4 | Q40: Economic affairs | R40: Financial infrastructure | S40: Market transparency & settlement risk | T40: G2B | U40: Not disclosed | V40: Not disclosed | W40: Not disclosed | X40: Not disclosed | Y40: NIC | Z40: Government IT (NIC / C-DAC / NeGD) | AA40: No | AB40: In progress | AC40: In development | AD40: Mentioned in MeitY reply | AE40: 2024-12-16 | AF40: 2024 | AG40: 2024-12 | AM40: 2024-12-16 | AO40: 1.8 | AQ40: Not reported | AW40: 0 | AX40: 3 | AY40: 3 – Mainstream news | AZ40: 1 | BA40: 0 | BB40: https://www.medianama.com/2024/12/223-blockchain-land-use-pilot-karnataka-jharkhandd/ | BC40: Confirm agency | BE40: 2026-10-15
A41: S01 | B41: Land records on blockchain – Amaravati capital region | C41: Secure land records against tampering; India's first state blockchain pilot | D41: active | E41: State | F41: Ministry / department | G41: Revenue Dept / CRDA | H41: Andhra Pradesh | I41: State / UT government | J41: IN-AP | K41: Andhra Pradesh | L41: State | M41: Southern | N41: 28 | O41: Land & Property | P41: 1 | Q41: General public services | R41: Land / property registry | S41: Land fraud & disputes | T41: G2C | U41: Private chains | V41: Not disclosed | W41: Not disclosed | X41: Permissioned | Y41: Zebi Data, ChromaWay | Z41: Private technology vendor | AA41: No | AB41: Pilot completed | AC41: Pilot completed | AD41: 100,000+ records secured in pilot | AE41: 2019-12-16 | AF41: 2017 | AG41: 2017-10-10 | AH41: 2017-12 | AM41: 2019-12-16 | AO41: 6.8 | AP41: 100,000+ records | AQ41: Medium (10,000–10 lakh) | AU41: T3;T4 | AV41: Technology | AW41: 2 | AX41: 3 | AY41: 3 – Mainstream news | AZ41: 6 | BA41: 0 | BB41: https://www.forbes.com/sites/outofasia/2018/03/05/this-indian-city-is-embracing-blockchain-technology-heres-why/ | BE41: 2026-10-15
A42: S02 | B42: Vehicle registration pilot | C42: Early AP pilot alongside land records | D42: active | E42: State | F42: Ministry / department | G42: Transport Dept | H42: Andhra Pradesh | I42: State / UT government | J42: IN-AP | K42: Andhra Pradesh | L42: State | M42: Southern | N42: 28 | O42: Transport | P42: 4 | Q42: Economic affairs | R42: Records & audit trail | S42: Tampering of records | T42: G2C | U42: Not stated | V42: Not disclosed | W42: Not disclosed | X42: Not disclosed | Y42: — | Z42: Not disclosed | AA42: No | AB42: Unclear (no recent update) | AC42: Unclear | AD42: No update after pilot | AE42: 2018-03-05 | AF42: 2017 | AG42: 2017 | AM42: 2018-03-05 | AO42: 8.6 | AQ42: Not reported | AW42: 0 | AX42: 3 | AY42: 3 – Mainstream news | AZ42: 1 | BA42: 0 | BB42: https://www.forbes.com/sites/outofasia/2018/03/05/this-indian-city-is-embracing-blockchain-technology-heres-why/ | BE42: 2026-10-15
A43: S03 | B43: Civil supplies & pension databases on blockchain | C43: Plan to move ration card and pension data to blockchain | D43: active | E43: State | F43: Ministry / department | G43: Civil Supplies / Revenue Dept | H43: Andhra Pradesh | I43: State / UT government | J43: IN-AP | K43: Andhra Pradesh | L43: State | M43: Southern | N43: 28 | O43: Welfare & Subsidy | P43: 10 | Q43: Social protection | R43: Welfare delivery | S43: Leakage / beneficiary fraud | T43: G2C | U43: Not stated | V43: Not disclosed | W43: Not disclosed | X43: Not disclosed | Y43: Snapper Future Tech | Z43: Private technology vendor | AA43: No | AB43: Unclear (no recent update) | AC43: Unclear | AD43: Announced; rollout not confirmed | AE43: 2019 | AF43: 2019 | AG43: 2017-06-27 | AH43: 2017 | AM43: 2019 | AO43: 7.3 | AP43: ~103 million ration card records | AQ43: Large (≥10 lakh) | AW43: 0 | AX43: 3 | AY43: 3 – Mainstream news | AZ43: 2 | BA43: 0 | BB43: https://www.econotimes.com/Telangana-and-Andhra-Pradesh-spearhead-blockchain-adoption-in-India--Report-776108 | BE43: 2026-10-15
A44: S04 | B44: Land acquisition documents on NIC chain | C44: Preliminary notification, draft declaration, LA award, R&R award stored for verification | D44: active | E44: State | F44: Ministry / department | G44: Water Resources Dept | H44: Andhra Pradesh | I44: State / UT government | J44: IN-AP | K44: Andhra Pradesh | L44: State | M44: Southern | N44: 28 | O44: Land & Property | P44: 1 | Q44: General public services | R44: Land / property registry | S44: Land fraud & disputes | T44: G2C | U44: Permissioned (NIC) | V44: NIC chains (Hyperledger-based) | W44: Hyperledger family | X44: Permissioned | Y44: NIC | Z44: Government IT (NIC / C-DAC / NeGD) | AA44: Yes | AB44: Unclear (no recent update) | AC44: Unclear | AD44: Listed in Jun 2024; not on NIC live dashboard (Oct 2026) | AE44: 2026-10-03 | AF44: 2023 | AJ44: 2023-12-04 | AM44: 2026-10-03 | AO44: 0.0 | AQ44: Not reported | AR44: 12 | AS44: 0 | AT44: 2024-07-23 | AW44: 0 | AX44: 5 | AY44: 5 – Official source with live/current data | AZ44: 2 | BA44: 1 | BB44: https://blockchain.gov.in/Home/Home | BC44: Listed in the NIC statistics file of Jul 2024 (12 documents, Water Resource Dept); no longer listed in Oct 2026. | BE44: 2026-10-15
A45: S05 | B45: Revenue records on blockchain + departmental data lake | C45: CM directive to sanitise and secure all revenue records using blockchain | D45: active | E45: State | F45: Government (whole of government) | G45: Chief Minister / RTGS | H45: Andhra Pradesh | I45: State / UT government | J45: IN-AP | K45: Andhra Pradesh | L45: State | M45: Southern | N45: 28 | O45: Land & Property | P45: 1 | Q45: General public services | R45: Land / property registry | S45: Land fraud & disputes | T45: G2C | U45: Not stated | V45: Not disclosed | W45: Not disclosed | X45: Not disclosed | Y45: — | Z45: Not disclosed | AA45: No | AB45: Proposed / Planned | AC45: Planned | AD45: Directive issued | AE45: 2025-07-08 | AF45: 2025 | AG45: 2025-07-07 | AM45: 2025-07-08 | AO45: 1.3 | AQ45: Not reported | AU45: T4 | AV45: Technology | AW45: 1 | AX45: 3 | AY45: 3 – Mainstream news | AZ45: 1 | BA45: 0 | BB45: https://thesouthfirst.com/news/andhra-pradesh-to-use-blockchain-technology-to-secure-records-and-data-across-various-departments/ | BE45: 2026-10-15
A46: S06 | B46: Mee Bhoomi–Blockchain pilot (NIC Property Chain) | C46: Digital identity per land parcel; auto-mutation, subdivision, extent correction; shared with other departments and banks | D46: active | E46: State | F46: Ministry / department | G46: Revenue & Survey Depts with NIC AP & NIC CoE | H46: Andhra Pradesh | I46: State / UT government | J46: IN-AP | K46: Andhra Pradesh | L46: State | M46: Southern | N46: 28 | O46: Land & Property | P46: 1 | Q46: General public services | R46: Land / property registry | S46: Land fraud & disputes | T46: G2C | U46: Hyperledger Fabric | V46: NIC chains (Hyperledger-based) | W46: Hyperledger family | X46: Permissioned | Y46: NIC | Z46: Government IT (NIC / C-DAC / NeGD) | AA46: Yes | AB46: In progress | AC46: In development | AD46: Pilot in 7 mandals of 7 districts; live on NIC Property Chain | AE46: 2026-10-14 | AF46: 2026 | AG46: 2025-07 | AH46: 2026-07-23 | AM46: 2026-10-14 | AO46: 0.0 | AP46: 3,16,434 documents; 1,60,368 verifications (NIC statistics, 2026-10-14) | AQ46: Medium (10,000–10 lakh) | AR46: 316434 | AS46: 160368 | AT46: 2026-10-14 | AU46: T1;T4 | AV46: Technology | AW46: 2 | AX46: 5 | AY46: 5 – Official source with live/current data | AZ46: 7 | BA46: 3 | BB46: https://blockchain.gov.in/Home/Home | BE46: 2026-10-15
A47: S07 | B47: Blockchain + QR-coded Pattadar passbooks | C47: Land passbooks with blockchain, QR and note-like security features | D47: active | E47: State | F47: Ministry / department | G47: Revenue Dept – Mee Bhumi Mee Hakku | H47: Andhra Pradesh | I47: State / UT government | J47: IN-AP | K47: Andhra Pradesh | L47: State | M47: Southern | N47: 28 | O47: Land & Property | P47: 1 | Q47: General public services | R47: Land / property registry | S47: Land fraud & disputes | T47: G2C | U47: Not disclosed | V47: Not disclosed | W47: Not disclosed | X47: Not disclosed | Y47: — | Z47: Not disclosed | AA47: No | AB47: In progress | AC47: In development | AD47: 32 lakh+ issued; 69 lakh pending in 9,365 villages | AE47: 2026-08-10 | AF47: 2026 | AG47: 2026-08-10 | AM47: 2026-08-10 | AO47: 0.2 | AP47: 32 lakh passbooks | AQ47: Large (≥10 lakh) | AU47: T4 | AV47: Technology | AW47: 1 | AX47: 3 | AY47: 3 – Mainstream news | AZ47: 1 | BA47: 0 | BB47: https://telanganatoday.com/tamper-proof-blockchain-naidu-announces-enhanced-security-for-ap-land-documents | BE47: 2026-10-15
A48: S08 | B48: Blockchain cadastre & land records pilot (Darrang) with NGDRS and ULPIN | C48: District-level blockchain land registry linked to NGDRS, Bhunaksha, Dharitree | D48: active | E48: State | F48: Ministry / department | G48: Revenue & Disaster Management Dept with Dept of Land Resources | H48: Assam | I48: State / UT government | J48: IN-AS | K48: Assam | L48: State | M48: North-Eastern | N48: 18 | O48: Land & Property | P48: 1 | Q48: General public services | R48: Land / property registry | S48: Land fraud & disputes | T48: G2C | U48: Permissioned (NIC) | V48: NIC chains (Hyperledger-based) | W48: Hyperledger family | X48: Permissioned | Y48: NIC | Z48: Government IT (NIC / C-DAC / NeGD) | AA48: Yes | AB48: In progress | AC48: In development | AD48: Listed as PoC on NIC dashboard; NGDRS live in all 77 SROs | AE48: 2026-10-03 | AF48: 2024 | AH48: 2024-02-13 | AM48: 2026-10-03 | AO48: 0.0 | AP48: 77 Sub-Registrar Offices | AQ48: Not reported | AW48: 0 | AX48: 5 | AY48: 5 – Official source with live/current data | AZ48: 4 | BA48: 3 | BB48: https://blockchain.gov.in/Home/Home | BE48: 2026-10-15
A49: S09 | B49: Mobile e-voting with blockchain vote proofs | C49: Municipal by-election votes on private DocChain with proofs anchored on Polygon | D49: active | E49: State | F49: Election commission | G49: Bihar State Election Commission | H49: Bihar | I49: State / UT government | J49: IN-BR | K49: Bihar | L49: State | M49: Eastern | N49: 10 | O49: Elections | P49: 1 | Q49: General public services | R49: E-voting | S49: Voter access & vote integrity | T49: G2C | U49: Private chain + Polygon (public) | V49: Polygon | W49: Ethereum / EVM chains | X49: Hybrid (private + public anchor) | Y49: C-DAC, Print2Block | Z49: Government–industry consortium | AA49: No | AB49: Pilot completed | AC49: Pilot completed | AD49: Pilot completed successfully | AE49: 2025-07-21 | AF49: 2025 | AG49: 2025-07 | AI49: 2025-07 | AM49: 2025-07-21 | AO49: 1.2 | AP49: 42 municipalities, 26 districts; 51,157 voters; ~70% turnout | AQ49: Medium (10,000–10 lakh) | AW49: 0 | AX49: 4 | AY49: 4 – Official document (govt site, PIB, tender, court) | AZ49: 2 | BA49: 1 | BB49: https://x.com/cdacindia/status/1947175299676016838 | BE49: 2026-10-15
A50: S10 | B50: Blockchain for e-Governance Grand Challenge | C50: Startup challenge on data exchange, e-health records, land records; winners to pilot with departments | D50: active | E50: State | F50: IT / e-governance agency | G50: CHiPS (IT agency) | H50: Chhattisgarh | I50: State / UT government | J50: IN-CG | K50: Chhattisgarh | L50: State | M50: Central | N50: 22 | O50: Platform & Infrastructure | P50: 1 | Q50: General public services | R50: Platform / ecosystem | S50: Capacity & shared infrastructure | T50: G2B | U50: — | V50: Not disclosed | W50: Not disclosed | X50: Not disclosed | Y50: GovBlocks and other winners | Z50: Private technology vendor | AA50: No | AB50: Unclear (no recent update) | AC50: Unclear | AD50: Pilots announced; no later status | AE50: 2018-08-31 | AF50: 2018 | AG50: 2018-08 | AM50: 2018-08-31 | AO50: 8.1 | AP50: 118 participants | AQ50: Not reported | AW50: 0 | AX50: 3 | AY50: 3 – Mainstream news | AZ50: 1 | BA50: 0 | BB50: https://yourstory.com/2018/08/chhattisgarh-blockchain-grand-challenge | BE50: 2026-10-15
A51: S12 | B51: Degree certificates on NIC Certificate Chain | C51: Degree certificates available for online verification | D51: active | E51: State | F51: University / research institute | G51: Indira Gandhi Krishi Vishwavidyalaya, Raipur (state agri university) | H51: Chhattisgarh | I51: State / UT government | J51: IN-CG | K51: Chhattisgarh | L51: State | M51: Central | N51: 22 | O51: Education & Skills | P51: 9 | Q51: Education | R51: Certificates & identity | S51: Forgery / fake documents | T51: G2C | U51: Permissioned (NIC) | V51: NIC chains (Hyperledger-based) | W51: Hyperledger family | X51: Permissioned | Y51: NIC | Z51: Government IT (NIC / C-DAC / NeGD) | AA51: Yes | AB51: Implemented | AC51: Live | AD51: Live | AE51: 2026-10-14 | AJ51: 2024-04 | AM51: 2026-10-14 | AO51: 0.0 | AP51: 7,277 documents; 103 verifications (NIC statistics, 2026-10-14) | AQ51: Small (<10,000) | AR51: 7277 | AS51: 103 | AT51: 2026-10-14 | AW51: 0 | AX51: 5 | AY51: 5 – Official source with live/current data | AZ51: 5 | BA51: 4 | BB51: https://blockchain.gov.in/Home/Home | BE51: 2026-10-15
A52: S13 | B52: Blockchain for land registration | C52: Tamper-proof land registration and property verification; notary records digitisation started | D52: active | E52: State | F52: Ministry / department | G52: Dept of IT, Electronics & Communication | H52: Goa | I52: State / UT government | J52: IN-GA | K52: Goa | L52: State | M52: Western | N52: 30 | O52: Land & Property | P52: 1 | Q52: General public services | R52: Land / property registry | S52: Land fraud & disputes | T52: G2C | U52: Not stated | V52: Not disclosed | W52: Not disclosed | X52: Not disclosed | Y52: Info Tech Corporation of Goa | Z52: State IT agency (in-house) | AA52: No | AB52: Proposed / Planned | AC52: Planned | AD52: 'Under consideration' (CM in Assembly) | AE52: 2025-07-28 | AF52: 2025 | AG52: 2025-07 | AM52: 2025-07-28 | AO52: 1.2 | AQ52: Not reported | AW52: 0 | AX52: 3 | AY52: 3 – Mainstream news | AZ52: 3 | BA52: 0 | BB52: https://www.thegoan.net/goa-news/%EF%BB%BFgovt-mulls-blockchain-tech-to-secure-land-transactions/133870.html | BC52: A 2024 roundup claims it is live – conflicting | BE52: 2026-10-15
A53: S14 | B53: Police records (FIRs) on blockchain | C53: Digitise FIRs and police documents on blockchain | D53: active | E53: State | F53: Ministry / department | G53: Goa Police (Crime Branch) | H53: Goa | I53: State / UT government | J53: IN-GA | K53: Goa | L53: State | M53: Western | N53: 30 | O53: Justice & Police | P53: 3 | Q53: Public order and safety | R53: Records & audit trail | S53: Tampering of records | T53: G2C | U53: 5ire | V53: 5ire | W53: Ethereum / EVM chains | X53: Public | Y53: 5ire | Z53: Private technology vendor | AA53: No | AB53: Unclear (no recent update) | AC53: Unclear | AD53: MoU signed; no later update | AE53: 2022-08-05 | AF53: 2022 | AG53: 2022-08 | AM53: 2022-08-05 | AO53: 4.2 | AQ53: Not reported | AW53: 0 | AX53: 3 | AY53: 3 – Mainstream news | AZ53: 3 | BA53: 0 | BB53: https://globalprimenews.com/2022/08/02/5ire-signs-mou-with-goa-police-to-develop-smart-policing-system/ | BE53: 2026-10-15
A54: S15 | B54: AI, blockchain & GIS for land records | C54: Exploring blockchain to secure land records and stop duplication | D54: active | E54: State | F54: Ministry / department | G54: Revenue Department | H54: Gujarat | I54: State / UT government | J54: IN-GJ | K54: Gujarat | L54: State | M54: Western | N54: 24 | O54: Land & Property | P54: 1 | Q54: General public services | R54: Land / property registry | S54: Land fraud & disputes | T54: G2C | U54: Not stated | V54: Not disclosed | W54: Not disclosed | X54: Not disclosed | Y54: — | Z54: Not disclosed | AA54: No | AB54: Proposed / Planned | AC54: Planned | AD54: Exploratory stage | AE54: 2026-05-09 | AF54: 2026 | AG54: 2026-05 | AM54: 2026-05-09 | AO54: 0.4 | AQ54: Not reported | AU54: T3 | AV54: Technology | AW54: 1 | AX54: 3 | AY54: 3 – Mainstream news | AZ54: 2 | BA54: 0 | BB54: https://www.convergence-now.com/future-cities/gujarat-ai-blockchain-gis-land-governance-reform/ | BE54: 2026-10-15
A55: S16 | B55: Digital notarisation MoU (AI + blockchain); CoE at GTU | C55: Blockchain-based authentication of notarised documents | D55: active | E55: State | F55: Government (whole of government) | G55: Govt of Gujarat | H55: Gujarat | I55: State / UT government | J55: IN-GJ | K55: Gujarat | L55: State | M55: Western | N55: 24 | O55: Certificates & Identity | P55: 1 | Q55: General public services | R55: Certificates & identity | S55: Forgery / fake documents | T55: G2C | U55: Not stated | V55: Not disclosed | W55: Not disclosed | X55: Not disclosed | Y55: — | Z55: Not disclosed | AA55: No | AB55: Proposed / Planned | AC55: Planned | AD55: DPR sent to Union Ministry of Law; proposal being finalised (Feb 2026, vendor source) | AE55: 2026-02-28 | AF55: 2023 | AG55: 2024-01-03 | AM55: 2026-02-28 | AO55: 0.6 | AQ55: Not reported | AW55: 0 | AX55: 3 | AY55: 3 – Mainstream news | AZ55: 5 | BA55: 0 | BB55: https://www.tribuneindia.com/news/business/naapbooks-directors-hold-strategic-meeting-with-odishas-it-minister-on-e-notary-digitalisation/ | BC55: No official source yet; the Feb 2026 status update comes from the vendor (Naapbooks). | BE55: 2026-10-15
A56: S17 | B56: Blockchain academic certificates | C56: Encrypted digital certificates with online verification for pass-outs | D56: active | E56: State | F56: Statutory board / authority | G56: Board of School Education Haryana (BSEH) | H56: Haryana | I56: State / UT government | J56: IN-HR | K56: Haryana | L56: State | M56: Northern | N56: 6 | O56: Education & Skills | P56: 9 | Q56: Education | R56: Certificates & identity | S56: Forgery / fake documents | T56: G2C | U56: Public blockchain (CRISP platform) | V56: Not disclosed | W56: Not disclosed | X56: Public | Y56: CRISP Bhopal (Madhya Pradesh govt society) | Z56: State IT agency (in-house) | AA56: No | AB56: Unclear (no recent update) | AC56: Unclear | AD56: Agreement with CRISP signed Jun 2023 (3-year term); no evidence of certificates issued | AE56: 2023-06-22 | AF56: 2023 | AG56: 2023-06-22 | AM56: 2023-06-22 | AO56: 3.3 | AP56: 5 lakh students | AQ56: Medium (10,000–10 lakh) | AW56: 0 | AX56: 4 | AY56: 4 – Official document (govt site, PIB, tender, court) | AZ56: 2 | BA56: 1 | BB56: https://crisp.mp.gov.in/news/235-haryana-government-will-give-digital-certificates-to-5-lakh-students-by-crisp-s-developed-blockchain-technology | BD56: S36 | BE56: 2026-10-15
A57: S18 | B57: Apiary – blockchain Centre of Entrepreneurship, STPI Gurugram | C57: Incubates blockchain startups (agri, supply chain, finance, health, e-governance) | D57: active | E57: State | F57: IT / e-governance agency | G57: Govt of Haryana with STPI (MeitY) | H57: Haryana | I57: State / UT government | J57: IN-HR | K57: Haryana | L57: State | M57: Northern | N57: 6 | O57: Platform & Infrastructure | P57: 1 | Q57: General public services | R57: Platform / ecosystem | S57: Capacity & shared infrastructure | T57: G2B | U57: — | V57: Not disclosed | W57: Not disclosed | X57: Not disclosed | Y57: STPI, MeitY, IBM, Intel, GBA, FITT-IIT Delhi | Z57: Government–industry consortium | AA57: No | AB57: Implemented | AC57: Live | AD57: Operating; 5 startup cohorts | AE57: 2025-02-19 | AF57: 2020 | AG57: 2020-07-17 | AJ57: 2021-03 | AK57: 2023-10-20 | AM57: 2025-02-19 | AN57: 8 | AO57: 1.7 | AP57: Cohorts: 23, 19, 13, 19, 6 startups screened in | AQ57: Small (<10,000) | AW57: 0 | AX57: 4 | AY57: 4 – Official document (govt site, PIB, tender, court) | AZ57: 8 | BA57: 5 | BB57: https://haryanait.gov.in/center-of-excellence-for-blockchain/ | BE57: 2026-10-15
A58: S19 | B58: Apple supply-chain quality monitoring (blockchain + IoT) | C58: Pilot to monitor apple quality and supply chain | D58: active | E58: State | F58: Policy / planning body | G58: NITI Aayog with Govt of Himachal Pradesh | H58: Himachal Pradesh | I58: State / UT government | J58: IN-HP | K58: Himachal Pradesh | L58: State | M58: Northern | N58: 2 | O58: Agriculture & Trade | P58: 4 | Q58: Economic affairs | R58: Supply-chain traceability | S58: Lack of traceability / counterfeits | T58: G2B | U58: Not stated | V58: Not disclosed | W58: Not disclosed | X58: Not disclosed | Y58: — | Z58: Not disclosed | AA58: No | AB58: Unclear (no recent update) | AC58: Unclear | AD58: Reported in 2024 eBook only; no official source found | AE58: 2024 | AM58: 2024 | AO58: 2.3 | AQ58: Not reported | AW58: 0 | AX58: 1 | AY58: 1 – Vendor-only, opinion or unverified claim | AZ58: 1 | BA58: 0 | BB58: https://lf-hyperledger.atlassian.net/wiki/spaces/HIRC/pages/19171362/Hyperledger+India+-+eBook | BC58: Not verified – check before citing | BE58: 2026-10-15
A59: S20 | B59: Seed distribution on blockchain | C59: Tracks seed supply orders and distribution to farmers with Aadhaar/OTP checks | D59: active | E59: State | F59: Ministry / department | G59: Directorate of Agriculture | H59: Jharkhand | I59: State / UT government | J59: IN-JH | K59: Jharkhand | L59: State | M59: Eastern | N59: 20 | O59: Agriculture & Trade | P59: 4 | Q59: Economic affairs | R59: Supply-chain traceability | S59: Lack of traceability / counterfeits | T59: G2C | U59: Not stated | V59: Not disclosed | W59: Not disclosed | X59: Not disclosed | Y59: SettleMint | Z59: Private technology vendor | AA59: No | AB59: Implemented | AC59: Live | AD59: Production system | AE59: 2026-06-14 | AF59: 2022 | AJ59: 2022 | AM59: 2026-06-14 | AO59: 0.3 | AP59: 3 lakh+ farmers; 600 LAMPS/PACS; 160 FPOs; ~30,000 quintals | AQ59: Medium (10,000–10 lakh) | AW59: 0 | AX59: 3 | AY59: 3 – Mainstream news | AZ59: 7 | BA59: 0 | BB59: https://krishijagran.com/agriculture-world/jharkhand-becomes-first-state-in-india-to-distribute-seed-to-farmers-via-blockchain-tech/ | BE59: 2026-10-15
A60: S21 | B60: Property records on NIC Property Chain (NBF pilot) | C60: Property transactions recorded for verification | D60: active | E60: State | F60: Ministry / department | G60: Department of Revenue | H60: Jharkhand | I60: State / UT government | J60: IN-JH | K60: Jharkhand | L60: State | M60: Eastern | N60: 20 | O60: Land & Property | P60: 1 | Q60: General public services | R60: Land / property registry | S60: Land fraud & disputes | T60: G2C | U60: Permissioned (NIC) | V60: NIC chains (Hyperledger-based) | W60: Hyperledger family | X60: Permissioned | Y60: NIC | Z60: Government IT (NIC / C-DAC / NeGD) | AA60: Yes | AB60: Implemented | AC60: Live | AD60: Live but small scale | AE60: 2026-10-14 | AF60: 2024 | AG60: 2024 | AJ60: 2024-07-23 | AM60: 2026-10-14 | AO60: 0.0 | AP60: 4,474 documents; 31 verifications (NIC statistics, 2026-10-14) | AQ60: Small (<10,000) | AR60: 4474 | AS60: 31 | AT60: 2026-10-14 | AW60: 0 | AX60: 5 | AY60: 5 – Official source with live/current data | AZ60: 4 | BA60: 3 | BB60: https://blockchain.gov.in/Home/Home | BE60: 2026-10-15
A61: S22 | B61: Aushada – drug logistics chain | C61: Drug movement manufacturer→warehouse→hospital with quality checks; smart contracts block non-standard drugs; patients can check drug details | D61: active | E61: State | F61: PSU / state-owned company | G61: Karnataka State Medical Supplies Corporation Ltd (formerly KSDLWS) | H61: Karnataka | I61: State / UT government | J61: IN-KA | K61: Karnataka | L61: State | M61: Southern | N61: 29 | O61: Health & Supply Chain | P61: 7 | Q61: Health | R61: Supply-chain traceability | S61: Lack of traceability / counterfeits | T61: G2G | U61: Permissioned (NIC NBF) | V61: NIC chains (Hyperledger-based) | W61: Hyperledger family | X61: Permissioned | Y61: NIC | Z61: Government IT (NIC / C-DAC / NeGD) | AA61: Yes | AB61: Implemented | AC61: Live | AD61: Live | AE61: 2026-10-14 | AF61: 2019 | AJ61: 2021-04 | AM61: 2026-10-14 | AO61: 0.0 | AP61: 35,38,745 documents (NIC statistics, 2026-10-14) | AQ61: Large (≥10 lakh) | AR61: 3538745 | AS61: 0 | AT61: 2026-10-14 | AW61: 0 | AX61: 5 | AY61: 5 – Official source with live/current data | AZ61: 8 | BA61: 8 | BB61: https://blockchain.gov.in/Home/Home | BE61: 2026-10-15
A62: S23 | B62: Birth & death certificates on Document Chain | C62: Certificates recorded for verification | D62: active | E62: State | F62: Ministry / department | G62: Directorate of Economics & Statistics | H62: Karnataka | I62: State / UT government | J62: IN-KA | K62: Karnataka | L62: State | M62: Southern | N62: 29 | O62: Certificates & Identity | P62: 1 | Q62: General public services | R62: Certificates & identity | S62: Forgery / fake documents | T62: G2C | U62: Permissioned (NIC) | V62: NIC chains (Hyperledger-based) | W62: Hyperledger family | X62: Permissioned | Y62: NIC | Z62: Government IT (NIC / C-DAC / NeGD) | AA62: Yes | AB62: Implemented | AC62: Live | AD62: Live | AE62: 2026-10-14 | AF62: 2022 | AJ62: 2022-04 | AM62: 2026-10-14 | AO62: 0.0 | AP62: 68,20,431 documents; 37 verifications (NIC statistics, 2026-10-14) | AQ62: Large (≥10 lakh) | AR62: 6820431 | AS62: 37 | AT62: 2026-10-14 | AW62: 0 | AX62: 5 | AY62: 5 – Official source with live/current data | AZ62: 4 | BA62: 3 | BB62: https://blockchain.gov.in/Home/Home | BE62: 2026-10-15
A63: S24 | B63: Caste & income certificates on Document Chain | C63: Certificates recorded; used for professional-college admission checks | D63: active | E63: State | F63: Ministry / department | G63: Revenue Department | H63: Karnataka | I63: State / UT government | J63: IN-KA | K63: Karnataka | L63: State | M63: Southern | N63: 29 | O63: Certificates & Identity | P63: 1 | Q63: General public services | R63: Certificates & identity | S63: Forgery / fake documents | T63: G2C | U63: Permissioned (NIC) | V63: NIC chains (Hyperledger-based) | W63: Hyperledger family | X63: Permissioned | Y63: NIC | Z63: Government IT (NIC / C-DAC / NeGD) | AA63: Yes | AB63: Implemented | AC63: Live | AD63: Live | AE63: 2026-10-14 | AF63: 2018 | AJ63: 2018-01 | AM63: 2026-10-14 | AO63: 0.0 | AP63: 4,24,82,055 documents; 2 verifications (NIC statistics, 2026-10-14) | AQ63: Large (≥10 lakh) | AR63: 42482055 | AS63: 2 | AT63: 2026-10-14 | AW63: 0 | AX63: 5 | AY63: 5 – Official source with live/current data | AZ63: 4 | BA63: 3 | BB63: https://blockchain.gov.in/Home/Home | BE63: 2026-10-15
A64: S25 | B64: SSLC & PUC marks on Certificate Chain | C64: Exam results stored for verification (planned for admissions, scheme eligibility, recruitment checks) | D64: active | E64: State | F64: Statutory board / authority | G64: Karnataka School Examination and Assessment Board | H64: Karnataka | I64: State / UT government | J64: IN-KA | K64: Karnataka | L64: State | M64: Southern | N64: 29 | O64: Education & Skills | P64: 9 | Q64: Education | R64: Certificates & identity | S64: Forgery / fake documents | T64: G2C | U64: Permissioned (NIC) | V64: NIC chains (Hyperledger-based) | W64: Hyperledger family | X64: Permissioned | Y64: NIC | Z64: Government IT (NIC / C-DAC / NeGD) | AA64: Yes | AB64: Implemented | AC64: Live | AD64: Live | AE64: 2026-10-14 | AF64: 2020 | AJ64: 2020 | AM64: 2026-10-14 | AO64: 0.0 | AP64: 1,43,97,704 documents; 1,258 verifications (NIC statistics, 2026-10-14) | AQ64: Large (≥10 lakh) | AR64: 14397704 | AS64: 1258 | AT64: 2026-10-14 | AW64: 0 | AX64: 5 | AY64: 5 – Official source with live/current data | AZ64: 5 | BA64: 4 | BB64: https://blockchain.gov.in/Home/Home | BE64: 2026-10-15
A65: S26 | B65: Property records on NIC Property Chain | C65: Bhoomi, e-Aasthi and e-Swathu integrated; full property history (pledge, mutation, sale, gift) visible to stakeholders | D65: active | E65: State | F65: Ministry / department | G65: Revenue Department (Bhoomi land records) | H65: Karnataka | I65: State / UT government | J65: IN-KA | K65: Karnataka | L65: State | M65: Southern | N65: 29 | O65: Land & Property | P65: 1 | Q65: General public services | R65: Land / property registry | S65: Land fraud & disputes | T65: G2C | U65: Permissioned (NIC) | V65: NIC chains (Hyperledger-based) | W65: Hyperledger family | X65: Permissioned | Y65: NIC | Z65: Government IT (NIC / C-DAC / NeGD) | AA65: Yes | AB65: Implemented | AC65: Live | AD65: Live – by far the largest govt blockchain use in India | AE65: 2026-10-14 | AF65: 2024 | AG65: 2024 | AJ65: 2024-07-23 | AM65: 2026-10-14 | AO65: 0.0 | AP65: 2,11,88,847 documents; 47,50,45,928 verifications (NIC statistics, 2026-10-14) | AQ65: Large (≥10 lakh) | AR65: 21188847 | AS65: 475045928 | AT65: 2026-10-14 | AW65: 0 | AX65: 5 | AY65: 5 – Official source with live/current data | AZ65: 11 | BA65: 7 | BB65: https://blockchain.gov.in/Home/Home | BE65: 2026-10-15
A66: S28 | B66: Kaveri blockchain + digital wallet for land records | C66: Smartcards and key-secured wallet tracking 67 types of property transactions | D66: active | E66: State | F66: IT / e-governance agency | G66: Centre for Smart Governance (CSG) | H66: Karnataka | I66: State / UT government | J66: IN-KA | K66: Karnataka | L66: State | M66: Southern | N66: 29 | O66: Land & Property | P66: 1 | Q66: General public services | R66: Land / property registry | S66: Land fraud & disputes | T66: G2C | U66: Not stated | V66: Not disclosed | W66: Not disclosed | X66: Not disclosed | Y66: — | Z66: State IT agency (in-house) | AA66: No | AB66: In progress | AC66: In development | AD66: Under development | AE66: 2025-12 | AG66: 2021-01 | AH66: 2021 | AM66: 2025-12 | AO66: 0.8 | AP66: 67 transaction types | AQ66: Not reported | AW66: 0 | AX66: 4 | AY66: 4 – Official document (govt site, PIB, tender, court) | AZ66: 7 | BA66: 1 | BB66: https://igr.karnataka.gov.in/info-1/e+Governance+Initiatives/en | BC66: v1.1: Tumakuru pilot dated Dec 2021 found; no full rollout date found. | BE66: 2026-10-15
A67: S29 | B67: Permissioned blockchain trust layer for e-Government Procurement (e-GP) | C67: Link 50+ siloed e-procurement systems; validate supplier claims; tokenise bank guarantees; national supplier database | D67: active | E67: State | F67: IT / e-governance agency | G67: Centre for Smart Governance (CSG) with IIT Kanpur's CRUBN | H67: Karnataka | I67: State / UT government | J67: IN-KA | K67: Karnataka | L67: State | M67: Southern | N67: 29 | O67: Grievance & Records | P67: 1 | Q67: General public services | R67: Public procurement | S67: Supplier fraud & opacity in procurement | T67: G2B | U67: Permissioned | V67: Not disclosed | W67: Not disclosed | X67: Permissioned | Y67: CRUBN (IIT Kanpur) | Z67: Academic / research partner | AA67: No | AB67: Unclear (no recent update) | AC67: Unclear | AD67: Partnership announced; no rollout reported | AE67: 2025-12 | AF67: 2021 | AG67: 2021-11-18 | AM67: 2025-12 | AO67: 0.8 | AP67: 50+ e-GP systems targeted | AQ67: Not reported | AW67: 0 | AX67: 4 | AY67: 4 – Official document (govt site, PIB, tender, court) | AZ67: 3 | BA67: 1 | BB67: https://www.iitk.ac.in/crubn-partners-with-centre-for-smart-governance | BE67: 2026-10-15
A68: S30 | B68: Govt blockchain CoE (Blockchain Garage, Decentralized Lab) | C68: Builds public-good blockchain solutions and trains officials | D68: active | E68: State | F68: University / research institute | G68: Kerala Blockchain Academy (Digital University Kerala) | H68: Kerala | I68: State / UT government | J68: IN-KL | K68: Kerala | L68: State | M68: Southern | N68: 32 | O68: Platform & Infrastructure | P68: 1 | Q68: General public services | R68: Platform / ecosystem | S68: Capacity & shared infrastructure | T68: G2G | U68: Hyperledger Fabric, Ethereum | V68: Hyperledger Fabric | W68: Hyperledger family | X68: Permissioned | Y68: — | Z68: Academic / research partner | AA68: No | AB68: Implemented | AC68: Live | AD68: Active | AE68: 2025-12-12 | AF68: 2017 | AG68: 2017-03-07 | AJ68: 2017 | AM68: 2025-12-12 | AO68: 0.8 | AQ68: Not reported | AW68: 0 | AX68: 4 | AY68: 4 – Official document (govt site, PIB, tender, court) | AZ68: 3 | BA68: 2 | BB68: https://kba.ai/about-kba/ | BE68: 2026-10-15
A69: S31 | B69: Immunochain – vaccine traceability | C69: Tracks vaccines through cold chain to the beneficiary | D69: active | E69: State | F69: University / research institute | G69: Kerala Blockchain Academy | H69: Kerala | I69: State / UT government | J69: IN-KL | K69: Kerala | L69: State | M69: Southern | N69: 32 | O69: Health & Supply Chain | P69: 7 | Q69: Health | R69: Supply-chain traceability | S69: Lack of traceability / counterfeits | T69: G2G | U69: Not stated | V69: Not disclosed | W69: Not disclosed | X69: Not disclosed | Y69: — | Z69: Academic / research partner | AA69: No | AB69: Unclear (no recent update) | AC69: Unclear | AD69: Award-winning solution; deployment scale not published | AE69: 2023-10 | AF69: 2019 | AG69: 2018-11-30 | AM69: 2023-10 | AO69: 3.0 | AP69: CM's Award for Innovation in Public Policy 2020 | AQ69: Not reported | AW69: 0 | AX69: 4 | AY69: 4 – Official document (govt site, PIB, tender, court) | AZ69: 5 | BA69: 4 | BB69: https://kba.ai/immunochain/ | BE69: 2026-10-15
A70: S32 | B70: Pilots in land records, workforce, immunisation, organic food traceability | C70: Five-year plan for blockchain pilots | D70: active | E70: State | F70: Government (whole of government) | G70: Govt of Kerala | H70: Kerala | I70: State / UT government | J70: IN-KL | K70: Kerala | L70: State | M70: Southern | N70: 32 | O70: Platform & Infrastructure | P70: 1 | Q70: General public services | R70: Platform / ecosystem | S70: Capacity & shared infrastructure | T70: G2G | U70: Not stated | V70: Not disclosed | W70: Not disclosed | X70: Not disclosed | Y70: — | Z70: Not disclosed | AA70: No | AB70: Unclear (no recent update) | AC70: Unclear | AD70: Announced as plans | AE70: 2020-01-09 | AF70: 2018 | AG70: 2020-01 | AM70: 2020-01-09 | AO70: 6.8 | AQ70: Not reported | AW70: 0 | AX70: 3 | AY70: 3 – Mainstream news | AZ70: 2 | BA70: 0 | BB70: https://inc42.com/buzz/blockchain-this-week-kerala-government-projects-ant-financial-targets-enterprise-blockchain-more/ | BE70: 2026-10-15
A71: S33 | B71: Blockchain land registration | C71: Tamper-proof ledger for land registration | D71: active | E71: State | F71: Ministry / department | G71: Registration Department | H71: Kerala | I71: State / UT government | J71: IN-KL | K71: Kerala | L71: State | M71: Southern | N71: 32 | O71: Land & Property | P71: 1 | Q71: General public services | R71: Land / property registry | S71: Land fraud & disputes | T71: G2C | U71: Not stated | V71: Not disclosed | W71: Not disclosed | X71: Not disclosed | Y71: — | Z71: Not disclosed | AA71: No | AB71: Proposed / Planned | AC71: Planned | AD71: Announced by CM | AE71: 2026-01-27 | AF71: 2026 | AG71: 2026-01-04 | AM71: 2026-01-27 | AO71: 0.7 | AQ71: Not reported | AW71: 0 | AX71: 4 | AY71: 4 – Official document (govt site, PIB, tender, court) | AZ71: 4 | BA71: 1 | BB71: https://www.keralapsc.gov.in/sri-pinarayi-vijayan-honchief-minister-kerala-inagurated-kerala-public-service-commission-block | BC71: v1.1: official Kerala PSC page on the launch found. | BE71: 2026-10-15
A72: S34 | B72: Blockchain-as-a-Service platform for MP | C72: RFP to design, build and run a state BaaS platform | D72: active | E72: State | F72: IT / e-governance agency | G72: MP State Electronics Development Corporation (MPSEDC) | H72: Madhya Pradesh | I72: State / UT government | J72: IN-MP | K72: Madhya Pradesh | L72: State | M72: Central | N72: 23 | O72: Platform & Infrastructure | P72: 1 | Q72: General public services | R72: Platform / ecosystem | S72: Capacity & shared infrastructure | T72: G2G | U72: To be selected | V72: Not disclosed | W72: Not disclosed | X72: Not disclosed | Y72: — | Z72: Not disclosed | AA72: No | AB72: In progress | AC72: In development | AD72: Tendered (bids closed 14 Nov 2025); award not confirmed | AE72: 2025-11-14 | AF72: 2025 | AG72: 2025-09-22 | AM72: 2025-11-14 | AO72: 0.9 | AQ72: Not reported | AW72: 0 | AX72: 2 | AY72: 2 – Trade/crypto press or secondary (eBook, deck, blog) | AZ72: 1 | BA72: 0 | BB72: https://tenderdekho.com/tender-detail/td-1br73DkHir | BC72: Check award on MP e-tender portal | BE72: 2026-10-15
A73: S35 | B73: Citizen apps on Praamaanik | C73: 14 state citizen apps verified on national Praamaanik | D73: active | E73: State | F73: IT / e-governance agency | G73: MPSEDC | H73: Madhya Pradesh | I73: State / UT government | J73: IN-MP | K73: Madhya Pradesh | L73: State | M73: Central | N73: 23 | O73: Telecom & Cyber | P73: 4 | Q73: Economic affairs | R73: Authentication & anti-fraud | S73: Fraud / spam / fake apps | T73: G2C | U73: Permissioned (NBF) | V73: NIC chains (Hyperledger-based) | W73: Hyperledger family | X73: Permissioned | Y73: MeitY | Z73: Government IT (NIC / C-DAC / NeGD) | AA73: Yes | AB73: Implemented | AC73: Live | AD73: Onboarded | AE73: 2026-03-27 | AF73: 2025 | AG73: 2025 | AM73: 2026-03-27 | AO73: 0.6 | AP73: 14 apps | AQ73: Small (<10,000) | AW73: 0 | AX73: 5 | AY73: 5 – Official source with live/current data | AZ73: 3 | BA73: 1 | BB73: https://www.pib.gov.in/PressReleasePage.aspx?PRID=2246221&reg=3&lang=1 | BE73: 2026-10-15
A74: S36 | B74: Blockchain digital certificate platform | C74: Platform built by MP society; used by BSEH Haryana | D74: merged | E74: State | F74: Society / foundation | G74: CRISP Bhopal (state society) | H74: Madhya Pradesh | I74: State / UT government | J74: IN-MP | K74: Madhya Pradesh | L74: State | M74: Central | N74: 23 | O74: Education & Skills | P74: 9 | Q74: Education | R74: Certificates & identity | S74: Forgery / fake documents | T74: G2C | U74: Public blockchain | V74: Not disclosed | W74: Not disclosed | X74: Public | Y74: — | Z74: State IT agency (in-house) | AA74: No | AB74: Unclear (no recent update) | AC74: Unclear | AD74: Provider side of the S17 agreement (Jun 2023); no evidence of certificates issued | AE74: 2023-06-22 | AF74: 2023 | AG74: 2023-06-22 | AM74: 2023-06-22 | AO74: 3.3 | AQ74: Not reported | AW74: 0 | AX74: 4 | AY74: 4 – Official document (govt site, PIB, tender, court) | AZ74: 2 | BA74: 1 | BB74: https://crisp.mp.gov.in/news/235-haryana-government-will-give-digital-certificates-to-5-lakh-students-by-crisp-s-developed-blockchain-technology | BC74: Same June 2023 agreement as S17 (CRISP is the provider; BSEH is the client). Kept as a separate row for continuity with v1.0.0; exclude one of the two when counting distinct initiatives. | BD74: S17 | BE74: 2026-10-15
A75: S37 | B75: State blockchain framework & sandbox | C75: Common framework; pilots in health, supply chain, documents; planned agri marketing, vehicle registration, SSC certificates | D75: active | E75: State | F75: Ministry / department | G75: Maharashtra IT Directorate | H75: Maharashtra | I75: State / UT government | J75: IN-MH | K75: Maharashtra | L75: State | M75: Western | N75: 27 | O75: Platform & Infrastructure | P75: 1 | Q75: General public services | R75: Platform / ecosystem | S75: Capacity & shared infrastructure | T75: G2G | U75: Not stated | V75: Not disclosed | W75: Not disclosed | X75: Not disclosed | Y75: — | Z75: State IT agency (in-house) | AA75: No | AB75: Unclear (no recent update) | AC75: Unclear | AD75: Sandbox launched 2020; no later status | AE75: 2020-02-08 | AF75: 2019 | AG75: 2019-08 | AI75: 2019 | AM75: 2020-02-08 | AO75: 6.7 | AP75: ₹10 crore over 18 months | AQ75: Not reported | AW75: 0 | AX75: 3 | AY75: 3 – Mainstream news | AZ75: 2 | BA75: 0 | BB75: https://inc42.com/buzz/maharashtra-launches-blockchain-sandbox-for-e-governance/ | BE75: 2026-10-15
A76: S39 | B76: Skill/diploma certificates on blockchain | C76: Tamper-proof diploma certificates with digital verification | D76: active | E76: State | F76: Statutory board / authority | G76: Maharashtra State Board of Skill Development | H76: Maharashtra | I76: State / UT government | J76: IN-MH | K76: Maharashtra | L76: State | M76: Western | N76: 27 | O76: Education & Skills | P76: 9 | Q76: Education | R76: Certificates & identity | S76: Forgery / fake documents | T76: G2C | U76: Ethereum/Polygon (LegitDoc) | V76: Polygon | W76: Ethereum / EVM chains | X76: Public | Y76: LegitDoc | Z76: Private technology vendor | AA76: No | AB76: Unclear (no recent update) | AC76: Unclear | AD76: Announced 2021; no later status found | AE76: 2021-07-27 | AF76: 2021 | AG76: 2021-07-27 | AM76: 2021-07-27 | AO76: 5.2 | AQ76: Not reported | AW76: 0 | AX76: 3 | AY76: 3 – Mainstream news | AZ76: 2 | BA76: 0 | BB76: https://www.deccanherald.com/india/gadchiroli-to-use-blockchain-to-authenticate-caste-certificates-report-1097491.html | BE76: 2026-10-15
A77: S40 | B77: Certificates on NIC Certificate Chain | C77: Health-science degrees/certificates verifiable online | D77: active | E77: State | F77: University / research institute | G77: Maharashtra University of Health Sciences (MUHS) | H77: Maharashtra | I77: State / UT government | J77: IN-MH | K77: Maharashtra | L77: State | M77: Western | N77: 27 | O77: Education & Skills | P77: 9 | Q77: Education | R77: Certificates & identity | S77: Forgery / fake documents | T77: G2C | U77: Permissioned (NIC) | V77: NIC chains (Hyperledger-based) | W77: Hyperledger family | X77: Permissioned | Y77: NIC | Z77: Government IT (NIC / C-DAC / NeGD) | AA77: Yes | AB77: Implemented | AC77: Live | AD77: Live | AE77: 2026-10-14 | AJ77: 2026-10-03 | AM77: 2026-10-14 | AO77: 0.0 | AP77: 31,760 documents; 6,460 verifications (NIC statistics, 2026-10-14) | AQ77: Medium (10,000–10 lakh) | AR77: 31760 | AS77: 6460 | AT77: 2026-10-14 | AW77: 0 | AX77: 5 | AY77: 5 – Official source with live/current data | AZ77: 4 | BA77: 3 | BB77: https://blockchain.gov.in/Home/Home | BE77: 2026-10-15
A78: S41 | B78: Certificates on NIC Certificate Chain | C78: Nursing/paramedical certificates verifiable online | D78: active | E78: State | F78: Statutory board / authority | G78: Maharashtra State Board of Nursing & Paramedical Education | H78: Maharashtra | I78: State / UT government | J78: IN-MH | K78: Maharashtra | L78: State | M78: Western | N78: 27 | O78: Education & Skills | P78: 9 | Q78: Education | R78: Certificates & identity | S78: Forgery / fake documents | T78: G2C | U78: Permissioned (NIC) | V78: NIC chains (Hyperledger-based) | W78: Hyperledger family | X78: Permissioned | Y78: NIC | Z78: Government IT (NIC / C-DAC / NeGD) | AA78: Yes | AB78: Implemented | AC78: Live | AD78: Live | AE78: 2026-10-14 | AG78: 2025-07-04 | AJ78: 2025-07 | AM78: 2026-10-14 | AN78: 0 | AO78: 0.0 | AP78: 2,02,444 documents; 10,783 verifications (NIC statistics, 2026-10-14) | AQ78: Medium (10,000–10 lakh) | AR78: 202444 | AS78: 10783 | AT78: 2026-10-14 | AW78: 0 | AX78: 5 | AY78: 5 – Official source with live/current data | AZ78: 6 | BA78: 6 | BB78: https://blockchain.gov.in/Home/Home | BE78: 2026-10-15
A79: S42 | B79: Documents on NIC Document Chain | C79: Govt documents recorded for verification | D79: active | E79: State | F79: Ministry / department | G79: General Administration Department | H79: Maharashtra | I79: State / UT government | J79: IN-MH | K79: Maharashtra | L79: State | M79: Western | N79: 27 | O79: Certificates & Identity | P79: 1 | Q79: General public services | R79: Certificates & identity | S79: Forgery / fake documents | T79: G2C | U79: Permissioned (NIC) | V79: NIC chains (Hyperledger-based) | W79: Hyperledger family | X79: Permissioned | Y79: NIC | Z79: Government IT (NIC / C-DAC / NeGD) | AA79: Yes | AB79: Implemented | AC79: Live | AD79: Live (small scale) | AE79: 2026-10-14 | AJ79: 2026-06-15 | AM79: 2026-10-14 | AO79: 0.0 | AP79: 1,005 documents; 73 verifications (NIC statistics, 2026-10-14) | AQ79: Small (<10,000) | AR79: 1005 | AS79: 73 | AT79: 2026-10-14 | AW79: 0 | AX79: 5 | AY79: 5 – Official source with live/current data | AZ79: 4 | BA79: 4 | BB79: https://blockchain.gov.in/Home/Home | BC79: Confirm document type | BE79: 2026-10-15
A80: S44 | B80: COVID-19 test certificates on blockchain | C80: Negative RT-PCR reports and universal passes issued with blockchain proof and QR verification | D80: active | E80: State | F80: Ministry / department | G80: Dept of Disaster Management, Relief & Rehabilitation (DMRR) | H80: Maharashtra | I80: State / UT government | J80: IN-MH | K80: Maharashtra | L80: State | M80: Western | N80: 27 | O80: Health & Supply Chain | P80: 7 | Q80: Health | R80: Certificates & identity | S80: Forgery / fake documents | T80: G2C | U80: Private DocChain + Polygon audit | V80: Polygon | W80: Ethereum / EVM chains | X80: Hybrid (private + public anchor) | Y80: Print2Block | Z80: Private technology vendor | AA80: No | AB80: Implemented | AC80: Live | AD80: Used during COVID-19; verification portal online | AE80: 2021-08-12 | AF80: 2021 | AJ80: 2021-05 | AM80: 2021-08-12 | AO80: 5.2 | AQ80: Not reported | AU80: T2;T3 | AV80: Technology | AW80: 2 | AX80: 4 | AY80: 4 – Official document (govt site, PIB, tender, court) | AZ80: 6 | BA80: 2 | BB80: https://block.dmrr.mahaonline.gov.in/report?id=2e63e5ad7e1ae7f4fa8568e8cdb49dec4ac701f9469e7289ba84d1ddb2dc385b | BC80: COVID-era service – may be retired | BE80: 2026-10-15
A81: S45 | B81: State Asset Tokenisation Framework & blockchain land-registry pilots | C81: Tokenise public/private assets; pilot blockchain land registry; secure asset registries | D81: active | E81: State | F81: Policy / planning body | G81: Maharashtra Institution for Transformation (MITRA) | H81: Maharashtra | I81: State / UT government | J81: IN-MH | K81: Maharashtra | L81: State | M81: Western | N81: 27 | O81: Land & Property | P81: 1 | Q81: General public services | R81: Tokenisation / NFTs | S81: Asset liquidity / digital ownership | T81: G2B | U81: Not disclosed | V81: Not disclosed | W81: Not disclosed | X81: Not disclosed | Y81: Infraledger Labs | Z81: Private technology vendor | AA81: No | AB81: Proposed / Planned | AC81: Planned | AD81: MoU signed; framework under development | AE81: 2026-09-11 | AF81: 2025 | AG81: 2025-10-09 | AM81: 2026-09-11 | AO81: 0.1 | AP81: Target ~₹50 trillion of assets | AQ81: Not reported | AU81: E1;O4 | AV81: Environment;Organisation | AW81: 2 | AX81: 3 | AY81: 3 – Mainstream news | AZ81: 7 | BA81: 0 | BB81: https://www.business-standard.com/finance/news/maharashtra-to-launch-asset-tokenisation-framework-says-fadnavis-125100901370_1.html | BE81: 2026-10-15
A82: S47 | B82: Academic Credential Verification System on Internet Computer | C82: Store and verify academic certificates with privacy-preserving login | D82: active | E82: State | F82: Ministry / department | G82: Department of Education | H82: Manipur | I82: State / UT government | J82: IN-MN | K82: Manipur | L82: State | M82: North-Eastern | N82: 14 | O82: Education & Skills | P82: 9 | Q82: Education | R82: Certificates & identity | S82: Forgery / fake documents | T82: G2C | U82: Internet Computer (ICP) | V82: Internet Computer (ICP) | W82: Other public chains | X82: Public | Y82: DFINITY Foundation, The Horizon | Z82: Private technology vendor | AA82: No | AB82: Unclear (no recent update) | AC82: Unclear | AD82: Announced; no deployment update | AE82: 2023-12-07 | AF82: 2023 | AG82: 2023-12-07 | AM82: 2023-12-07 | AO82: 2.9 | AQ82: Not reported | AW82: 0 | AX82: 3 | AY82: 3 – Mainstream news | AZ82: 1 | BA82: 0 | BB82: https://www.business-standard.com/content/press-releases-ani/manipur-education-department-embraces-blockchain-technology-on-icp-123120701068_1.html | BE82: 2026-10-15
A83: S48 | B83: Higher Secondary mark statements on NIC Certificate Chain | C83: Mark statements available for verification | D83: active | E83: State | F83: Statutory board / authority | G83: Council of Higher Secondary Education, Manipur | H83: Manipur | I83: State / UT government | J83: IN-MN | K83: Manipur | L83: State | M83: North-Eastern | N83: 14 | O83: Education & Skills | P83: 9 | Q83: Education | R83: Certificates & identity | S83: Forgery / fake documents | T83: G2C | U83: Permissioned (NIC) | V83: NIC chains (Hyperledger-based) | W83: Hyperledger family | X83: Permissioned | Y83: NIC | Z83: Government IT (NIC / C-DAC / NeGD) | AA83: Yes | AB83: Implemented | AC83: Live | AD83: Live | AE83: 2026-10-14 | AF83: 2022 | AJ83: 2022-09-08 | AM83: 2026-10-14 | AO83: 0.0 | AP83: 79,614 documents; 59 verifications (NIC statistics, 2026-10-14) | AQ83: Medium (10,000–10 lakh) | AR83: 79614 | AS83: 59 | AT83: 2026-10-14 | AW83: 0 | AX83: 5 | AY83: 5 – Official source with live/current data | AZ83: 5 | BA83: 4 | BB83: https://blockchain.gov.in/Home/Home | BE83: 2026-10-15
A84: S49 | B84: Blockchain employee data & promotion tracking | C84: Tracks recruitment and promotion records, starting with Police | D84: active | E84: State | F84: Ministry / department | G84: IT & Communications Dept with NeGD | H84: Meghalaya | I84: State / UT government | J84: IN-ML | K84: Meghalaya | L84: State | M84: North-Eastern | N84: 17 | O84: Grievance & Records | P84: 1 | Q84: General public services | R84: Records & audit trail | S84: Tampering of records | T84: G2G | U84: Not stated | V84: Not disclosed | W84: Not disclosed | X84: Not disclosed | Y84: NeGD | Z84: Government IT (NIC / C-DAC / NeGD) | AA84: No | AB84: Proposed / Planned | AC84: Planned | AD84: Announced by CM | AE84: 2025-04-25 | AF84: 2025 | AG84: 2025-04 | AM84: 2025-04-25 | AO84: 1.5 | AQ84: Not reported | AW84: 0 | AX84: 3 | AY84: 3 – Mainstream news | AZ84: 1 | BA84: 0 | BB84: https://www.sentinelassam.com/north-east-india-news/meghalaya-news/meghalaya-to-launch-blockchain-employee-data-base | BE84: 2026-10-15
A85: S50 | B85: Blockchain-as-a-Service platform for Odisha | C85: State BaaS for academic credentials, eDistrict certificates, IGR land registration data and sandbox | D85: active | E85: State | F85: IT / e-governance agency | G85: Odisha Computer Application Centre (OCAC) | H85: Odisha | I85: State / UT government | J85: IN-OD | K85: Odisha | L85: State | M85: Eastern | N85: 21 | O85: Platform & Infrastructure | P85: 1 | Q85: General public services | R85: Platform / ecosystem | S85: Capacity & shared infrastructure | T85: G2G | U85: To be selected | V85: Not disclosed | W85: Not disclosed | X85: Not disclosed | Y85: — | Z85: Not disclosed | AA85: No | AB85: In progress | AC85: In development | AD85: RFP issued; 60-month plan (pilot at 8 months) | AE85: 2025-02-13 | AF85: 2023 | AG85: 2023-12-14 | AM85: 2025-02-13 | AO85: 1.7 | AQ85: Not reported | AW85: 0 | AX85: 4 | AY85: 4 – Official document (govt site, PIB, tender, court) | AZ85: 2 | BA85: 1 | BB85: https://odisha.gov.in/sites/default/files/2023-12/RFP-23123_14.12.2023.pdf | BC85: Check award status | BE85: 2026-10-15
A86: S51 | B86: Shakti app – blockchain record for GBV survivors | C86: Survivor data shared securely across shelters and One Stop Centres | D86: active | E86: State | F86: Ministry / department | G86: Women & Child Development Dept with UNFPA | H86: Odisha | I86: State / UT government | J86: IN-OD | K86: Odisha | L86: State | M86: Eastern | N86: 21 | O86: Welfare & Subsidy | P86: 10 | Q86: Social protection | R86: Welfare delivery | S86: Leakage / beneficiary fraud | T86: G2G | U86: Not stated | V86: Not disclosed | W86: Not disclosed | X86: Not disclosed | Y86: UNFPA | Z86: International organisation | AA86: No | AB86: In progress | AC86: In development | AD86: Pilot in 5 districts; statewide planned | AE86: 2024-12-11 | AF86: 2024 | AJ86: 2024-12 | AM86: 2024-12-11 | AO86: 1.8 | AP86: 5 districts | AQ86: Not reported | AW86: 0 | AX86: 2 | AY86: 2 – Trade/crypto press or secondary (eBook, deck, blog) | AZ86: 1 | BA86: 0 | BB86: https://www.cointrust.com/market-news/odisha-pioneers-blockchain-technology-to-combat-gender-based-violence | BE86: 2026-10-15
A87: S52 | B87: AI & blockchain handloom hubs (Cuttack, Bargarh, Jajpur) | C87: Blockchain traceability for handloom supply chain | D87: active | E87: State | F87: Ministry / department | G87: Handloom, Textiles & Construction Depts | H87: Odisha | I87: State / UT government | J87: IN-OD | K87: Odisha | L87: State | M87: Eastern | N87: 21 | O87: Agriculture & Trade | P87: 4 | Q87: Economic affairs | R87: Supply-chain traceability | S87: Lack of traceability / counterfeits | T87: G2B | U87: Not stated | V87: Not disclosed | W87: Not disclosed | X87: Not disclosed | Y87: — | Z87: Not disclosed | AA87: No | AB87: Proposed / Planned | AC87: Planned | AD87: Proposal stage | AE87: 2026-05-23 | AF87: 2026 | AG87: 2026-05 | AM87: 2026-05-23 | AO87: 0.4 | AQ87: Not reported | AW87: 0 | AX87: 2 | AY87: 2 – Trade/crypto press or secondary (eBook, deck, blog) | AZ87: 1 | BA87: 0 | BB87: https://www.cointrust.com/market-news/indias-odisha-plans-ai-and-blockchain-handloom-hubs | BE87: 2026-10-15
A88: S53 | B88: Seed potato traceability & certification | C88: Geo-tagged, QR-coded seed potatoes tracked from nucleus to harvest | D88: active | E88: State | F88: Ministry / department | G88: Dept of Agriculture & Farmers Welfare with PAGREXCO | H88: Punjab | I88: State / UT government | J88: IN-PB | K88: Punjab | L88: State | M88: Northern | N88: 3 | O88: Agriculture & Trade | P88: 4 | Q88: Economic affairs | R88: Supply-chain traceability | S88: Lack of traceability / counterfeits | T88: G2B | U88: Not stated | V88: Not disclosed | W88: Not disclosed | X88: Not disclosed | Y88: CropIn | Z88: Private technology vendor | AA88: No | AB88: Unclear (no recent update) | AC88: Unclear | AD88: Planned for next season; no later update | AE88: 2019-07-30 | AF88: 2019 | AG88: 2019-07 | AM88: 2019-07-30 | AO88: 7.2 | AQ88: Not reported | AW88: 0 | AX88: 3 | AY88: 3 – Mainstream news | AZ88: 1 | BA88: 0 | BB88: https://www.potatopro.com/news/2019/punjab-introduce-seed-potato-tracebility-and-certification-using-blockchain-technology | BE88: 2026-10-15
A89: S54 | B89: Centre of Excellence in Blockchain | C89: CoE for transparent, secure e-governance apps | D89: active | E89: State | F89: Ministry / department | G89: Dept of IT & Communication with RVPN & IIT Kanpur | H89: Rajasthan | I89: State / UT government | J89: IN-RJ | K89: Rajasthan | L89: State | M89: Northern | N89: 8 | O89: Platform & Infrastructure | P89: 1 | Q89: General public services | R89: Platform / ecosystem | S89: Capacity & shared infrastructure | T89: G2G | U89: — | V89: Not disclosed | W89: Not disclosed | X89: Not disclosed | Y89: IIT Kanpur | Z89: Academic / research partner | AA89: No | AB89: In progress | AC89: In development | AD89: MoU signed | AE89: 2025-02-13 | AF89: 2024 | AG89: 2024-02 | AM89: 2025-02-13 | AO89: 1.7 | AQ89: Not reported | AW89: 0 | AX89: 3 | AY89: 3 – Mainstream news | AZ89: 2 | BA89: 0 | BB89: https://changingtomorrow.in/rajasthan-government-takes-strides-towards-digital-india-with-landmark-mou-on-blockchain-technology/ | BE89: 2026-10-15
A90: S55 | B90: Land records & health records on blockchain | C90: Plan for blockchain land titles; vendor claims EHR on blockchain | D90: active | E90: State | F90: Government (whole of government) | G90: Govt of Rajasthan | H90: Rajasthan | I90: State / UT government | J90: IN-RJ | K90: Rajasthan | L90: State | M90: Northern | N90: 8 | O90: Land & Property | P90: 1 | Q90: General public services | R90: Land / property registry | S90: Land fraud & disputes | T90: G2C | U90: Not stated | V90: Not disclosed | W90: Not disclosed | X90: Not disclosed | Y90: Auxesis Group | Z90: Private technology vendor | AA90: No | AB90: Unclear (no recent update) | AC90: Unclear | AD90: Vendor claim; no official confirmation | AE90: 2018-09-13 | AF90: 2018 | AG90: 2018-09 | AM90: 2018-09-13 | AO90: 8.1 | AP90: Vendor claims 53 million residents (EHR) | AQ90: Not reported | AW90: 0 | AX90: 1 | AY90: 1 – Vendor-only, opinion or unverified claim | AZ90: 1 | BA90: 0 | BB90: https://medium.com/auxesis/rajasthan-to-roll-out-blockchain-technology-for-land-records-80d181da4daa | BC90: Vendor source – verify | BE90: 2026-10-15
A91: S56 | B91: Nambikkai Inaiyam blockchain backbone + e-Pettagam app | C91: State Blockchain-as-a-Service: secures academic certificates, marksheets, 24 e-Sevai certificates and land transaction data; citizens share via e-Pettagam | D91: active | E91: State | F91: IT / e-governance agency | G91: TNeGA (IT Dept) | H91: Tamil Nadu | I91: State / UT government | J91: IN-TN | K91: Tamil Nadu | L91: State | M91: Southern | N91: 33 | O91: Certificates & Identity | P91: 1 | Q91: General public services | R91: Platform / ecosystem | S91: Capacity & shared infrastructure | T91: G2C | U91: Not stated | V91: Not disclosed | W91: Not disclosed | X91: Not disclosed | Y91: TNeGA | Z91: State IT agency (in-house) | AA91: No | AB91: Implemented | AC91: Live | AD91: Launched by IT Minister | AE91: 2025-12 | AF91: 2020 | AG91: 2020-09 | AJ91: 2023-06-13 | AM91: 2025-12 | AN91: 33 | AO91: 0.8 | AP91: 24 e-Sevai certificate types; ~₹40 crore earmarked | AQ91: Not reported | AW91: 0 | AX91: 4 | AY91: 4 – Official document (govt site, PIB, tender, court) | AZ91: 7 | BA91: 2 | BB91: https://it.tn.gov.in/sites/default/files/2025-08/it_e_pn_2025_26.pdf | BE91: 2026-10-15
A92: S57 | B92: Blockchain complaint & informant portal | C92: Complaints and tips cannot be deleted or altered | D92: active | E92: State | F92: Ministry / department | G92: TN Police – Idol Wing CID | H92: Tamil Nadu | I92: State / UT government | J92: IN-TN | K92: Tamil Nadu | L92: State | M92: Southern | N92: 33 | O92: Justice & Police | P92: 3 | Q92: Public order and safety | R92: Records & audit trail | S92: Tampering of records | T92: G2C | U92: Polygon (Ethereum) | V92: Polygon | W92: Ethereum / EVM chains | X92: Public | Y92: Polygon | Z92: Private technology vendor | AA92: No | AB92: Implemented | AC92: Live | AD92: Operational | AE92: 2023-01-13 | AF92: 2022 | AG92: 2022-12-01 | AJ92: 2022-12 | AM92: 2023-01-13 | AN92: 0 | AO92: 3.8 | AQ92: Not reported | AW92: 0 | AX92: 3 | AY92: 3 – Mainstream news | AZ92: 5 | BA92: 0 | BB92: https://www.dtnext.in/tamilnadu/2022/12/23/tn-idol-wing-now-uses-blockchain-tech-to-receive-inputs-complaints | BE92: 2026-10-15
A93: S58 | B93: Soulbound tokens as digital medals | C93: Non-transferable tokens awarded to officers and informants | D93: active | E93: State | F93: Ministry / department | G93: TN Police – Idol Wing CID | H93: Tamil Nadu | I93: State / UT government | J93: IN-TN | K93: Tamil Nadu | L93: State | M93: Southern | N93: 33 | O93: Grievance & Records | P93: 1 | Q93: General public services | R93: Tokenisation / NFTs | S93: Asset liquidity / digital ownership | T93: G2G | U93: Not stated | V93: Not disclosed | W93: Not disclosed | X93: Not disclosed | Y93: GuardianLink | Z93: Private technology vendor | AA93: No | AB93: Implemented | AC93: Live | AD93: Issued | AE93: 2023-01-13 | AF93: 2022 | AJ93: 2022-12-01 | AM93: 2023-01-13 | AO93: 3.8 | AQ93: Not reported | AW93: 0 | AX93: 3 | AY93: 3 – Mainstream news | AZ93: 4 | BA93: 0 | BB93: https://indianmasterminds.com/feature-stories-on-bureaucrats-changemakers/change-makers/tamil-nadu-police-first-in-the-world-to-adopt-blockchain-technology/ | BE93: 2026-10-15
A94: S59 | B94: Blockchain District, Hyderabad | C94: Ecosystem hub: CoE, incubators, skilling | D94: active | E94: State | F94: Ministry / department | G94: ITE&C Dept | H94: Telangana | I94: State / UT government | J94: IN-TS | K94: Telangana | L94: State | M94: Southern | N94: 36 | O94: Platform & Infrastructure | P94: 1 | Q94: General public services | R94: Platform / ecosystem | S94: Capacity & shared infrastructure | T94: G2B | U94: — | V94: Not disclosed | W94: Not disclosed | X94: Not disclosed | Y94: Tech Mahindra, IIIT-H, C-DAC | Z94: Government–industry consortium | AA94: No | AB94: Implemented | AC94: Live | AD94: Set up | AE94: 2025-01-04 | AF94: 2018 | AG94: 2018-08 | AJ94: 2018-08 | AM94: 2025-01-04 | AN94: 0 | AO94: 1.8 | AQ94: Not reported | AW94: 0 | AX94: 4 | AY94: 4 – Official document (govt site, PIB, tender, court) | AZ94: 6 | BA94: 1 | BB94: https://it.telangana.gov.in/initiatives/blockchain/ | BE94: 2026-10-15
A95: S60 | B95: T-Block Accelerator | C95: Blockchain startup accelerator | D95: active | E95: State | F95: Ministry / department | G95: ITE&C Dept | H95: Telangana | I95: State / UT government | J95: IN-TS | K95: Telangana | L95: State | M95: Southern | N95: 36 | O95: Platform & Infrastructure | P95: 1 | Q95: General public services | R95: Platform / ecosystem | S95: Capacity & shared infrastructure | T95: G2B | U95: — | V95: Not disclosed | W95: Not disclosed | X95: Not disclosed | Y95: IIIT-H, ISB, Tech Mahindra, Microsoft | Z95: Government–industry consortium | AA95: No | AB95: Implemented | AC95: Live | AD95: Run in 2020; official cited 'a dozen+' blockchain use cases in departments | AE95: 2021-12-17 | AF95: 2020 | AG95: 2020-02 | AJ95: 2020-06 | AM95: 2021-12-17 | AN95: 4 | AO95: 4.8 | AP95: 25 startups (phase 1) | AQ95: Not reported | AW95: 0 | AX95: 3 | AY95: 3 – Mainstream news | AZ95: 6 | BA95: 0 | BB95: https://inc42.com/buzz/telangana-aims-to-be-indias-blockchain-capital-with-new-incubators/ | BE95: 2026-10-15
A96: S61 | B96: Blockchain Property Registration Management System (Shamshabad) | C96: Integrated with state registration workflow to stop duplicate registrations, fake documents and insider tampering; called first of its kind in India | D96: active | E96: State | F96: Ministry / department | G96: Registration & Stamps Dept with MeitY & C-DAC Hyderabad | H96: Telangana | I96: State / UT government | J96: IN-TS | K96: Telangana | L96: State | M96: Southern | N96: 36 | O96: Land & Property | P96: 1 | Q96: General public services | R96: Land / property registry | S96: Land fraud & disputes | T96: G2C | U96: Not stated | V96: Not disclosed | W96: Not disclosed | X96: Not disclosed | Y96: C-DAC Hyderabad, IDRBT, IIT Hyderabad, NIC | Z96: Government IT (NIC / C-DAC / NeGD) | AA96: No | AB96: Unclear (no recent update) | AC96: Unclear | AD96: Piloted at Shamshabad SRO (Dec 2021); no later update found | AE96: 2021-12 | AF96: 2019 | AH96: 2017-06 | AM96: 2021-12 | AO96: 4.8 | AQ96: Not reported | AW96: 0 | AX96: 5 | AY96: 5 – Official source with live/current data | AZ96: 5 | BA96: 3 | BB96: https://blockchain.meity.gov.in/index.php/success-stories/13-blockchain-based-property-registration-management-system | BE96: 2026-10-15
A97: S62 | B97: Blockchain e-voting for municipal elections | C97: Vote data kept immutable on blockchain | D97: active | E97: State | F97: Election commission | G97: Telangana State Election Commission with C-DAC | H97: Telangana | I97: State / UT government | J97: IN-TS | K97: Telangana | L97: State | M97: Southern | N97: 36 | O97: Elections | P97: 1 | Q97: General public services | R97: E-voting | S97: Voter access & vote integrity | T97: G2C | U97: Not stated | V97: Not disclosed | W97: Not disclosed | X97: Not disclosed | Y97: C-DAC Mumbai & Hyderabad | Z97: Government IT (NIC / C-DAC / NeGD) | AA97: No | AB97: Pilot completed | AC97: Pilot completed | AD97: Dry run completed (Khammam, Oct 2021); not used in an actual election | AE97: 2021-10 | AH97: 2021-10 | AI97: 2021-10 | AM97: 2021-10 | AO97: 5.0 | AQ97: Not reported | AW97: 0 | AX97: 5 | AY97: 5 – Official source with live/current data | AZ97: 2 | BA97: 2 | BB97: https://blockchain.meity.gov.in/index.php/success-stories/11-evoting-ensuring-vote-data-immutability-through-blockchain | BE97: 2026-10-15
A98: S63 | B98: Class 10 / +2 certificates on blockchain | C98: Pilot to secure school certificates | D98: active | E98: State | F98: Ministry / department | G98: School Education Dept | H98: Telangana | I98: State / UT government | J98: IN-TS | K98: Telangana | L98: State | M98: Southern | N98: 36 | O98: Education & Skills | P98: 9 | Q98: Education | R98: Certificates & identity | S98: Forgery / fake documents | T98: G2C | U98: Not stated | V98: Not disclosed | W98: Not disclosed | X98: Not disclosed | Y98: — | Z98: Not disclosed | AA98: No | AB98: Unclear (no recent update) | AC98: Unclear | AD98: Announced as pilot | AE98: 2018-08-07 | AF98: 2018 | AG98: 2018-08 | AM98: 2018-08-07 | AO98: 8.2 | AQ98: Not reported | AW98: 0 | AX98: 4 | AY98: 4 – Official document (govt site, PIB, tender, court) | AZ98: 2 | BA98: 1 | BB98: https://it.telangana.gov.in/initiatives/blockchain/ | BE98: 2026-10-15
A99: S64 | B99: Blockchain beneficiary management system | C99: Stores scheme-wise approved beneficiary lists and transactions to stop tampering | D99: active | E99: State | F99: Ministry / department | G99: IT Department with NIC Blockchain CoE | H99: Tripura | I99: State / UT government | J99: IN-TR | K99: Tripura | L99: State | M99: North-Eastern | N99: 16 | O99: Welfare & Subsidy | P99: 10 | Q99: Social protection | R99: Welfare delivery | S99: Leakage / beneficiary fraud | T99: G2G | U99: Permissioned (NIC) | V99: NIC chains (Hyperledger-based) | W99: Hyperledger family | X99: Permissioned | Y99: NIC | Z99: Government IT (NIC / C-DAC / NeGD) | AA99: Yes | AB99: Implemented | AC99: Live | AD99: Operational | AE99: 2025-02 | AF99: 2023 | AJ99: 2023-08 | AM99: 2025-02 | AO99: 1.7 | AQ99: Not reported | AW99: 0 | AX99: 3 | AY99: 3 – Mainstream news | AZ99: 2 | BA99: 0 | BB99: https://inc42.com/buzz/tripura-blockchain-based-beneficiary-management-system-secure-data/ | BE99: 2026-10-15
A100: S65 | B100: Land & revenue records on blockchain | C100: Online mutation, registration and verification on blockchain | D100: active | E100: State | F100: Ministry / department | G100: Revenue Department | H100: Uttar Pradesh | I100: State / UT government | J100: IN-UP | K100: Uttar Pradesh | L100: State | M100: Central | N100: 9 | O100: Land & Property | P100: 1 | Q100: General public services | R100: Land / property registry | S100: Land fraud & disputes | T100: G2C | U100: Not stated | V100: Not disclosed | W100: Not disclosed | X100: Not disclosed | Y100: IIT Kanpur (knowledge partner) | Z100: Academic / research partner | AA100: No | AB100: Unclear (no recent update) | AC100: Unclear | AD100: 6-month directive in 2018; eBook says implemented; no official confirmation | AE100: 2025-02 | AF100: 2018 | AG100: 2018-07 | AM100: 2025-02 | AO100: 1.7 | AQ100: Not reported | AW100: 0 | AX100: 3 | AY100: 3 – Mainstream news | AZ100: 2 | BA100: 0 | BB100: https://www.business-standard.com/article/economy-policy/yogi-adityanath-govt-to-build-blockchain-architecture-for-data-security-118072200331_1.html | BC100: Sources conflict | BE100: 2026-10-15
...

Sheet Stage events
A1: event_id | B1: project_id | C1: event_type | D1: date | E1: date_precision | F1: source_id | G1: evidence | H1: recorded_by | I1: recorded_on
A2: C01-E01 | B2: C01 | C2: announced | D2: 2021-03 | E2: month | F2: R01 | G2: PIB backgrounder: National Blockchain Framework was initiated in March 2021 with a budget outlay of Rs 64.76 crore. | H2: AI-assisted research (Claude), reviewed by author | I2: 2026-10-15
A3: C01-E02 | B3: C01 | C3: live | D3: 2024-09-04 | E3: day | F3: R34 | G3: MeitY Secretary S. Krishnan launched Vishvasya stack offering BaaS on NIC data centres at Bhubaneswar, Pune and Hyderabad. | H3: AI-assisted research (Claude), reviewed by author | I3: 2026-10-15
A4: C01-E03 | B4: C01 | C4: latest_update | D4: 2026-10-03 | E4: day | F4: B01 | G4: NIC dashboard lists 6 live blockchain products and 4 PoCs; per dataset, as on 03-10-2026: 12 orgs/states, 22 departments. | H4: AI-assisted research (Claude), reviewed by author | I4: 2026-10-15
A5: C02-E01 | B5: C02 | C5: live | D5: 2024-09-04 | E5: day | F5: R34 | G5: NBFLite sandbox launched with Vishvasya stack for startups/academia for rapid prototyping, research and capacity building. | H5: AI-assisted research (Claude), reviewed by author | I5: 2026-10-15
A6: C02-E02 | B6: C02 | C6: latest_update | D6: 2025-10-24 | E6: day | F6: R01 | G6: PIB describes NBFLite as sandbox version of the stack encouraging innovation, experimentation and capacity building, with smart-contract templates. | H6: AI-assisted research (Claude), reviewed by author | I6: 2026-10-15
A7: C03-E01 | B7: C03 | C7: live | D7: 2024-09-04 | E7: day | F7: R34 | G7: Praamaanik, a blockchain-enabled solution for verifying mobile app origin, launched alongside Vishvasya stack. | H7: AI-assisted research (Claude), reviewed by author | I7: 2026-10-15
A8: C03-E02 | B8: C03 | C8: latest_update | D8: 2026-03-27 | E8: day | F8: N12 | G8: Rajya Sabha reply: 14 citizen-centric apps of MP State Electronics Development Corporation onboarded; users verify via M-Kavach-2 app. | H8: AI-assisted research (Claude), reviewed by author | I8: 2026-10-15
A9: C04-E01 | B9: C04 | C9: announced | D9: 2026-02-23 | E9: day | F9: N63 | G9: MeitY Secretary S. Krishnan launched Blockchain India Challenge, implemented by C-DAC, for DPIIT-recognised startups with government departments. | H9: AI-assisted research (Claude), reviewed by author | I9: 2026-10-15
A10: C04-E02 | B10: C04 | C10: latest_update | D10: 2026-03-27 | E10: day | F10: N12 | G10: Rajya Sabha reply sets out four-stage incentives: up to 40/30/20/10 entries receiving Rs 1.5 lakh/4 lakh/10 lakh/50 lakh. | H10: AI-assisted research (Claude), reviewed by author | I10: 2026-10-15
A11: C05-E01 | B11: C05 | C11: announced | D11: 2020-01-17 | E11: day | F11: W008 | G11: Report says Minister Ravi Shankar Prasad will inaugurate NIC's Blockchain CoE in Bengaluru tomorrow, offering Blockchain as a Service. | H11: AI-assisted research (Claude), reviewed by author | I11: 2026-10-15
A12: C05-E02 | B12: C05 | C12: live | D12: 2020-01-18 | E12: day | F12: W009 | G12: Ravi Shankar Prasad inaugurated NIC Centre of Excellence in Blockchain Technology in Bengaluru on Saturday (18 Jan 2020), providing BaaS. | H12: AI-assisted research (Claude), reviewed by author | I12: 2026-10-15
... A25: C10-E01 | B25: C10 | C25: latest_update | D25: 2026-10-03 | E25: day | F25: B01 | G25: Dashboard PoC list: Assam - Land Records, Blood Bank, GST Chain, Public Distribution System. | H25: AI-assisted research (Claude), reviewed by author | I25: 2026-10-15
A26: C10-E02 | B26: C10 | C26: announced | D26: 2023 | E26: year | F26: B01 | G26: Start/announcement date recorded in v1.0.0 ("2023–25"). | H26: v1.0.0 field | I26: 2026-10-15
A27: C11-E01 | B27: C11 | C27: live | D27: 2023 | E27: year | F27: R16 | G27: Onboarding table: Legal Metrology packaged-commodity registration (from 15/06/2023), W&M model approvals (01/01/2023), importer certificates (18/09/2023) on chain. | H27: AI-assisted research (Claude), reviewed by author | I27: 2026-10-15
A28: C11-E02 | B28: C11 | C28: latest_update | D28: 2026-10-03 | E28: day | F28: B01 | G28: Per dataset's reading of dashboard: Legal Metrology 22,709 documents, 16 verifications; tables load dynamically, not re-verified on 4 Oct 2026. | H28: AI-assisted research (Claude), reviewed by author | I28: 2026-10-15
A29: C11-E03 | B29: C11 | C29: latest_update | D29: 2026-10-14 | E29: day | F29: B11 | G29: NIC statistics file (data date 2026-10-14) lists Ministry of Consumer Affairs – Department of Consumer Affairs: 23,047 documents. | H29: Derived from official NIC snapshot | I29: 2026-10-15
A30: C12-E01 | B30: C12 | C30: latest_update | D30: 2026-10-03 | E30: day | F30: B01 | G30: Per dataset's reading of dashboard: MoRD Rural Skills Division, 409 documents, 24 verifications; table loads dynamically, not re-verified. | H30: AI-assisted research (Claude), reviewed by author | I30: 2026-10-15
A31: C12-E02 | B31: C12 | C31: live | D31: 2026-10-03 | E31: day | F31: B01 | G31: Live by this date: the NIC statistics file lists 409 documents for Ministry of Rural Development – Rural Skills Division (earliest snapshot showing use; actual start may be earlier). | H31: Derived from official NIC snapshot | I31: 2026-10-15
A32: C12-E03 | B32: C12 | C32: latest_update | D32: 2026-10-14 | E32: day | F32: B11 | G32: NIC statistics file (data date 2026-10-14) lists Ministry of Rural Development – Rural Skills Division: 4,553 documents. | H32: Derived from official NIC snapshot | I32: 2026-10-15
A33: C13-E01 | B33: C13 | C33: pilot_started | D33: 2026-02 | E33: month | F33: R05 | G33: Gujarat CBDC-based PDS pilot and Puducherry PMGKAY food-subsidy pilot (RBI, PFMS, Canara Bank) both began February 2026. | H33: AI-assisted research (Claude), reviewed by author | I33: 2026-10-15
A34: C13-E02 | B34: C13 | C34: live | D34: 2026-08-14 | E34: day | F34: N44 | G34: Chandigarh and Dadra & Nagar Haveli achieved complete CBDC-based food-subsidy transfer for all eligible PMGKAY beneficiaries. | H34: AI-assisted research (Claude), reviewed by author | I34: 2026-10-15
A35: C13-E03 | B35: C13 | C35: latest_update | D35: 2026-08-14 | E35: day | F35: N44 | G35: Rollout in two UTs called a template for other states and UTs. | H35: AI-assisted research (Claude), reviewed by author | I35: 2026-10-15
A36: C14-E01 | B36: C14 | C36: announced | D36: 2024 | E36: year | F36: R02 | G36: MeitY Rajya Sabha reply (reported 16 Dec 2024) lists Ministry of Corporate Affairs among organisations developing blockchain solutions with government. | H36: AI-assisted research (Claude), reviewed by author | I36: 2026-10-15
A37: C14-E02 | B37: C14 | C37: latest_update | D37: 2024-12-16 | E37: day | F37: R02 | G37: 'Many organisations are developing blockchain solutions in association with the government', including Ministry of Corporate Affairs. | H37: AI-assisted research (Claude), reviewed by author | I37: 2026-10-15
A38: C15-E01 | B38: C15 | C38: announced | D38: 2022-12-15 | E38: day | F38: N46 | G38: MoU among CCI, Ministry of Textiles and TEXPROCIL formalised Kasturi Cotton Bharat with Rs 30 crore (incl. Rs 15 crore industry). | H38: AI-assisted research (Claude), reviewed by author | I38: 2026-10-15
A39: C15-E02 | B39: C15 | C39: live | D39: 2024-08-06 | E39: day | F39: N46 | G39: Live by (earliest dated evidence): Lok Sabha reply says a Kasturi microsite with QR verification and blockchain technology has been developed; 343 ginning units registered. | H39: AI-assisted research (Claude), reviewed by author | I39: 2026-10-15
A40: C15-E03 | B40: C15 | C40: latest_update | D40: 2026-08-06 | E40: day | F40: W199 | G40: Kasturi Cotton, run by CCI and Texprocil, uses QR-coded blockchain tracking (KC-Track) from farm to garment; certified bales to feed new 2026/27-2030/31 cotton mission. | H40: AI-assisted research (Claude), reviewed by author | I40: 2026-10-15
A41: C16-E01 | B41: C16 | C41: announced | D41: 2022-01-21 | E41: day | F41: W015 | G41: PIB advance release: PM would give digital certificates to PMRBP 2022 winners using blockchain, first time; 2021 awardees also included. | H41: AI-assisted research (Claude), reviewed by author | I41: 2026-10-15
A42: C16-E02 | B42: C16 | C42: live | D42: 2022-01-24 | E42: day | F42: W014 | G42: PM gave blockchain digital certificates (IIT Kanpur National Blockchain Project) to 61 PMRBP 2021 and 2022 winners during the 24 Jan function. | H42: AI-assisted research (Claude), reviewed by author | I42: 2026-10-15
A43: C16-E03 | B43: C16 | C43: latest_update | D43: 2022-01-24 | E43: day | F43: W016 | G43: IIT Kanpur: 61 awardees (29 for 2022, 32 for 2021) got SSI/blockchain certificates in mobile wallets, built by incubatee CRUBN. | H43: AI-assisted research (Claude), reviewed by author | I43: 2026-10-15
A44: C17-E01 | B44: C17 | C44: announced | D44: 2023-06 | E44: month | F44: W018 | G44: Railway Minister Vaishnaw sought a proposal for a foolproof blockchain-based signalling system; IIT Kharagpur professor writing the programme (article 30 Jun 2023). | H44: AI-assisted research (Claude), reviewed by author | I44: 2026-10-15
A45: C17-E02 | B45: C17 | C45: latest_update | D45: 2023-07-11 | E45: day | F45: W019 | G45: Design blueprint about 15 days from completion; project would take two years once the Ministry approves the design; joint IIT KGP–IIT BBS team planned. | H45: AI-assisted research (Claude), reviewed by author | I45: 2026-10-15
A46: C18-E01 | B46: C18 | C46: announced | D46: 2018-06-29 | E46: day | F46: W020 | G46: NITI Aayog and GNFC signed Statement of Intent to jointly develop a blockchain PoC for fertilizer subsidy disbursement. | H46: AI-assisted research (Claude), reviewed by author | I46: 2026-10-15
A47: C18-E02 | B47: C18 | C47: pilot_completed | D47: 2020-01 | E47: month | F47: R03 | G47: Draft strategy describes completed PoC with results: shipment acknowledgements in minutes and near real-time B1 quantity certification instead of weeks. | H47: AI-assisted research (Claude), reviewed by author | I47: 2026-10-15
A48: C18-E03 | B48: C18 | C48: latest_update | D48: 2020-01 | E48: month | F48: R03 | G48: Says a scaled-up version of the pilot intends to add the certifying agency as a node; no scale-up reported afterwards. | H48: AI-assisted research (Claude), reviewed by author | I48: 2026-10-15
... A67: O04-E03 | B67: O04 | C67: latest_update | D67: 2017-09-04 | E67: day | F67: W039 | G67: IDRBT, after its January 2017 trade-finance PoC, announced plans for a blockchain platform for banking applications; no launch date given. | H67: AI-assisted research (Claude), reviewed by author | I67: 2026-10-15
A68: O04-E04 | B68: O04 | C68: latest_update | D68: 2018 | E68: year | F68: R04 | G68: Status as recorded in v1.0.0: PoCs completed | H68: v1.0.0 field | I68: 2026-10-15
A69: O05-E01 | B69: O05 | C69: announced | D69: 2021-08-13 | E69: day | F69: W041 | G69: NSDL: SEBI on 13 Aug 2021 set protocols for issuers, trustees and rating agencies to record debenture information on the DLT platform. | H69: AI-assisted research (Claude), reviewed by author | I69: 2026-10-15
A70: O05-E02 | B70: O05 | C70: live | D70: 2022-04-01 | E70: day | F70: R08 | G70: SEBI: from 1 April 2022 asset recording/verification, allotment, listing and interest/redemption for debentures move to the DLT system. | H70: AI-assisted research (Claude), reviewed by author | I70: 2026-10-15
A71: O05-E03 | B71: O05 | C71: latest_update | D71: 2025-10-24 | E71: day | F71: W044 | G71: PIB NBF backgrounder: NSDL's DLT platform lets issuers and trustees record charges, monitor asset cover and track covenants; tamper-proof, timestamped ledger. | H71: AI-assisted research (Claude), reviewed by author | I71: 2026-10-15
A72: O06-E01 | B72: O06 | C72: announced | D72: 2018-07-19 | E72: day | F72: W045 | G72: TRAI: TCCCPR 2018 issued 19 July 2018, fully effective 28 February 2019, setting up the DLT-based commercial communication regime. | H72: AI-assisted research (Claude), reviewed by author | I72: 2026-10-15
A73: O06-E02 | B73: O06 | C73: live | D73: 2021-03-08 | E73: day | F73: W045 | G73: Access providers activated SMS template scrubbing on 8 March 2021; suspended seven days after failures; resumed 17 March 2021. | H73: AI-assisted research (Claude), reviewed by author | I73: 2026-10-15
A74: O06-E03 | B74: O06 | C74: scaled | D74: 2024-12-11 | E74: day | F74: W046 | G74: Message traceability enforced: from 11 Dec 2024 SMS via undeclared PE-telemarketer chains on DLT are rejected; about 1.13 lakh PEs to onboard. | H74: AI-assisted research (Claude), reviewed by author | I74: 2026-10-15
A75: O06-E04 | B75: O06 | C75: latest_update | D75: 2025-10-24 | E75: day | F75: W044 | G75: PIB NBF backgrounder: TRAI requires PEs and telemarketers to register message chains on DLT; over 1.13 lakh entities; with RBI, SEBI, NIC, C-DAC. | H75: AI-assisted research (Claude), reviewed by author | I75: 2026-10-15
A76: O07-E01 | B76: O07 | C76: announced | D76: 2020-02 | E76: month | F76: W049 | G76: HT (17 Feb 2020 edition, PTI): ECI partnered with IIT Madras on 'block chain' remote voting; in R&D, prototype first. | H76: AI-assisted research (Claude), reviewed by author | I76: 2026-10-15
A77: O07-E02 | B77: O07 | C77: latest_update | D77: 2022-01 | E77: month | F77: W054 | G77: NIC Informatics (Jan 2022): blockchain remote voting system for migrants and in-service voters; PoC was demonstrated to ECI. No deployment reported. | H77: AI-assisted research (Claude), reviewed by author | I77: 2026-10-15
A78: O08-E01 | B78: O08 | C78: announced | D78: 2022-09-23 | E78: day | F78: N56 | G78: Phase III vision document (Executive Summary, key goals) lists 'digital signatures & blockchain to ensure authentication & security' of court documents. | H78: AI-assisted research (Claude), reviewed by author | I78: 2026-10-15
A79: O08-E02 | B79: O08 | C79: latest_update | D79: 2025-12-19 | E79: day | F79: W060 | G79: IANS on Law Minister's reply: Phase III earmarks Rs 53.57 crore for 'Future Technological Advancements (AI, Blockchain, etc.)'; AI still in controlled pilots. | H79: AI-assisted research (Claude), reviewed by author | I79: 2026-10-15
A80: O09-E01 | B80: O09 | C80: announced | D80: 2025-11-07 | E80: day | F80: N85 | G80: Narasimha & Bagchi JJ suggested blockchain for land registration; asked Law Commission to study reform and Union to lead initiative with States. | H80: AI-assisted research (Claude), reviewed by author | I80: 2026-10-15
... A91: O12-E02 | B91: O12 | C91: live | D91: 2024-10-22 | E91: day | F91: N74 | G91: At NDDB Diamond Jubilee, Gir Ghee (Mother Dairy) and Badri Ghee (UCDF) launched, using Bharat Pashudhan traceability mechanism. | H91: AI-assisted research (Claude), reviewed by author | I91: 2026-10-15
A92: O12-E03 | B92: O12 | C92: latest_update | D92: 2025 | E92: year | F92: W078 | G92: NDDB Annual Report 2024-25 records launch of Mother Dairy Gir Ghee and Badri Ghee with traceability under Bharat Pashudhan platform. | H92: AI-assisted research (Claude), reviewed by author | I92: 2026-10-15
A93: O12-E04 | B93: O12 | C93: latest_update | D93: 2025-12 | E93: month | F93: D01 | G93: Status as recorded in v1.0.0: Live; showcased in Republic Day 2025 tableau (per deck) | H93: v1.0.0 field | I93: 2026-10-15
A94: O13-E01 | B94: O13 | C94: announced | D94: 2024-03 | E94: month | F94: W081 | G94: IRCTC announced NFT souvenir tickets for Holi on Lucknow-New Delhi Tejas Express (82501/82502), 20 March-2 April 2024, with NFTtrace. | H94: AI-assisted research (Claude), reviewed by author | I94: 2026-10-15
A95: O13-E02 | B95: O13 | C95: live | D95: 2024-03 | E95: month | F95: N64 | G95: IRCTC previously issued limited NFT train tickets during Holi in March 2024. | H95: AI-assisted research (Claude), reviewed by author | I95: 2026-10-15
A96: O13-E03 | B96: O13 | C96: latest_update | D96: 2025-01-13 | E96: day | F96: N64 | G96: IRCTC with Chaincode Consulting and NFTtrace to issue Polygon NFT tickets for MahaKumbh Mela travellers. | H96: AI-assisted research (Claude), reviewed by author | I96: 2026-10-15
A97: O14-E01 | B97: O14 | C97: announced | D97: 2021-09-22 | E97: day | F97: W082 | G97: CBSE press note: Academic Blockchain Documents (ABCD) with NIC records results/certificates tamper-proof, verifiable at cbse.certchain.nic.in. | H97: AI-assisted research (Claude), reviewed by author | I97: 2026-10-15
A98: O14-E02 | B98: O14 | C98: live | D98: 2021-09-22 | E98: day | F98: W082 | G98: Class X/XII certificates of 2019-2021 available on blockchain via cbse.certchain.nic.in; NIC nodes at Bangalore, Pune, Jaipur. | H98: AI-assisted research (Claude), reviewed by author | I98: 2026-10-15
A99: O14-E03 | B99: O14 | C99: latest_update | D99: 2026-10-03 | E99: day | F99: B01 | G99: NIC dashboard (as on 03-10-2026, per batch capture): CBSE has 2,10,71,556 documents and 85,261 verifications on Certificate Chain. | H99: AI-assisted research (Claude), reviewed by author | I99: 2026-10-15
A100: O14-E04 | B100: O14 | C100: latest_update | D100: 2026-10-14 | E100: day | F100: B11 | G100: NIC statistics file (data date 2026-10-14) lists Central Board of Secondary Education: 2,10,71,556 documents. | H100: Derived from official NIC snapshot | I100: 2026-10-15
A101: O15-E01 | B101: O15 | C101: live | D101: 2021-12-28 | E101: day | F101: W084 | G101: At IIT Kanpur's 54th convocation, PM issued digital degrees through in-house blockchain-driven technology. | H101: AI-assisted research (Claude), reviewed by author | I101: 2026-10-15
A102: O15-E02 | B102: O15 | C102: scaled | D102: 2022-01 | E102: month | F102: N47 | G102: Same National Blockchain Project technology used to issue digital certificates to 61 PM Rashtriya Bal Puraskar 2022 awardees. | H102: AI-assisted research (Claude), reviewed by author | I102: 2026-10-15
A103: O15-E03 | B103: O15 | C103: latest_update | D103: 2024-06-29 | E103: day | F103: W088 | G103: 57th convocation: graduates can access digital degrees through IIT Kanpur's in-house blockchain application; forgery-proof, globally verifiable. | H103: AI-assisted research (Claude), reviewed by author | I103: 2026-10-15
A104: O15-E04 | B104: O15 | C104: latest_update | D104: 2025-12 | E104: month | F104: D01 | G104: Status as recorded in v1.0.0: In use | H104: v1.0.0 field | I104: 2026-10-15
... A107: O16-E03 | B107: O16 | C107: latest_update | D107: 2019-11 | E107: month | F107: R11 | G107: After a tepid launch, about 30,000 farmers registered versus 23 at launch; Board training staff to upload quality certificates. | H107: AI-assisted research (Claude), reviewed by author | I107: 2026-10-15
A108: O16-E04 | B108: O16 | C108: latest_update | D108: 2021 | E108: year | F108: R10 | G108: Status as recorded in v1.0.0: Grew to ~30,000 farmers; no later status | H108: v1.0.0 field | I108: 2026-10-15
A109: O17-E01 | B109: O17 | C109: announced | D109: 2021-04-05 | E109: day | F109: N82 | G109: Spices Board and UNDP Accelerator Lab signed MoU for blockchain traceability interface linked to e-Spice Bazaar; chilli/turmeric pilot, 3,000+ AP farmers. | H109: AI-assisted research (Claude), reviewed by author | I109: 2026-10-15
A110: O17-E02 | B110: O17 | C110: latest_update | D110: 2021-04-05 | E110: day | F110: N82 | G110: Interface design expected to be completed by May 2021; pilot planned in select Andhra Pradesh districts. | H110: AI-assisted research (Claude), reviewed by author | I110: 2026-10-15
A111: O18-E01 | B111: O18 | C111: announced | D111: 2024-12 | E111: month | F111: R02 | G111: MeitY Rajya Sabha reply named UIDAI, SPMCIL, Cotton Corporation of India and Forensic Science Laboratory as developing blockchain solutions with government. | H111: AI-assisted research (Claude), reviewed by author | I111: 2026-10-15
A112: O18-E02 | B112: O18 | C112: latest_update | D112: 2024-12-16 | E112: day | F112: R02 | G112: MediaNama report of MoS Jitin Prasada's reply lists these bodies among those developing blockchain solutions; no scope given. | H112: AI-assisted research (Claude), reviewed by author | I112: 2026-10-15
A113: O19-E01 | B113: O19 | C113: announced | D113: 2024-12 | E113: month | F113: R02 | G113: MeitY Rajya Sabha reply: blockchain provides a tamper-proof, secure record of eStamp transactions with government financial agencies. | H113: AI-assisted research (Claude), reviewed by author | I113: 2026-10-15
A114: O19-E02 | B114: O19 | C114: latest_update | D114: 2024-12-16 | E114: day | F114: R02 | G114: Reported in present tense ('uses blockchain') under National Blockchain Framework applications; agency not named. | H114: AI-assisted research (Claude), reviewed by author | I114: 2026-10-15
A115: S01-E01 | B115: S01 | C115: announced | D115: 2017-10-10 | E115: day | F115: W091 | G115: Andhra Pradesh partnered Swedish startup ChromaWay to develop and test a blockchain land registry pilot under Fintech Valley Vizag. | H115: AI-assisted research (Claude), reviewed by author | I115: 2026-10-15
A116: S01-E02 | B116: S01 | C116: pilot_started | D116: 2017-12 | E116: month | F116: W090 | G116: CRDA launched blockchain-based land registration for Amaravati in December 2017 with Zebi; 83,000 records migrated by March 2018. | H116: AI-assisted research (Claude), reviewed by author | I116: 2026-10-15
A117: S01-E03 | B117: S01 | C117: latest_update | D117: 2019-12-16 | E117: day | F117: R35 | G117: New AP government's Deputy CM says state is in talks with companies to put purified land records on blockchain; decision after Assembly session. | H117: AI-assisted research (Claude), reviewed by author | I117: 2026-10-15
A118: S02-E01 | B118: S02 | C118: latest_update | D118: 2018-03-05 | E118: day | F118: R13 | G118: Forbes lists 'streamlining vehicle registrations' alongside land records as AP blockchain pilots; no further details given. | H118: AI-assisted research (Claude), reviewed by author | I118: 2026-10-15
A119: S02-E02 | B119: S02 | C119: announced | D119: 2017 | E119: year | F119: R13 | G119: Start/announcement date recorded in v1.0.0 ("2017–18"). | H119: v1.0.0 field | I119: 2026-10-15
A120: S03-E01 | B120: S03 | C120: announced | D120: 2017-06-27 | E120: day | F120: W094 | G120: Citing Economic Times: AP launched blockchain pilots in civil supplies and land records departments, planning data transfer within 8–12 months. | H120: AI-assisted research (Claude), reviewed by author | I120: 2026-10-15
A121: S03-E02 | B121: S03 | C121: pilot_started | D121: 2017 | E121: year | F121: W094 | G121: Report says AP had launched pilot projects in the civil supplies department (as of June 2017). | H121: AI-assisted research (Claude), reviewed by author | I121: 2026-10-15
A122: S03-E03 | B122: S03 | C122: latest_update | D122: 2017-06-28 | E122: day | F122: R15 | G122: Snapper co-founder: revenue department pension data could move to blockchain 'by next year'; state holds 103 million ration card records. | H122: AI-assisted research (Claude), reviewed by author | I122: 2026-10-15
A123: S03-E04 | B123: S03 | C123: latest_update | D123: 2019 | E123: year | F123: R15 | G123: Status as recorded in v1.0.0: Announced; rollout not confirmed | H123: v1.0.0 field | I123: 2026-10-15
A124: S04-E01 | B124: S04 | C124: live | D124: 2023-12-04 | E124: day | F124: R16 | G124: NIC onboarding table: AP Water Resources Dept's Preliminary Notification, Draft Declaration, LA Award and R&R Award available on chain since 04/12/2023. | H124: AI-assisted research (Claude), reviewed by author | I124: 2026-10-15
A125: S04-E02 | B125: S04 | C125: latest_update | D125: 2026-10-03 | E125: day | F125: B01 | G125: Per dataset snapshot of NIC dashboard (as on 03-10-2026), AP Water Resources land-acquisition documents not listed. | H125: AI-assisted research (Claude), reviewed by author | I125: 2026-10-15
A126: S05-E01 | B126: S05 | C126: announced | D126: 2025-07-07 | E126: day | F126: N33 | G126: At 7 July review, CM directed revenue records be thoroughly sanitised and secured using blockchain, and departmental data integrated via a data lake/RTGS. | H126: AI-assisted research (Claude), reviewed by author | I126: 2026-10-15
A127: S05-E02 | B127: S05 | C127: latest_update | D127: 2025-07-08 | E127: day | F127: N33 | G127: Report of the directive; departments told to sync beneficiary data with RTGS; no implementation details or timeline. | H127: AI-assisted research (Claude), reviewed by author | I127: 2026-10-15
A128: S06-E01 | B128: S06 | C128: announced | D128: 2025-07 | E128: month | F128: W097 | G128: NIC Informatics: Property Chain PoC developed with NIC CoE Blockchain Bengaluru and IIT Hyderabad; government decided to implement it very soon. | H128: AI-assisted research (Claude), reviewed by author | I128: 2026-10-15
A129: S06-E02 | B129: S06 | C129: pilot_started | D129: 2026-07-23 | E129: day | F129: N31 | G129: Mee Bhoomi–Blockchain pilot launched in seven mandals of seven districts: 89 resurvey villages, ~1,37,763 parcel maps, Hyperledger Fabric, eight services. | H129: AI-assisted research (Claude), reviewed by author | I129: 2026-10-15
A130: S06-E03 | B130: S06 | C130: latest_update | D130: 2026-10-03 | E130: day | F130: B01 | G130: Per dataset snapshot of NIC dashboard: AP Survey Dept 1,49,781 documents and Revenue Dept 1,44,471 verifications on Property Chain. | H130: AI-assisted research (Claude), reviewed by author | I130: 2026-10-15
A131: S06-E04 | B131: S06 | C131: pilot_started | D131: 2026-10-03 | E131: day | F131: B01 | G131: In use (pilot) by this date: the NIC statistics file lists 1,49,781 documents for Andhra Pradesh – Department of Survey (earliest snapshot showing use; actual start may be earlier). | H131: Derived from official NIC snapshot | I131: 2026-10-15
A132: S06-E05 | B132: S06 | C132: latest_update | D132: 2026-10-14 | E132: day | F132: B11 | G132: NIC statistics file (data date 2026-10-14) lists Andhra Pradesh – Department of Revenue: 0 documents; Andhra Pradesh – Department of Survey: 3,16,434 documents. | H132: Derived from official NIC snapshot | I132: 2026-10-15
A133: S07-E01 | B133: S07 | C133: announced | D133: 2026-08-10 | E133: day | F133: R14 | G133: At Kalidindi meeting, CM said blockchain extends tamper-proof security to pattadar passbooks, with QR codes and currency-note-like security features embedded. | H133: AI-assisted research (Claude), reviewed by author | I133: 2026-10-15
A134: S07-E02 | B134: S07 | C134: latest_update | D134: 2026-08-10 | E134: day | F134: R14 | G134: Over 32 lakh passbooks distributed; 9,365 villages yet to be resurveyed before another 69 lakh passbooks can be issued. | H134: AI-assisted research (Claude), reviewed by author | I134: 2026-10-15
A135: S08-E01 | B135: S08 | C135: pilot_started | D135: 2024-02-13 | E135: day | F135: N01 | G135: DoLR Secretary Nidhi Khare launched district-level blockchain cadastre and land records pilot in Darrang on 13 Feb 2024; pan-Assam rollout 'shortly'. | H135: AI-assisted research (Claude), reviewed by author | I135: 2026-10-15
... A160: S18-E04 | B160: S18 | C160: latest_update | D160: 2025-02-19 | E160: day | F160: W114 | G160: STPI Apiary co-organising India Blockchain Horizons 2025 (24 Feb 2025), showcasing more than 25 Apiary-incubated startups. | H160: AI-assisted research (Claude), reviewed by author | I160: 2026-10-15
A161: S19-E01 | B161: S19 | C161: latest_update | D161: 2024 | E161: year | F161: R16 | G161: Hyperledger India eBook says NITI Aayog has a pilot to improve apple farming using blockchain with IoT sensors for storage/supply-chain monitoring; undated. | H161: AI-assisted research (Claude), reviewed by author | I161: 2026-10-15
A162: S20-E01 | B162: S20 | C162: live | D162: 2022 | E162: year | F162: N11 | G162: Blockchain seed distribution in use during Kharif 2022: 3 lakh+ farmers registered, 600 LAMPS/PACS, 160 FPOs, about 30,000 quintals distributed. | H162: AI-assisted research (Claude), reviewed by author | I162: 2026-10-15
A163: S20-E02 | B163: S20 | C163: latest_update | D163: 2026-06-14 | E163: day | F163: W119 | G163: For Kharif 2026, the agriculture director said seed distribution will run through blockchain for monitoring, plus geo-tagging of fields. | H163: AI-assisted research (Claude), reviewed by author | I163: 2026-10-15
A164: S21-E01 | B164: S21 | C164: latest_update | D164: 2026-10-03 | E164: day | F164: B01 | G164: NIC blockchain dashboard (as on 03-10-2026, per batch capture B01): Jharkhand Revenue Dept shows 4,474 Property Chain documents and 31 verifications. | H164: AI-assisted research (Claude), reviewed by author | I164: 2026-10-15
A165: S21-E02 | B165: S21 | C165: announced | D165: 2024 | E165: year | F165: B01 | G165: Start/announcement date recorded in v1.0.0 ("2024"). | H165: v1.0.0 field | I165: 2026-10-15
A166: S21-E03 | B166: S21 | C166: live | D166: 2024-07-23 | E166: day | F166: B12 | G166: Live by this date: the NIC statistics file lists 4,185 documents for Jharkhand – Department of Revenue (earliest snapshot showing use; actual start may be earlier). | H166: Derived from official NIC snapshot | I166: 2026-10-15
...

Sheet Challenges
A1: challenge_id | B1: project_id | C1: challenge_code | D1: description | E1: source_id | F1: evidence | G1: recorded_by | H1: recorded_on
A2: C01-C01 | B2: C01 | C2: O2 | D2: MeitY cites the need for skilled manpower to build blockchain applications as a challenge the NBF/Vishvasya stack is meant to address. | E2: R34 | F2: Launch release says NBF addresses the need for skilled manpower for building blockchain-based applications. | G2: AI-assisted research (Claude), reviewed by author | H2: 2026-10-15
A3: C01-C02 | B3: C01 | C3: O3 | D3: Vendor lock-in named by MeitY as a challenge motivating a shared, indigenous, extensible government blockchain stack. | E3: R34 | F3: Launch release lists vendor lock-in among the challenges the framework is designed to tackle. | G3: AI-assisted research (Claude), reviewed by author | H3: 2026-10-15
A4: C05-C01 | B4: C05 | C4: O2 | D4: NIC says a lack of trained and experienced blockchain developers was a barrier that led to setting up the CoE. | E4: W010 | F4: NIC blog names lack of trained and experienced developers among barriers prompting the CoE. | G4: AI-assisted research (Claude), reviewed by author | H4: 2026-10-15
A5: C05-C02 | B5: C05 | C5: O1 | D5: Lack of investment in blockchain infrastructure and its maintenance cited by NIC as an adoption barrier the CoE was meant to overcome. | E5: W010 | F5: Blog cites lack of investments in infrastructure and its maintenance as a barrier. | G5: AI-assisted research (Claude), reviewed by author | H5: 2026-10-15
A6: C05-C03 | B6: C05 | C6: T2 | D6: CoE's multi-node Hyperledger Sawtooth production setup for Drug Logistics chain had node-sync delays, forks and full transaction queues that brought network down. | E6: W010 | F6: Node synchronisation delayed, chain forked, transaction queue filled and network went down; team tried new consensus/Sawtooth releases. | G6: AI-assisted research (Claude), reviewed by author | H6: 2026-10-15
A7: C18-C01 | B7: C18 | C7: T1 | D7: PoC had to link GNFC's SAP-based invoicing with the Department of Fertilizers' iFMS; scale-up would need integrating multiple systems of record across the supply chain. | E7: R03 | F7: GNFC invoices sit on SAP servers and are replicated to DoF's iFMS; paper stresses that legacy-system integration must lead design choices. | G7: AI-assisted research (Claude), reviewed by author | H7: 2026-10-15
A8: C19-C01 | B8: C19 | C8: T1 | D8: Existing ERP and supply-chain management systems of participants had to be integrated with the blockchain platform to give a unified view of drug movement. | E8: R03 | F8: In the drug track-and-trace implementation, existing ERP/SCM needed integration with the blockchain platform. | G8: AI-assisted research (Claude), reviewed by author | H8: 2026-10-15
A9: C19-C02 | B9: C19 | C9: T2 | D9: Blockchain platform could not handle low-latency IoT sensor inputs (e.g., temperature), so a middleware layer filtered events before writing to the ledger. | E9: R03 | F9: A software middle layer passed only significant IoT events to the blockchain, given some platforms' inability to handle low-latency inputs. | G9: AI-assisted research (Claude), reviewed by author | H9: 2026-10-15
A10: C19-C03 | B10: C19 | C10: E2 | D10: Supply-chain participants had to adopt a new barcode-scanning step at each transfer, using special three-tier GS1 codes on packaging. | E10: R03 | F10: Stakeholders had to scan barcodes at each stage of transfer, an action not previously required; packaging needed three-tiered QR/barcodes. | G10: AI-assisted research (Claude), reviewed by author | H10: 2026-10-15
A11: C20-C01 | B11: C20 | C11: T3 | D11: Officials flagged the need to protect privacy on IndiaChain, e.g., hiding government tender bids and property sale prices on a shared ledger. | E11: W022 | F11: Challenges in safeguarding privacy of individuals and companies; IndiaChain must address identity, privacy and policy. | G11: AI-assisted research (Claude), reviewed by author | H11: 2026-10-15
A12: C20-C02 | B12: C20 | C12: E1 | D12: Regulatory and legal framework for IndiaChain was still being drafted when it was announced in Nov 2017. | E12: W022 | F12: Government was still firming up regulations; legal framework pending at time of report. | G12: AI-assisted research (Claude), reviewed by author | H12: 2026-10-15
... A40: O16-C01 | B40: O16 | C40: E2 | D40: Marketplace had a tepid start with only 23 farmers registered at launch before uptake grew. | E40: R11 | F40: After a tepid launch earlier in 2019, platform has about 30,000 farmers versus just 23 at launch. | G40: AI-assisted research (Claude), reviewed by author | H40: 2026-10-15

Sheet Sources
A1: source_id | B1: author | C1: date | D1: date_precision | E1: title | F1: publisher | G1: url | H1: note | I1: source_type | J1: evidence_score | K1: accessed | L1: added_in
A2: R01 | B2: Press Information Bureau (MeitY) | C2: 2025-10-24 | D2: day | E2: National Blockchain Framework: Strengthening governance through blockchain technology [Backgrounder, Release ID 2182023] | F2: Government of India | G2: https://www.pib.gov.in/PressReleasePage.aspx?PRID=2182023 | I2: Official | J2: 5 | K2: 2026-10-04 | L2: 1.0.0
A3: R02 | B3: Pandey, K. | C3: 2024-12-16 | D3: day | E3: Blockchain tech in use for verifying property transactions in Karnataka and Jharkhand: IT Ministry | F3: MediaNama | G3: https://www.medianama.com/2024/12/223-blockchain-land-use-pilot-karnataka-jharkhandd/ | I3: News | J3: 3 | K3: 2026-10-04 | L3: 1.0.0
A4: R03 | B4: NITI Aayog | C4: 2020-01 | D4: month | E4: Blockchain: The India Strategy – Part I (Draft discussion paper) | F4: NITI Aayog | G4: https://www.niti.gov.in/sites/default/files/2020-01/Blockchain_The_India_Strategy_Part_I.pdf | I4: Official | J4: 4 | K4: 2026-10-04 | L4: 1.0.0
A5: R04 | B5: Invest India | C5: 2018 | D5: year | E5: Implementing blockchain in India | F5: Invest India | G5: https://www.investindia.gov.in/team-india-blogs/implementing-blockchain-india | I5: Official | J5: 4 | K5: 2026-10-04 | L5: 1.0.0
A6: R05 | B6: The Crypto Times | C6: 2026-04-15 | D6: day | E6: RBI urges Indians to join CBDC pilot, calls e₹ 'future of money' | F6: The Crypto Times | G6: https://www.cryptotimes.io/2026/04/15/rbi-urges-indians-to-join-cbdc-pilot-calls-e-rupee-future-of-money/ | I6: News | J6: 2 | K6: 2026-10-04 | L6: 1.0.0
A7: R06 | B7: Reserve Bank of India | C7: 2026-10-01 | D7: day | E7: Digital Rupee (e₹) – Frequently Asked Questions | F7: RBI | G7: https://www.rbi.org.in/commonman/English/scripts/FAQs.aspx?Id=3686 | I7: Official | J7: 5 | K7: 2026-10-04 | L7: 1.0.0
A8: R07 | B8: The United Indian | C8: 2026 | D8: year | E8: Digital Rupee in 2026: What RBI's e-Rupee is and how to actually use it | F8: The United Indian | G8: https://www.theunitedindian.com/news/digital-rupee-e-rupee-2026-rbi-explainer | I8: News | J8: 2 | K8: 2026-10-04 | L8: 1.0.0
A9: R08 | B9: Business Standard | C9: 2022-04-18 | D9: day | E9: Use of blockchain for security and covenant monitoring becomes operational | F9: Business Standard | G9: https://www.business-standard.com/amp/article/markets/use-of-blockchain-for-security-and-covenant-monitoring-becomes-operational-122041801023_1.html | I9: News | J9: 3 | K9: 2026-10-04 | L9: 1.0.0
A10: R09 | B10: Press Trust of India | C10: 2022-03-29 | D10: day | E10: Sebi issues operational guidelines for covenant monitoring with DLT | F10: Business Standard | G10: https://www.business-standard.com/amp/article/markets/sebi-issues-operational-guidelines-for-covenant-monitoring-with-dlt-122032901511_1.html | I10: News | J10: 3 | K10: 2026-10-04 | L10: 1.0.0
A11: R10 | B11: Ledger Insights | C11: 2019-03 | D11: month | E11: India's Coffee Board unveils blockchain based marketplace | F11: Ledger Insights | G11: https://www.ledgerinsights.com/blockchain-coffee-food-traceability-india/ | I11: News | J11: 2 | K11: 2026-10-04 | L11: 1.0.0
A12: R11 | B12: Comunicaffe | C12: 2019-11-21 | D12: day | E12: Coffee Board of India registers 30,000 farmers on blockchain marketplace | F12: Comunicaffe International | G12: https://www.comunicaffe.com/coffee-board-of-india-registers-30000-farmers-on-blockchain-marketplace/ | I12: News | J12: 2 | K12: 2026-10-04 | L12: 1.0.0
A13: R12 | B13: GS1 India | E13: UNDP and Spices Board blockchain project (eSpiceBazaar) | F13: GS1 India | G13: https://www.gs1india.org/spices-board-echilli-bazaar/ | I13: Secondary | J13: 2 | K13: 2026-10-04 | L13: 1.0.0
A14: R13 | B14: Forbes (Out of Asia) | C14: 2018-03-05 | D14: day | E14: This Indian city is embracing blockchain technology – here's why | F14: Forbes | G14: https://www.forbes.com/sites/outofasia/2018/03/05/this-indian-city-is-embracing-blockchain-technology-heres-why/ | I14: News | J14: 3 | K14: 2026-10-04 | L14: 1.0.0
A15: R14 | B15: Telangana Today | C15: 2026-08-10 | D15: day | E15: Tamper-proof blockchain: Naidu announces enhanced security for AP land documents | F15: Telangana Today | G15: https://telanganatoday.com/tamper-proof-blockchain-naidu-announces-enhanced-security-for-ap-land-documents | I15: News | J15: 3 | K15: 2026-10-04 | L15: 1.0.0
A16: R15 | B16: CCN | C16: 2017-06-28 | D16: day | E16: Indian states go big on blockchain for land registry, pensions | F16: CCN | G16: https://www.ccn.com/indian-states-launch-blockchain-pilot-land-registry-records/ | I16: News | J16: 2 | K16: 2026-10-04 | L16: 1.0.0
A17: R16 | B17: Hyperledger India Regional Chapter | C17: 2024 | D17: year | E17: Hyperledger India – eBook (state-wise blockchain applications; NIC onboarding table as of June 2024) | F17: LF Decentralized Trust | G17: https://lf-hyperledger.atlassian.net/wiki/spaces/HIRC/pages/19171362/Hyperledger+India+-+eBook | I17: Secondary | J17: 2 | K17: 2026-10-04 | L17: 1.0.0
A18: R17 | B18: NIC Centre of Excellence in Blockchain Technology | E18: Blockchain technology in judiciary: A concept note | F18: National Informatics Centre | G18: https://blockchain.gov.in/Documents/JudiciaryChain.pdf | I18: Official | J18: 4 | K18: 2026-10-04 | L18: 1.0.0
A19: R18 | B19: Kerala Blockchain Academy | E19: About Kerala Blockchain Academy | F19: Digital University Kerala | G19: https://kba.ai/about-kba/ | I19: Official | J19: 4 | K19: 2026-10-04 | L19: 1.0.0
A20: R19 | B20: Business Today | C20: 2022-04-13 | D20: day | E20: Maharashtra minister launches project to issue caste certificates via blockchain | F20: Business Today | G20: https://www.businesstoday.in/crypto/story/maharashtra-minister-launches-project-to-issue-caste-certificates-via-blockchain-329731-2022-04-13 | I20: News | J20: 3 | K20: 2026-10-04 | L20: 1.0.0
A21: R20 | B21: DH Web Desk | C21: 2022-04-04 | D21: day | E21: Gadchiroli to use blockchain to authenticate caste certificates: Report | F21: Deccan Herald | G21: https://www.deccanherald.com/india/gadchiroli-to-use-blockchain-to-authenticate-caste-certificates-report-1097491.html | I21: News | J21: 3 | K21: 2026-10-04 | L21: 1.0.0
A22: R21 | B22: The Cryptonomist | C22: 2025-10-31 | D22: day | E22: Blockchain pilot: India records lands on Polygon | F22: The Cryptonomist | G22: https://en.cryptonomist.ch/2025/10/31/amravati-blockchain-polygon-pilot-india/ | I22: News | J22: 2 | K22: 2026-10-04 | L22: 1.0.0
A23: R22 | B23: CCN | C23: 2025 | D23: year | E23: Indian city Amravati just put its government on Polygon | F23: CCN | G23: https://www.ccn.com/news/crypto/indian-city-amravati-government-records-on-the-blockchain/ | I23: News | J23: 2 | K23: 2026-10-04 | L23: 1.0.0
A24: R23 | B24: Press Trust of India | C24: 2020-09-20 | D24: day | E24: Blockchain policy by TN govt ensures access to services 'anywhere, anytime' | F24: Business Standard | G24: https://www.business-standard.com/article/current-affairs/blockchain-policy-by-tn-govt-ensures-access-to-services-anywhere-anytime-120092000758_1.html | I24: News | J24: 3 | K24: 2026-10-04 | L24: 1.0.0
A25: R24 | B25: Business Standard | C25: 2020-02-05 | D25: day | E25: Tamil Nadu's leap into AI, blockchain to help the state with better service | F25: Business Standard | G25: https://www.business-standard.com/article/technology/tamil-nadu-s-leap-into-ai-blockchain-to-help-the-state-with-better-service-120020502136_1.html | I25: News | J25: 3 | K25: 2026-10-04 | L25: 1.0.0
A26: R25 | B26: Government of Telangana, ITE&C Department | E26: Blockchain – Blockchain District and blockchain initiatives | F26: Government of Telangana | G26: https://it.telangana.gov.in/initiatives/blockchain/ | I26: Official | J26: 4 | K26: 2026-10-04 | L26: 1.0.0
A27: R26 | B27: Inc42 | C27: 2018 | D27: year | E27: Telangana govt launches Blockchain District in partnership with Tech Mahindra | F27: Inc42 | G27: https://inc42.com/buzz/telangana-govt-announce-the-launch-of-blockchain-district-in-partnership-with-tech-mahindra-and-others/ | I27: News | J27: 3 | K27: 2026-10-04 | L27: 1.0.0
A28: R27 | B28: TokenPost | C28: 2018 | D28: year | E28: Government of Telangana to establish first Blockchain District in India | F28: TokenPost | G28: https://www.tokenpost.com/Government-of-Telangana-to-establish-first-Blockchain-District-in-India-87 | I28: News | J28: 3 | K28: 2026-10-04 | L28: 1.0.0
A29: R28 | B29: Observer Research Foundation | C29: 2023 | D29: year | E29: The growing role of blockchain in Indian governance | F29: ORF Expert Speak | G29: https://www.orfonline.org/expert-speak/the-growing-role-of-blockchain-in-indian-governance | I29: Secondary | J29: 2 | K29: 2026-10-04 | L29: 1.0.0
A30: R29 | B30: CCN | C30: 2018 | D30: year | E30: Indian state government will issue birth certificates on a blockchain | F30: CCN | G30: https://www.ccn.com/indian-state-government-will-issue-birth-certificates-on-a-blockchain/ | I30: News | J30: 2 | K30: 2026-10-04 | L30: 1.0.0
A31: R31 | B31: Cointelegraph | C31: 2024 | D31: year | E31: India hosts 8M gov't docs across 5 blockchains | F31: Cointelegraph | G31: https://cointelegraph.com/news/india-8m-govt-docs-blockchains | I31: News | J31: 2 | K31: 2026-10-04 | L31: 1.0.0
A32: R32 | B32: National Informatics Centre | E32: In Focus: Blockchain technology driving the next generation eGovernance applications | F32: Informatics (NIC) | G32: https://informatics.nic.in/uploads/infocus/b318d6b5_inf_blockchain_compressed.pdf | I32: Official | J32: 4 | K32: 2026-10-04 | L32: 1.0.0
A33: R34 | B33: Press Information Bureau (MeitY) | C33: 2024-09-04 | D33: day | E33: Government launches Vishvasya-Blockchain Technology Stack | F33: Government of India | G33: https://www.pib.gov.in/PressReleasePage.aspx?PRID=2051934 | I33: Official | J33: 4 | K33: 2026-10-04 | L33: 1.0.0
A34: R35 | B34: Ledger Insights | C34: 2019 | D34: year | E34: Indian state to implement blockchain for land records | F34: Ledger Insights | G34: https://www.ledgerinsights.com/indian-blockchain-land-records-registry-andhra-pradesh/ | I34: News | J34: 2 | K34: 2026-10-04 | L34: 1.0.0
A35: R36 | B35: MediaNama | C35: 2019-05 | D35: month | E35: Summary: Telangana's draft policy for a Blockchain District for Hyderabad | F35: MediaNama | G35: https://www.medianama.com/2019/05/223-summary-telanganas-draft-policy-for-a-blockchain-district-for-hyderabad/ | I35: News | J35: 3 | K35: 2026-10-04 | L35: 1.0.0
A36: N01 | B36: National Informatics Centre | C36: 2024-04 | D36: month | E36: Land records revolution: Blockchain pilot launched in Assam | F36: Informatics (NIC) | G36: https://informatics.nic.in/files/websites/april-2024/land-records-revolution-blockchain-pilot-launched-in-assam.php | I36: Official | J36: 4 | K36: 2026-10-04 | L36: 1.0.0
A37: N02 | B37: Government of Assam / Dept of Land Resources | C37: 2024-09 | D37: month | E37: NGDRS and implementation of blockchain in land records of Assam [PDF] | F37: Government of India (S3WaaS) | G37: https://cdnbbsr.s3waas.gov.in/s3d69116f8b0140cdeb1f99a4d5096ffe4/uploads/2024/09/202409121024408634.pdf | I37: Official | J37: 4 | K37: 2026-10-04 | L37: 1.0.0
A38: N03 | B38: The Crypto Times | C38: 2025-07-18 | D38: day | E38: Bihar conducts first mobile e-voting using Polygon blockchain | F38: The Crypto Times | G38: https://www.cryptotimes.io/2025/07/18/bihar-conducts-first-mobile-e-voting-using-polygon-blockchain/ | I38: News | J38: 2 | K38: 2026-10-04 | L38: 1.0.0
A39: N04 | B39: YourStory | C39: 2018-08-31 | D39: day | E39: Chhattisgarh successfully conducts its first Blockchain Grand Challenge | F39: YourStory | G39: https://yourstory.com/2018/08/chhattisgarh-blockchain-grand-challenge | I39: News | J39: 3 | K39: 2026-10-04 | L39: 1.0.0
A40: N05 | B40: Benzinga | C40: 2025-03-06 | D40: day | E40: Indian district digitizes 700k land records on Avalanche blockchain | F40: Benzinga | G40: https://benzinga.com/content/44171553/indian-district-digitizes-700k-land-records-on-avalanche-blockchain | I40: News | J40: 2 | K40: 2026-10-04 | L40: 1.0.0
A41: N06 | B41: The Goan | C41: 2025-07-28 | D41: day | E41: Govt mulls blockchain tech to secure land transactions | F41: The Goan EveryDay | G41: https://www.thegoan.net/goa-news/%EF%BB%BFgovt-mulls-blockchain-tech-to-secure-land-transactions/133870.html | I41: News | J41: 3 | K41: 2026-10-04 | L41: 1.0.0
A42: N07 | B42: CoinGeek | C42: 2022-08-05 | D42: day | E42: India's Goa to digitize police records with blockchain help | F42: CoinGeek | G42: https://coingeek.com/india-goa-to-digitize-police-records-with-blockchain-help/ | I42: News | J42: 2 | K42: 2026-10-04 | L42: 1.0.0
A43: N08 | B43: Convergence Now | C43: 2026-05-09 | D43: day | E43: Gujarat Revenue Department turns to AI, blockchain and GIS to strengthen land governance | F43: Convergence Now | G43: https://www.convergence-now.com/future-cities/gujarat-ai-blockchain-gis-land-governance-reform/ | I43: News | J43: 3 | K43: 2026-10-04 | L43: 1.0.0
A44: N09 | B44: CRISP (Govt of Madhya Pradesh society) | C44: 2023-06-22 | D44: day | E44: Haryana Government will give digital certificates to 5 lakh students by CRISP's developed blockchain technology | F44: CRISP Bhopal | G44: https://crisp.mp.gov.in/news/235-haryana-government-will-give-digital-certificates-to-5-lakh-students-by-crisp-s-developed-blockchain-technology | I44: Official | J44: 4 | K44: 2026-10-04 | L44: 1.0.0
A45: N10 | B45: Government of Haryana, Dept of IT, Electronics & Communication | C45: 2022-03-15 | D45: day | E45: Center of Excellence for Blockchain | F45: Government of Haryana | G45: https://haryanait.gov.in/center-of-excellence-for-blockchain/ | I45: Official | J45: 4 | K45: 2026-10-04 | L45: 1.0.0
A46: N11 | B46: Krishi Jagran | C46: 2022-08-19 | D46: day | E46: Jharkhand becomes first state in India to distribute seed to farmers via blockchain tech | F46: Krishi Jagran | G46: https://krishijagran.com/agriculture-world/jharkhand-becomes-first-state-in-india-to-distribute-seed-to-farmers-via-blockchain-tech/ | I46: News | J46: 3 | K46: 2026-10-04 | L46: 1.0.0
A47: N12 | B47: Press Information Bureau (MeitY) | C47: 2026-03-27 | D47: day | E47: Startup Challenge to develop citizen-centric innovative solutions using Blockchain and Web3 provides opportunities to build innovative government use cases [Release ID 2246221] | F47: Government of India | G47: https://www.pib.gov.in/PressReleasePage.aspx?PRID=2246221&reg=3&lang=1 | I47: Official | J47: 5 | K47: 2026-10-04 | L47: 1.0.0
A48: N13 | B48: Techshots | E48: Karnataka govt to launch digital wallet, Kaveri blockchain | F48: Techshots | G48: https://www.techshotsapp.com/Blockchain/karnataka-govt-to-launch-digital-wallet-kaveri-blockchain | I48: Secondary | J48: 2 | K48: 2026-10-04 | L48: 1.0.0
A49: N14 | B49: Deccan Herald | C49: 2017-11-18 | D49: day | E49: To ensure better citizen service, Karnataka plans new blockchain policy | F49: Deccan Herald | G49: https://www.deccanherald.com/india/karnataka/bengaluru/to-ensure-better-citizen-service-2034471 | I49: News | J49: 3 | K49: 2026-10-04 | L49: 1.0.0
A50: N15 | B50: Kerala Real Estate | C50: 2026-01-27 | D50: day | E50: Kerala's digital leap: Blockchain to transform land registration | F50: keralarealestate.com (blog) | G50: https://keralarealestate.com/blogs/keralas-digital-leap-blockchain-to-transform-land-registration | I50: Secondary | J50: 2 | K50: 2026-10-04 | L50: 1.0.0
A51: N16 | B51: Inc42 | C51: 2018 | D51: year | E51: Blockchain this week: Kerala government projects; Ant Financial targets enterprise blockchain & more | F51: Inc42 | G51: https://inc42.com/buzz/blockchain-this-week-kerala-government-projects-ant-financial-targets-enterprise-blockchain-more/ | I51: News | J51: 3 | K51: 2026-10-04 | L51: 1.0.0
A52: N17 | B52: Kerala Blockchain Academy | E52: Immunochain | F52: Digital University Kerala | G52: https://kba.ai/immunochain/ | I52: Official | J52: 4 | K52: 2026-10-04 | L52: 1.0.0
A53: N18 | B53: TenderDekho | C53: 2025-09-22 | D53: day | E53: RFP for selection of implementation agency for MPSEDC to design, develop, deploy and maintain Blockchain as a Service platform for Madhya Pradesh (Tender ID 2025_SEDC_453633_1) | F53: TenderDekho | G53: https://tenderdekho.com/tender-detail/td-1br73DkHir | I53: Secondary | J53: 2 | K53: 2026-10-04 | L53: 1.0.0
A54: N19 | B54: CoinGeek | C54: 2019-08-20 | D54: day | E54: Maharashtra to use blockchain technology to monitor services | F54: CoinGeek | G54: https://coingeek.com/maharashtra-to-use-blockchain-technology-to-monitor-services/ | I54: News | J54: 2 | K54: 2026-10-04 | L54: 1.0.0
A55: N20 | B55: Inc42 | C55: 2020-02-08 | D55: day | E55: Maharashtra launches blockchain sandbox for e-governance | F55: Inc42 | G55: https://inc42.com/buzz/maharashtra-launches-blockchain-sandbox-for-e-governance/ | I55: News | J55: 3 | K55: 2026-10-04 | L55: 1.0.0
A56: N21 | B56: ANI | C56: 2023-12-07 | D56: day | E56: Manipur Education Department embraces blockchain technology on ICP | F56: Business Standard (ANI press release) | G56: https://www.business-standard.com/content/press-releases-ani/manipur-education-department-embraces-blockchain-technology-on-icp-123120701068_1.html | I56: News | J56: 3 | K56: 2026-10-04 | L56: 1.0.0
A57: N22 | B57: Sentinel Assam | C57: 2025-04-25 | D57: day | E57: Meghalaya to launch blockchain employee data base | F57: The Sentinel | G57: https://www.sentinelassam.com/north-east-india-news/meghalaya-news/meghalaya-to-launch-blockchain-employee-data-base | I57: News | J57: 3 | K57: 2026-10-04 | L57: 1.0.0
A58: N23 | B58: CoinTrust | C58: 2024-12-11 | D58: day | E58: Odisha pioneers blockchain technology to combat gender-based violence | F58: CoinTrust | G58: https://www.cointrust.com/market-news/odisha-pioneers-blockchain-technology-to-combat-gender-based-violence | I58: News | J58: 2 | K58: 2026-10-04 | L58: 1.0.0
A59: N24 | B59: CoinTrust | C59: 2026-05-23 | D59: day | E59: India's Odisha plans AI and blockchain handloom hubs | F59: CoinTrust | G59: https://www.cointrust.com/market-news/indias-odisha-plans-ai-and-blockchain-handloom-hubs | I59: News | J59: 2 | K59: 2026-10-04 | L59: 1.0.0
A60: N25 | B60: Odisha Computer Application Centre | C60: 2023-12-14 | D60: day | E60: RFP for selection of service provider for design, development, implementation and maintenance of Blockchain as a Service platform for Odisha (OCAC-CERT-INFRA-0001-2023-23123) | F60: Government of Odisha | G60: https://odisha.gov.in/sites/default/files/2023-12/RFP-23123_14.12.2023.pdf | I60: Official | J60: 4 | K60: 2026-10-04 | L60: 1.0.0
A61: N26 | B61: PotatoPro | C61: 2019-07-30 | D61: day | E61: Punjab to introduce seed potato traceability and certification using blockchain technology | F61: PotatoPro | G61: https://www.potatopro.com/news/2019/punjab-introduce-seed-potato-tracebility-and-certification-using-blockchain-technology | I61: News | J61: 3 | K61: 2026-10-04 | L61: 1.0.0
A62: N27 | B62: Changing Tomorrow | C62: 2024-02-23 | D62: day | E62: Rajasthan government takes strides towards Digital India with landmark MoU on blockchain technology | F62: Changing Tomorrow | G62: https://changingtomorrow.in/rajasthan-government-takes-strides-towards-digital-india-with-landmark-mou-on-blockchain-technology/ | I62: News | J62: 3 | K62: 2026-10-04 | L62: 1.0.0
A63: N28 | B63: Auxesis Group | C63: 2018-09 | D63: month | E63: Rajasthan to roll out blockchain technology for land records | F63: Medium (vendor blog) | G63: https://medium.com/auxesis/rajasthan-to-roll-out-blockchain-technology-for-land-records-80d181da4daa | I63: Vendor | J63: 1 | K63: 2026-10-04 | L63: 1.0.0
A64: N29 | B64: Inc42 | C64: 2023-08-12 | D64: day | E64: Tripura introduces blockchain-based beneficiary management system to secure data | F64: Inc42 | G64: https://inc42.com/buzz/tripura-blockchain-based-beneficiary-management-system-secure-data/ | I64: News | J64: 3 | K64: 2026-10-04 | L64: 1.0.0
... A76: N41 | B76: National Informatics Centre | C76: 2023-10 | D76: month | E76: Blockchain technology in Inter-Operable Criminal Justice System for DFSL in Delhi | F76: Informatics (NIC) | G76: https://informatics.nic.in/files/websites/oct-2023/delhi-takes-a-technological-leap-in-forensic-science-by-blockchain.php | I76: Official | J76: 5 | K76: 2026-10-04 | L76: 1.0.0
A77: N42 | B77: The Pioneer | C77: 2023 | D77: year | E77: Delhi FSL to use blockchain technology for tamper-proof evidence recording | F77: The Daily Pioneer | G77: https://www.dailypioneer.com/2023/state-editions/delhi-fsl-to-use-blockchain-technology-for-tamper-proof-evidence-recording.html | I77: News | J77: 3 | K77: 2026-10-04 | L77: 1.0.0
A78: N43 | B78: Press Information Bureau (MoCAF&PD) | C78: 2026-02-26 | D78: day | E78: Government of India launches CBDC-based Digital Food Currency pilot for DBT under PMGKAY in Puducherry [Release ID 2233186] | F78: Government of India | G78: https://www.pib.gov.in/PressReleseDetailm.aspx?PRID=2233186&reg=3&lang=1 | I78: Official | J78: 5 | K78: 2026-10-04 | L78: 1.0.0
A79: N44 | B79: Upstox News | C79: 2026-08-14 | D79: day | E79: CBDC-based DBT for food subsidy rolled out in Chandigarh, Dadra & Nagar Haveli | F79: Upstox | G79: https://upstox.com/news/business-news/latest-updates/cbdc-based-dbt-for-food-subsidy-rolled-out-in-chandigarh-dadra-and-nagar-haveli/article-198689/ | I79: News | J79: 3 | K79: 2026-10-04 | L79: 1.0.0
A80: N45 | B80: Reddy E, S. V. K. | C80: 2026-09-07 | D80: day | E80: India's blockchain experiments need an exit plan [Opinion] | F80: Kashmir Observer | G80: https://kashmirobserver.net/2026/09/07/indias-blockchain-experiments-need-an-exit-plan/ | I80: Secondary | J80: 1 | K80: 2026-10-04 | L80: 1.0.0
A81: N46 | B81: Press Information Bureau (Ministry of Textiles) | C81: 2024-08-06 | D81: day | E81: Ministry of Textiles empowers ginners to produce Kasturi Cotton Bharat brand [Release ID 2042089] | F81: Government of India | G81: https://www.pib.gov.in/PressReleasePage.aspx?PRID=2042089 | I81: Official | J81: 5 | K81: 2026-10-04 | L81: 1.0.0
A82: N47 | B82: Careers360 | C82: 2022-01-25 | D82: day | E82: IIT Kanpur's blockchain project assumes limelight as PM Modi awards Bal Puraskar digitally | F82: Careers360 | G82: https://news.careers360.com/iit-kanpur-blockchain-assumes-limelight-pm-modi-takes-new-tech-award-bal-puraskar-2022-certificates-digitally | I82: News | J82: 3 | K82: 2026-10-04 | L82: 1.0.0
A83: N48 | B83: Singh, R. | C83: 2025-08-27 | D83: day | E83: IBDIC's blockchain lending tool for MSMEs clears the theme-neutral sandbox of RBI | F83: MediaNama | G83: https://www.medianama.com/2025/08/223-ibdic-blockchain-lending-tool-msme-theme-neutral-sandbox-rbi/ | I83: News | J83: 3 | K83: 2026-10-04 | L83: 1.0.0
A84: N49 | B84: FXStreet | C84: 2022-06-23 | D84: day | E84: RBI, Indian banks to pilot blockchain trade financing – report | F84: FXStreet | G84: https://www.fxstreet.com/cryptocurrencies/news/rbi-indian-banks-to-pilot-blockchain-trade-financing-report-202206230917 | I84: News | J84: 2 | K84: 2026-10-04 | L84: 1.0.0
A85: N50 | B85: CoinGeek | C85: 2023-07-09 | D85: day | E85: India to deploy blockchain for railway system 'tamper-proof' signaling | F85: CoinGeek | G85: https://coingeek.com/india-to-deploy-blockchain-for-railway-system-tamper-proof-signaling/ | I85: News | J85: 2 | K85: 2026-10-04 | L85: 1.0.0
A86: N51 | B86: Deccan Herald | C86: 2021-03-26 | D86: day | E86: Election Commission working with IIT Madras on blockchain technology for e-voting | F86: Deccan Herald | G86: https://www.deccanherald.com/india/election-commission-working-with-iit-madras-on-blockchain-technology-for-e-voting-966817.html | I86: News | J86: 3 | K86: 2026-10-04 | L86: 1.0.0
A87: N52 | B87: Vision IAS | C87: 2026-02-25 | D87: day | E87: Blockchain-based digital governance (Blockchain India Challenge) | F87: Vision IAS Current Affairs | G87: https://visionias.in/current-affairs/news-today/2026-02-25/polity-and-governance/blockchain-based-digital-governance | I87: Secondary | J87: 2 | K87: 2026-10-04 | L87: 1.0.0
A88: N53 | B88: Oracle India | C88: 2018-09-28 | D88: day | E88: NITI Aayog, Oracle, Apollo Hospitals and Strides Pharma Sciences come together to end India's growing battle against fake drug distribution [Press release] | F88: Oracle | G88: https://www.oracle.com/in/corporate/pressrelease/niti-aayog-oracle-pilot-real-drug-supply-chain-with-blockchain-iot-2018-09-28.html | I88: Vendor | J88: 1 | K88: 2026-10-04 | L88: 1.0.0
A89: N54 | B89: CoinGeek | C89: 2024 | D89: year | E89: 2024 sees India embracing blockchain for various use cases | F89: CoinGeek | G89: https://coingeek.com/2024-sees-india-embracing-blockchain-for-various-use-cases/ | I89: News | J89: 2 | K89: 2026-10-04 | L89: 1.0.0
A90: N56 | B90: e-Committee, Supreme Court of India | C90: 2022-09-23 | D90: day | E90: Final report on the vision document for Phase III of the eCourts Project | F90: Supreme Court of India (S3WaaS) | G90: https://cdnbbsr.s3waas.gov.in/s35d6646aad9bcc0be55b2c82f69750387/uploads/2024/07/202407161620804267.pdf | I90: Official | J90: 4 | K90: 2026-10-04 | L90: 1.0.0
A91: N57 | B91: LawBeat | C91: 2025-11 | D91: month | E91: 'We must dare to think of alternatives': SC urges blockchain technology reform in land registration | F91: LawBeat | G91: https://lawbeat.in/supreme-court-judgments/we-must-dare-to-think-of-alternatives-sc-urges-blockchain-technology-reform-in-land-registration-1538701 | I91: News | J91: 3 | K91: 2026-10-04 | L91: 1.0.0
A92: N58 | B92: Vision IAS | C92: 2025-11-08 | D92: day | E92: Supreme Court raises concern over India's land registration system in Samiullah v. State of Bihar | F92: Vision IAS Current Affairs | G92: https://visionias.in/current-affairs/news-today/2025-11-08/polity-and-governance/supreme-court-raises-concern-over-indias-land-registration-system-in-samiullah-v-state-of-bihar | I92: Secondary | J92: 2 | K92: 2026-10-04 | L92: 1.0.0
A93: N59 | B93: Supreme Court of India | C93: 2025-11-07 | D93: day | E93: Samiullah v. The State of Bihar & Ors., 2025 INSC 1292 (P.S. Narasimha & Joymalya Bagchi, JJ.) [Judgment text via LawCurb] | F93: LawCurb | G93: https://www.lawcurb.in/judgements/samiullah-vs-the-state-of-bihar-&-ors-2025-insc-1292 | I93: Official | J93: 4 | K93: 2026-10-04 | L93: 1.0.0
A94: D01 | B94: Nagware, K. | C94: 2025-12 | D94: month | E94: Blockchain adoption and opportunities in India [Presentation slides, IIT Madras; incl. NBF dashboard 'as on 14-12-2025'] | F94: Hyperledger India / LF Decentralized Trust | H94: User-provided PDF (no public URL) | I94: Secondary | J94: 2 | K94: 2026-10-04 | L94: 1.0.0
A95: D02 | B95: Chakraborty, S. | C95: 2025-12 | D95: month | E95: Interoperability in the age of Web 3.0 [Presentation slides] | F95: IIT Kharagpur, Ubiquitous Networked Systems Lab | H95: User-provided PDF (no public URL) | I95: Secondary | J95: 2 | K95: 2026-10-04 | L95: 1.0.0
A96: N60 | B96: MeitY – National Blockchain Framework portal | E96: Domicile certificate storage and verification system – online genuinity check of certificates through blockchain (J&K; C-DAC Mumbai) | F96: Government of India | G96: https://blockchain.meity.gov.in/index.php/success-stories/12-domicile-certificate-storage-and-verification-system-online-genuinity-check-of-certificates-is-now-possible-through-blockchain | I96: Official | J96: 5 | K96: 2026-10-04 | L96: 1.0.0
A97: N61 | B97: MeitY – National Blockchain Framework portal | E97: Blockchain based Property Registration Management System (Shamshabad, Telangana; C-DAC Hyderabad) | F97: Government of India | G97: https://blockchain.meity.gov.in/index.php/success-stories/13-blockchain-based-property-registration-management-system | I97: Official | J97: 5 | K97: 2026-10-04 | L97: 1.0.0
A98: N62 | B98: MeitY – National Blockchain Framework portal | E98: eVoting – ensuring vote data immutability through blockchain (Telangana State Election Commission; C-DAC) | F98: Government of India | G98: https://blockchain.meity.gov.in/index.php/success-stories/11-evoting-ensuring-vote-data-immutability-through-blockchain | I98: Official | J98: 5 | K98: 2026-10-04 | L98: 1.0.0
A99: N63 | B99: Press Information Bureau (MeitY) | C99: 2026-02-23 | D99: day | E99: MeitY launches Blockchain India Challenge to promote blockchain-based digital governance solutions [Release ID 2232339] | F99: Government of India | G99: https://www.pib.gov.in/PressReleasePage.aspx?PRID=2232339 | I99: Official | J99: 4 | K99: 2026-10-04 | L99: 1.0.0
A100: N64 | B100: Cointelegraph | C100: 2025-01-13 | D100: day | E100: Indian Railways to issue NFT tickets on Polygon for rare festival | F100: Cointelegraph | G100: https://cointelegraph.com/news/indian-railways-nft-tickets-mahakumbh-mela | I100: News | J100: 2 | K100: 2026-10-04 | L100: 1.0.0
A101: N65 | B101: Inc42 | C101: 2021-05 | D101: month | E101: Maharashtra govt onboards blockchain startup Print2Block for issuing Covid-19 test certificates | F101: Inc42 | G101: https://inc42.com/buzz/maharashtra-onboards-blockchain-startup-print2block-for-issuing-covid-19-test-certificates/ | I101: News | J101: 3 | K101: 2026-10-04 | L101: 1.0.0
A102: N66 | B102: Dept of Disaster Management, Relief & Rehabilitation, Govt of Maharashtra | C102: 2021 | D102: year | E102: COVID-19 test report – blockchain verification portal (sample record) | F102: Government of Maharashtra (MahaOnline) | G102: https://block.dmrr.mahaonline.gov.in/report?id=2e63e5ad7e1ae7f4fa8568e8cdb49dec4ac701f9469e7289ba84d1ddb2dc385b | I102: Official | J102: 4 | K102: 2026-10-04 | L102: 1.0.0
A103: N67 | B103: Business Standard | C103: 2025-10-09 | D103: day | E103: Fadnavis unveils Maharashtra's ₹50 trillion asset tokenisation plan | F103: Business Standard | G103: https://www.business-standard.com/finance/news/maharashtra-to-launch-asset-tokenisation-framework-says-fadnavis-125100901370_1.html | I103: News | J103: 3 | K103: 2026-10-04 | L103: 1.0.0
A104: N68 | B104: The Tribune (press release) | C104: 2025-12-04 | D104: day | E104: Maharashtra takes major leap towards blockchain governance with MoU signed with Infraledger Labs | F104: The Tribune | G104: https://www.tribuneindia.com/news/business/maharashtra-takes-major-leap-towards-blockchain-governance-with-mou-signed-with-infraledger-labs/amp/?utm=relatedarticles | I104: News | J104: 3 | K104: 2026-10-04 | L104: 1.0.0
A105: N69 | B105: CoinGeek | C105: 2025-10-17 | D105: day | E105: RBI eyes market transformation with CBDC-based tokenization | F105: CoinGeek | G105: https://coingeek.com/rbi-eyes-market-transformation-with-cbdc-based-tokenization/ | I105: News | J105: 2 | K105: 2026-10-04 | L105: 1.0.0
A106: N70 | B106: The Crypto Basic | C106: 2026-09-11 | D106: day | E106: India launches $107 million tokenised bond pilot linked to RBI wholesale CBDC | F106: The Crypto Basic | G106: https://thecryptobasic.com/2026/09/11/india-launches-107-million-tokenised-bond-pilot-linked-to-rbi-wholesale-cbdc/ | I106: News | J106: 2 | K106: 2026-10-04 | L106: 1.0.0
A107: N71 | B107: NewKerala (IANS) | C107: 2026-05-29 | D107: day | E107: RBI expands e-rupee pilots, starts tokenised credit deposit trial (RBI Annual Report FY26) | F107: NewKerala | G107: https://www.newkerala.com/news/a/rbi-expands-e-rupee-pilots-starts-tokenised-credit-deposit-979.htm | I107: News | J107: 3 | K107: 2026-10-04 | L107: 1.0.0
A108: N72 | B108: Business Standard | C108: 2022-12-01 | D108: day | E108: DigiYatra data will be saved in decentralised manner, says Scindia | F108: Business Standard | G108: https://www.business-standard.com/article/current-affairs/digiyatra-data-will-be-saved-in-decentralised-manner-says-scindia-122120100546_1.html | I108: News | J108: 3 | K108: 2026-10-04 | L108: 1.0.0
A109: N73 | B109: Spydra | E109: GS1 / Mother Dairy ghee traceability case study | F109: Spydra (vendor) | G109: https://www.spydra.app/gs1-maahi-ghee-traceability-case-study | I109: Vendor | J109: 1 | K109: 2026-10-04 | L109: 1.0.0
A110: N74 | B110: National Dairy Development Board | C110: 2024-10-22 | D110: day | E110: Shri Amit Shah launched farmer-oriented activities during NDDB's Diamond Jubilee Year | F110: NDDB | G110: https://www.nddb.coop/node/2436 | I110: Official | J110: 4 | K110: 2026-10-04 | L110: 1.0.0
A111: N75 | B111: IIT Kanpur | C111: 2021-11-18 | D111: day | E111: IIT Kanpur-backed CRUBN to assist Karnataka Government in developing key blockchain network across the country | F111: IIT Kanpur | G111: https://www.iitk.ac.in/crubn-partners-with-centre-for-smart-governance | I111: Official | J111: 4 | K111: 2026-10-04 | L111: 1.0.0
...

Sheet Project sources
A1: project_id | B1: source_id | C1: role
A2: C01 | B2: B01 | C2: citation
A3: C01 | B3: D01 | C3: citation
A4: C01 | B4: R01 | C4: citation
A5: C01 | B5: R34 | C5: citation
A6: C01 | B6: R02 | C6: additional
A7: C01 | B7: W001 | C7: additional
A8: C01 | B8: W002 | C8: additional
A9: C02 | B9: R01 | C9: citation
A10: C02 | B10: R34 | C10: event evidence
A11: C02 | B11: W001 | C11: additional
A12: C02 | B12: W003 | C12: additional
... A501: S79 | B501: W183 | C501: citation

Sheet NIC snapshots
A1: snapshot_date | B1: source_id | C1: level | D1: application | E1: chain_product | F1: unit | G1: unit_as_published | H1: project_id | I1: metric | J1: value | K1: note
A2: 2024-07-23 | B2: B12 | C2: platform | H2: C01 | I2: departments | J2: 19
A3: 2024-07-23 | B3: B12 | C3: platform | H3: C01 | I3: documents | J3: 81192971
A4: 2024-07-23 | B4: B12 | C4: platform | H4: C01 | I4: organisations_states | J4: 9
A5: 2024-07-23 | B5: B12 | C5: platform | H5: C01 | I5: products | J5: 5
A6: 2024-07-23 | B6: B12 | C6: application | D6: Central Board of Secondary Education | E6: Certificate Chain | I6: documents | J6: 17124672
A7: 2024-07-23 | B7: B12 | C7: application | D7: Certificate Chain | E7: Certificate Chain | I7: documents | J7: 29733
A8: 2024-07-23 | B8: B12 | C8: application | D8: Document Chain | E8: Document Chain | I8: documents | J8: 29083400
A9: 2024-07-23 | B9: B12 | C9: application | D9: Drug logistics | E9: Logistics Chain | I9: documents | J9: 2675479
A10: 2024-07-23 | B10: B12 | C10: application | D10: Judiciary Chain | E10: Judiciary Chain | I10: documents | J10: 97
A11: 2024-07-23 | B11: B12 | C11: application | D11: Property Chain | E11: Property Chain | I11: documents | J11: 19659090
A12: 2024-07-23 | B12: B12 | C12: application | D12: SSLC & PUC | E12: Certificate Chain | I12: documents | J12: 12620500
A13: 2024-07-23 | B13: B12 | C13: department | D13: Central Board of Secondary Education | E13: Certificate Chain | F13: Central Board of Secondary Education | G13: Central Board of Secondary Education | H13: O14 | I13: documents | J13: 17124672 | K13: application total (single department)
A14: 2024-07-23 | B14: B12 | C14: department | D14: Certificate Chain | E14: Certificate Chain | F14: Chhattisgarh – Indira Gandhi Krishi Vishwavidyalaya, Raipur | G14: Chhattisgarh – Indira Gandhi Krishi Vishwavidyalaya, Raipur | H14: S12 | I14: documents | J14: 1349
